Workbook

Sheet Users
A1: Name | B1: UsersId | C1: Email | D1: FirstName | E1: LastName | F1: Role | G1: FullName
A2: =C2 -> alice@example.com | B2: alice@example.com | C2: alice@example.com | D2: Alice | E2: Anderson | F2: admin | G2: =_xlfn.CONCAT(E2, ", ", D2) -> Anderson, Alice
A3: =C3 -> bob@example.com | B3: bob@example.com | C3: bob@example.com | D3: Bob | E3: Baker | F3: viewer | G3: =_xlfn.CONCAT(E3, ", ", D3) -> Baker, Bob

Sheet Customers
A1: Name | B1: CustomersId | C1: Email | D1: FirstName | E1: LastName | F1: FullName | G1: LifetimeSales | H1: UnpaidOrderCount | I1: LargeOrderCount | J1: IsVIP
A2: =C2 -> ada.lovelace@analytical.engine | B2: ada.lovelace@analytical.engine | C2: ada.lovelace@analytical.engine | D2: Ada | E2: Lovelace | F2: =_xlfn.CONCAT(E2, ", ", D2) -> Lovelace, Ada | G2: =SUMIFS(Orders!P2:P999,Orders!E2:E999, A2) -> 50 | H2: =SUMIFS(Orders!N2:N999,Orders!E2:E999, A2) -> 0 | I2: {=SUMIFS(Orders!J2:J999*0+1,Orders!E2:E999, A2,Orders!J2:J999, ">500")} -> 1 | J2: =AND(G2 > 1500, H2 = 0) -> FALSE
A3: =C3 -> grace.hopper@nautical.mil | B3: grace.hopper@nautical.mil | C3: grace.hopper@nautical.mil | D3: Grace | E3: Hopper | F3: =_xlfn.CONCAT(E3, ", ", D3) -> Hopper, Grace | G3: =SUMIFS(Orders!P2:P999,Orders!E2:E999, A3) -> 1820.49 | H3: =SUMIFS(Orders!N2:N999,Orders!E2:E999, A3) -> 1 | I3: {=SUMIFS(Orders!J2:J999*0+1,Orders!E2:E999, A3,Orders!J2:J999, ">500")} -> 1 | J3: =AND(G3 > 1500, H3 = 0) -> FALSE
A4: =C4 -> alan.turing@bletchley.uk | B4: alan.turing@bletchley.uk | C4: alan.turing@bletchley.uk | D4: Alan | E4: Turing | F4: =_xlfn.CONCAT(E4, ", ", D4) -> Turing, Alan | G4: =SUMIFS(Orders!P2:P999,Orders!E2:E999, A4) -> 99 | H4: =SUMIFS(Orders!N2:N999,Orders!E2:E999, A4) -> 0 | I4: {=SUMIFS(Orders!J2:J999*0+1,Orders!E2:E999, A4,Orders!J2:J999, ">500")} -> 0 | J4: =AND(G4 > 1500, H4 = 0) -> FALSE
A5: =C5 -> katherine.johnson@nasa.gov | B5: katherine.johnson@nasa.gov | C5: katherine.johnson@nasa.gov | D5: Katherine | E5: Johnson | F5: =_xlfn.CONCAT(E5, ", ", D5) -> Johnson, Katherine | G5: =SUMIFS(Orders!P2:P999,Orders!E2:E999, A5) -> 1152 | H5: =SUMIFS(Orders!N2:N999,Orders!E2:E999, A5) -> 1 | I5: {=SUMIFS(Orders!J2:J999*0+1,Orders!E2:E999, A5,Orders!J2:J999, ">500")} -> 2 | J5: =AND(G5 > 1500, H5 = 0) -> FALSE
A6: =C6 -> linus.torvalds@kernel.org | B6: linus.torvalds@kernel.org | C6: linus.torvalds@kernel.org | D6: Linus | E6: Torvalds | F6: =_xlfn.CONCAT(E6, ", ", D6) -> Torvalds, Linus | G6: =SUMIFS(Orders!P2:P999,Orders!E2:E999, A6) -> 2580 | H6: =SUMIFS(Orders!N2:N999,Orders!E2:E999, A6) -> 0 | I6: {=SUMIFS(Orders!J2:J999*0+1,Orders!E2:E999, A6,Orders!J2:J999, ">500")} -> 1 | J6: =AND(G6 > 1500, H6 = 0) -> TRUE

Sheet Orders
A1: Name | B1: OrdersId | C1: OrderNumber | D1: OrderDate | E1: Customer | F1: CustomerFirstName | G1: CustomerLastName | H1: CustomerFullName | I1: CustomerEmail | J1: Total | K1: AmountPaid | L1: Balance | M1: IsPaid | N1: UnpaidFlag | O1: IsRecent | P1: RecentTotal
A2: =C2 -> ORD-1001 | B2: ORD-1001 | C2: ORD-1001 | D2: 46037.25 | E2: ada.lovelace@analytical.engine | F2: =INDEX(Customers!D2:D999, MATCH(E2,Customers!B2:B999, 0)) -> Ada | G2: =INDEX(Customers!E2:E999, MATCH(E2,Customers!B2:B999, 0)) -> Lovelace | H2: =INDEX(Customers!F2:F999, MATCH(E2,Customers!B2:B999, 0)) -> Lovelace, Ada | I2: =INDEX(Customers!C2:C999, MATCH(E2,Customers!B2:B999, 0)) -> ada.lovelace@analytical.engine | J2: 250 | K2: =SUMIFS(Payments!F2:F999,Payments!D2:D999, A2) -> 250 | L2: =J2 - K2 -> 0 | M2: =L2 <= 0 -> TRUE | N2: =IF(M2, 0, 1) -> 0 | O2: =(TODAY() - D2) <= 90 -> FALSE | P2: =IF(O2, J2, 0) -> 0
A3: =C3 -> ORD-1002 | B3: ORD-1002 | C3: ORD-1002 | D3: 46056.25 | E3: ada.lovelace@analytical.engine | F3: =INDEX(Customers!D2:D999, MATCH(E3,Customers!B2:B999, 0)) -> Ada | G3: =INDEX(Customers!E2:E999, MATCH(E3,Customers!B2:B999, 0)) -> Lovelace | H3: =INDEX(Customers!F2:F999, MATCH(E3,Customers!B2:B999, 0)) -> Lovelace, Ada | I3: =INDEX(Customers!C2:C999, MATCH(E3,Customers!B2:B999, 0)) -> ada.lovelace@analytical.engine | J3: 875 | K3: =SUMIFS(Payments!F2:F999,Payments!D2:D999, A3) -> 875 | L3: =J3 - K3 -> 0 | M3: =L3 <= 0 -> TRUE | N3: =IF(M3, 0, 1) -> 0 | O3: =(TODAY() - D3) <= 90 -> FALSE | P3: =IF(O3, J3, 0) -> 0
A4: =C4 -> ORD-1003 | B4: ORD-1003 | C4: ORD-1003 | D4: 46073.25 | E4: grace.hopper@nautical.mil | F4: =INDEX(Customers!D2:D999, MATCH(E4,Customers!B2:B999, 0)) -> Grace | G4: =INDEX(Customers!E2:E999, MATCH(E4,Customers!B2:B999, 0)) -> Hopper | H4: =INDEX(Customers!F2:F999, MATCH(E4,Customers!B2:B999, 0)) -> Hopper, Grace | I4: =INDEX(Customers!C2:C999, MATCH(E4,Customers!B2:B999, 0)) -> grace.hopper@nautical.mil | J4: 1499.99 | K4: =SUMIFS(Payments!F2:F999,Payments!D2:D999, A4) -> 1000 | L4: =J4 - K4 -> 499.99 | M4: =L4 <= 0 -> FALSE | N4: =IF(M4, 0, 1) -> 1 | O4: =(TODAY() - D4) <= 90 -> TRUE | P4: =IF(O4, J4, 0) -> 1499.99
A5: =C5 -> ORD-1004 | B5: ORD-1004 | C5: ORD-1004 | D5: 46091.208 | E5: grace.hopper@nautical.mil | F5: =INDEX(Customers!D2:D999, MATCH(E5,Customers!B2:B999, 0)) -> Grace | G5: =INDEX(Customers!E2:E999, MATCH(E5,Customers!B2:B999, 0)) -> Hopper | H5: =INDEX(Customers!F2:F999, MATCH(E5,Customers!B2:B999, 0)) -> Hopper, Grace | I5: =INDEX(Customers!C2:C999, MATCH(E5,Customers!B2:B999, 0)) -> grace.hopper@nautical.mil | J5: 320.5 | K5: =SUMIFS(Payments!F2:F999,Payments!D2:D999, A5) -> 320.5 | L5: =J5 - K5 -> 0 | M5: =L5 <= 0 -> TRUE | N5: =IF(M5, 0, 1) -> 0 | O5: =(TODAY() - D5) <= 90 -> TRUE | P5: =IF(O5, J5, 0) -> 320.5
A6: =C6 -> ORD-1005 | B6: ORD-1005 | C6: ORD-1005 | D6: 46103.208 | E6: alan.turing@bletchley.uk | F6: =INDEX(Customers!D2:D999, MATCH(E6,Customers!B2:B999, 0)) -> Alan | G6: =INDEX(Customers!E2:E999, MATCH(E6,Customers!B2:B999, 0)) -> Turing | H6: =INDEX(Customers!F2:F999, MATCH(E6,Customers!B2:B999, 0)) -> Turing, Alan | I6: =INDEX(Customers!C2:C999, MATCH(E6,Customers!B2:B999, 0)) -> alan.turing@bletchley.uk | J6: 99 | K6: =SUMIFS(Payments!F2:F999,Payments!D2:D999, A6) -> 99 | L6: =J6 - K6 -> 0 | M6: =L6 <= 0 -> TRUE | N6: =IF(M6, 0, 1) -> 0 | O6: =(TODAY() - D6) <= 90 -> TRUE | P6: =IF(O6, J6, 0) -> 99
A7: =C7 -> ORD-1006 | B7: ORD-1006 | C7: ORD-1006 | D7: 46113.208 | E7: katherine.johnson@nasa.gov | F7: =INDEX(Customers!D2:D999, MATCH(E7,Customers!B2:B999, 0)) -> Katherine | G7: =INDEX(Customers!E2:E999, MATCH(E7,Customers!B2:B999, 0)) -> Johnson | H7: =INDEX(Customers!F2:F999, MATCH(E7,Customers!B2:B999, 0)) -> Johnson, Katherine | I7: =INDEX(Customers!C2:C999, MATCH(E7,Customers!B2:B999, 0)) -> katherine.johnson@nasa.gov | J7: 540 | K7: =SUMIFS(Payments!F2:F999,Payments!D2:D999, A7) -> 540 | L7: =J7 - K7 -> 0 | M7: =L7 <= 0 -> TRUE | N7: =IF(M7, 0, 1) -> 0 | O7: =(TODAY() - D7) <= 90 -> TRUE | P7: =IF(O7, J7, 0) -> 540
A8: =C8 -> ORD-1007 | B8: ORD-1007 | C8: ORD-1007 | D8: 46124.208 | E8: katherine.johnson@nasa.gov | F8: =INDEX(Customers!D2:D999, MATCH(E8,Customers!B2:B999, 0)) -> Katherine | G8: =INDEX(Customers!E2:E999, MATCH(E8,Customers!B2:B999, 0)) -> Johnson | H8: =INDEX(Customers!F2:F999, MATCH(E8,Customers!B2:B999, 0)) -> Johnson, Katherine | I8: =INDEX(Customers!C2:C999, MATCH(E8,Customers!B2:B999, 0)) -> katherine.johnson@nasa.gov | J8: 612 | K8: =SUMIFS(Payments!F2:F999,Payments!D2:D999, A8) -> 0 | L8: =J8 - K8 -> 612 | M8: =L8 <= 0 -> FALSE | N8: =IF(M8, 0, 1) -> 1 | O8: =(TODAY() - D8) <= 90 -> TRUE | P8: =IF(O8, J8, 0) -> 612
A9: =C9 -> ORD-1008 | B9: ORD-1008 | C9: ORD-1008 | D9: 46140.208 | E9: linus.torvalds@kernel.org | F9: =INDEX(Customers!D2:D999, MATCH(E9,Customers!B2:B999, 0)) -> Linus | G9: =INDEX(Customers!E2:E999, MATCH(E9,Customers!B2:B999, 0)) -> Torvalds | H9: =INDEX(Customers!F2:F999, MATCH(E9,Customers!B2:B999, 0)) -> Torvalds, Linus | I9: =INDEX(Customers!C2:C999, MATCH(E9,Customers!B2:B999, 0)) -> linus.torvalds@kernel.org | J9: 2400 | K9: =SUMIFS(Payments!F2:F999,Payments!D2:D999, A9) -> 2400 | L9: =J9 - K9 -> 0 | M9: =L9 <= 0 -> TRUE | N9: =IF(M9, 0, 1) -> 0 | O9: =(TODAY() - D9) <= 90 -> TRUE | P9: =IF(O9, J9, 0) -> 2400
A10: =C10 -> ORD-1009 | B10: ORD-1009 | C10: ORD-1009 | D10: 46147.208 | E10: linus.torvalds@kernel.org | F10: =INDEX(Customers!D2:D999, MATCH(E10,Customers!B2:B999, 0)) -> Linus | G10: =INDEX(Customers!E2:E999, MATCH(E10,Customers!B2:B999, 0)) -> Torvalds | H10: =INDEX(Customers!F2:F999, MATCH(E10,Customers!B2:B999, 0)) -> Torvalds, Linus | I10: =INDEX(Customers!C2:C999, MATCH(E10,Customers!B2:B999, 0)) -> linus.torvalds@kernel.org | J10: 180 | K10: =SUMIFS(Payments!F2:F999,Payments!D2:D999, A10) -> 180 | L10: =J10 - K10 -> 0 | M10: =L10 <= 0 -> TRUE | N10: =IF(M10, 0, 1) -> 0 | O10: =(TODAY() - D10) <= 90 -> TRUE | P10: =IF(O10, J10, 0) -> 180
A11: =C11 -> ORD-1010 | B11: ORD-1010 | C11: ORD-1010 | D11: 46157.208 | E11: ada.lovelace@analytical.engine | F11: =INDEX(Customers!D2:D999, MATCH(E11,Customers!B2:B999, 0)) -> Ada | G11: =INDEX(Customers!E2:E999, MATCH(E11,Customers!B2:B999, 0)) -> Lovelace | H11: =INDEX(Customers!F2:F999, MATCH(E11,Customers!B2:B999, 0)) -> Lovelace, Ada | I11: =INDEX(Customers!C2:C999, MATCH(E11,Customers!B2:B999, 0)) -> ada.lovelace@analytical.engine | J11: 50 | K11: =SUMIFS(Payments!F2:F999,Payments!D2:D999, A11) -> 50 | L11: =J11 - K11 -> 0 | M11: =L11 <= 0 -> TRUE | N11: =IF(M11, 0, 1) -> 0 | O11: =(TODAY() - D11) <= 90 -> TRUE | P11: =IF(O11, J11, 0) -> 50

Sheet Payments
A1: Name | B1: PaymentsId | C1: PaymentNumber | D1: OrderId | E1: PaymentDate | F1: Amount | G1: Method | H1: OrderNumber | I1: OrderDate | J1: OrderTotal | K1: OrderAmountPaid | L1: OrderBalance | M1: OrderIsPaid | N1: OrderCustomer | O1: CustomerFullName | P1: CustomerEmail
A2: =C2 -> PMT-2001 | B2: PMT-2001 | C2: PMT-2001 | D2: ORD-1001 | E2: 46038.25 | F2: 250 | G2: card | H2: =INDEX(Orders!C2:C999, MATCH(D2,Orders!B2:B999, 0)) -> ORD-1001 | I2: =INDEX(Orders!D2:D999, MATCH(D2,Orders!B2:B999, 0)) -> 46037.25 | J2: =INDEX(Orders!J2:J999, MATCH(D2,Orders!B2:B999, 0)) -> 250 | K2: =INDEX(Orders!K2:K999, MATCH(D2,Orders!B2:B999, 0)) -> 250 | L2: =INDEX(Orders!L2:L999, MATCH(D2,Orders!B2:B999, 0)) -> 0 | M2: =INDEX(Orders!M2:M999, MATCH(D2,Orders!B2:B999, 0)) -> TRUE | N2: =INDEX(Orders!E2:E999, MATCH(D2,Orders!B2:B999, 0)) -> ada.lovelace@analytical.engine | O2: =INDEX(Orders!H2:H999, MATCH(D2,Orders!B2:B999, 0)) -> Lovelace, Ada | P2: =INDEX(Orders!I2:I999, MATCH(D2,Orders!B2:B999, 0)) -> ada.lovelace@analytical.engine
A3: =C3 -> PMT-2002 | B3: PMT-2002 | C3: PMT-2002 | D3: ORD-1002 | E3: 46057.25 | F3: 500 | G3: card | H3: =INDEX(Orders!C2:C999, MATCH(D3,Orders!B2:B999, 0)) -> ORD-1002 | I3: =INDEX(Orders!D2:D999, MATCH(D3,Orders!B2:B999, 0)) -> 46056.25 | J3: =INDEX(Orders!J2:J999, MATCH(D3,Orders!B2:B999, 0)) -> 875 | K3: =INDEX(Orders!K2:K999, MATCH(D3,Orders!B2:B999, 0)) -> 875 | L3: =INDEX(Orders!L2:L999, MATCH(D3,Orders!B2:B999, 0)) -> 0 | M3: =INDEX(Orders!M2:M999, MATCH(D3,Orders!B2:B999, 0)) -> TRUE | N3: =INDEX(Orders!E2:E999, MATCH(D3,Orders!B2:B999, 0)) -> ada.lovelace@analytical.engine | O3: =INDEX(Orders!H2:H999, MATCH(D3,Orders!B2:B999, 0)) -> Lovelace, Ada | P3: =INDEX(Orders!I2:I999, MATCH(D3,Orders!B2:B999, 0)) -> ada.lovelace@analytical.engine
A4: =C4 -> PMT-2003 | B4: PMT-2003 | C4: PMT-2003 | D4: ORD-1002 | E4: 46071.25 | F4: 375 | G4: ach | H4: =INDEX(Orders!C2:C999, MATCH(D4,Orders!B2:B999, 0)) -> ORD-1002 | I4: =INDEX(Orders!D2:D999, MATCH(D4,Orders!B2:B999, 0)) -> 46056.25 | J4: =INDEX(Orders!J2:J999, MATCH(D4,Orders!B2:B999, 0)) -> 875 | K4: =INDEX(Orders!K2:K999, MATCH(D4,Orders!B2:B999, 0)) -> 875 | L4: =INDEX(Orders!L2:L999, MATCH(D4,Orders!B2:B999, 0)) -> 0 | M4: =INDEX(Orders!M2:M999, MATCH(D4,Orders!B2:B999, 0)) -> TRUE | N4: =INDEX(Orders!E2:E999, MATCH(D4,Orders!B2:B999, 0)) -> ada.lovelace@analytical.engine | O4: =INDEX(Orders!H2:H999, MATCH(D4,Orders!B2:B999, 0)) -> Lovelace, Ada | P4: =INDEX(Orders!I2:I999, MATCH(D4,Orders!B2:B999, 0)) -> ada.lovelace@analytical.engine
A5: =C5 -> PMT-2004 | B5: PMT-2004 | C5: PMT-2004 | D5: ORD-1003 | E5: 46074.25 | F5: 1000 | G5: wire | H5: =INDEX(Orders!C2:C999, MATCH(D5,Orders!B2:B999, 0)) -> ORD-1003 | I5: =INDEX(Orders!D2:D999, MATCH(D5,Orders!B2:B999, 0)) -> 46073.25 | J5: =INDEX(Orders!J2:J999, MATCH(D5,Orders!B2:B999, 0)) -> 1499.99 | K5: =INDEX(Orders!K2:K999, MATCH(D5,Orders!B2:B999, 0)) -> 1000 | L5: =INDEX(Orders!L2:L999, MATCH(D5,Orders!B2:B999, 0)) -> 499.99 | M5: =INDEX(Orders!M2:M999, MATCH(D5,Orders!B2:B999, 0)) -> FALSE | N5: =INDEX(Orders!E2:E999, MATCH(D5,Orders!B2:B999, 0)) -> grace.hopper@nautical.mil | O5: =INDEX(Orders!H2:H999, MATCH(D5,Orders!B2:B999, 0)) -> Hopper, Grace | P5: =INDEX(Orders!I2:I999, MATCH(D5,Orders!B2:B999, 0)) -> grace.hopper@nautical.mil
A6: =C6 -> PMT-2005 | B6: PMT-2005 | C6: PMT-2005 | D6: ORD-1005 | E6: 46104.208 | F6: 99 | G6: cash | H6: =INDEX(Orders!C2:C999, MATCH(D6,Orders!B2:B999, 0)) -> ORD-1005 | I6: =INDEX(Orders!D2:D999, MATCH(D6,Orders!B2:B999, 0)) -> 46103.208 | J6: =INDEX(Orders!J2:J999, MATCH(D6,Orders!B2:B999, 0)) -> 99 | K6: =INDEX(Orders!K2:K999, MATCH(D6,Orders!B2:B999, 0)) -> 99 | L6: =INDEX(Orders!L2:L999, MATCH(D6,Orders!B2:B999, 0)) -> 0 | M6: =INDEX(Orders!M2:M999, MATCH(D6,Orders!B2:B999, 0)) -> TRUE | N6: =INDEX(Orders!E2:E999, MATCH(D6,Orders!B2:B999, 0)) -> alan.turing@bletchley.uk | O6: =INDEX(Orders!H2:H999, MATCH(D6,Orders!B2:B999, 0)) -> Turing, Alan | P6: =INDEX(Orders!I2:I999, MATCH(D6,Orders!B2:B999, 0)) -> alan.turing@bletchley.uk
A7: =C7 -> PMT-2006 | B7: PMT-2006 | C7: PMT-2006 | D7: ORD-1006 | E7: 46114.208 | F7: 540 | G7: check | H7: =INDEX(Orders!C2:C999, MATCH(D7,Orders!B2:B999, 0)) -> ORD-1006 | I7: =INDEX(Orders!D2:D999, MATCH(D7,Orders!B2:B999, 0)) -> 46113.208 | J7: =INDEX(Orders!J2:J999, MATCH(D7,Orders!B2:B999, 0)) -> 540 | K7: =INDEX(Orders!K2:K999, MATCH(D7,Orders!B2:B999, 0)) -> 540 | L7: =INDEX(Orders!L2:L999, MATCH(D7,Orders!B2:B999, 0)) -> 0 | M7: =INDEX(Orders!M2:M999, MATCH(D7,Orders!B2:B999, 0)) -> TRUE | N7: =INDEX(Orders!E2:E999, MATCH(D7,Orders!B2:B999, 0)) -> katherine.johnson@nasa.gov | O7: =INDEX(Orders!H2:H999, MATCH(D7,Orders!B2:B999, 0)) -> Johnson, Katherine | P7: =INDEX(Orders!I2:I999, MATCH(D7,Orders!B2:B999, 0)) -> katherine.johnson@nasa.gov
A8: =C8 -> PMT-2007 | B8: PMT-2007 | C8: PMT-2007 | D8: ORD-1008 | E8: 46141.208 | F8: 1200 | G8: wire | H8: =INDEX(Orders!C2:C999, MATCH(D8,Orders!B2:B999, 0)) -> ORD-1008 | I8: =INDEX(Orders!D2:D999, MATCH(D8,Orders!B2:B999, 0)) -> 46140.208 | J8: =INDEX(Orders!J2:J999, MATCH(D8,Orders!B2:B999, 0)) -> 2400 | K8: =INDEX(Orders!K2:K999, MATCH(D8,Orders!B2:B999, 0)) -> 2400 | L8: =INDEX(Orders!L2:L999, MATCH(D8,Orders!B2:B999, 0)) -> 0 | M8: =INDEX(Orders!M2:M999, MATCH(D8,Orders!B2:B999, 0)) -> TRUE | N8: =INDEX(Orders!E2:E999, MATCH(D8,Orders!B2:B999, 0)) -> linus.torvalds@kernel.org | O8: =INDEX(Orders!H2:H999, MATCH(D8,Orders!B2:B999, 0)) -> Torvalds, Linus | P8: =INDEX(Orders!I2:I999, MATCH(D8,Orders!B2:B999, 0)) -> linus.torvalds@kernel.org
A9: =C9 -> PMT-2008 | B9: PMT-2008 | C9: PMT-2008 | D9: ORD-1008 | E9: 46152.208 | F9: 1200 | G9: wire | H9: =INDEX(Orders!C2:C999, MATCH(D9,Orders!B2:B999, 0)) -> ORD-1008 | I9: =INDEX(Orders!D2:D999, MATCH(D9,Orders!B2:B999, 0)) -> 46140.208 | J9: =INDEX(Orders!J2:J999, MATCH(D9,Orders!B2:B999, 0)) -> 2400 | K9: =INDEX(Orders!K2:K999, MATCH(D9,Orders!B2:B999, 0)) -> 2400 | L9: =INDEX(Orders!L2:L999, MATCH(D9,Orders!B2:B999, 0)) -> 0 | M9: =INDEX(Orders!M2:M999, MATCH(D9,Orders!B2:B999, 0)) -> TRUE | N9: =INDEX(Orders!E2:E999, MATCH(D9,Orders!B2:B999, 0)) -> linus.torvalds@kernel.org | O9: =INDEX(Orders!H2:H999, MATCH(D9,Orders!B2:B999, 0)) -> Torvalds, Linus | P9: =INDEX(Orders!I2:I999, MATCH(D9,Orders!B2:B999, 0)) -> linus.torvalds@kernel.org
A10: =C10 -> PMT-2009 | B10: PMT-2009 | C10: PMT-2009 | D10: ORD-1010 | E10: 46158.208 | F10: 50 | G10: card | H10: =INDEX(Orders!C2:C999, MATCH(D10,Orders!B2:B999, 0)) -> ORD-1010 | I10: =INDEX(Orders!D2:D999, MATCH(D10,Orders!B2:B999, 0)) -> 46157.208 | J10: =INDEX(Orders!J2:J999, MATCH(D10,Orders!B2:B999, 0)) -> 50 | K10: =INDEX(Orders!K2:K999, MATCH(D10,Orders!B2:B999, 0)) -> 50 | L10: =INDEX(Orders!L2:L999, MATCH(D10,Orders!B2:B999, 0)) -> 0 | M10: =INDEX(Orders!M2:M999, MATCH(D10,Orders!B2:B999, 0)) -> TRUE | N10: =INDEX(Orders!E2:E999, MATCH(D10,Orders!B2:B999, 0)) -> ada.lovelace@analytical.engine | O10: =INDEX(Orders!H2:H999, MATCH(D10,Orders!B2:B999, 0)) -> Lovelace, Ada | P10: =INDEX(Orders!I2:I999, MATCH(D10,Orders!B2:B999, 0)) -> ada.lovelace@analytical.engine
A11: =C11 -> PMT-525034 | B11: PMT-525034 | C11: PMT-525034 | D11: ORD-1004 | E11: 46162.208 | F11: 320.5 | G11: card | H11: =INDEX(Orders!C2:C999, MATCH(D11,Orders!B2:B999, 0)) -> ORD-1004 | I11: =INDEX(Orders!D2:D999, MATCH(D11,Orders!B2:B999, 0)) -> 46091.208 | J11: =INDEX(Orders!J2:J999, MATCH(D11,Orders!B2:B999, 0)) -> 320.5 | K11: =INDEX(Orders!K2:K999, MATCH(D11,Orders!B2:B999, 0)) -> 320.5 | L11: =INDEX(Orders!L2:L999, MATCH(D11,Orders!B2:B999, 0)) -> 0 | M11: =INDEX(Orders!M2:M999, MATCH(D11,Orders!B2:B999, 0)) -> TRUE | N11: =INDEX(Orders!E2:E999, MATCH(D11,Orders!B2:B999, 0)) -> grace.hopper@nautical.mil | O11: =INDEX(Orders!H2:H999, MATCH(D11,Orders!B2:B999, 0)) -> Hopper, Grace | P11: =INDEX(Orders!I2:I999, MATCH(D11,Orders!B2:B999, 0)) -> grace.hopper@nautical.mil
A12: =C12 -> PMT-643977 | B12: PMT-643977 | C12: PMT-643977 | D12: ORD-1009 | E12: 46162.208 | F12: 180 | G12: card | H12: =INDEX(Orders!C2:C999, MATCH(D12,Orders!B2:B999, 0)) -> ORD-1009 | I12: =INDEX(Orders!D2:D999, MATCH(D12,Orders!B2:B999, 0)) -> 46147.208 | J12: =INDEX(Orders!J2:J999, MATCH(D12,Orders!B2:B999, 0)) -> 180 | K12: =INDEX(Orders!K2:K999, MATCH(D12,Orders!B2:B999, 0)) -> 180 | L12: =INDEX(Orders!L2:L999, MATCH(D12,Orders!B2:B999, 0)) -> 0 | M12: =INDEX(Orders!M2:M999, MATCH(D12,Orders!B2:B999, 0)) -> TRUE | N12: =INDEX(Orders!E2:E999, MATCH(D12,Orders!B2:B999, 0)) -> linus.torvalds@kernel.org | O12: =INDEX(Orders!H2:H999, MATCH(D12,Orders!B2:B999, 0)) -> Torvalds, Linus | P12: =INDEX(Orders!I2:I999, MATCH(D12,Orders!B2:B999, 0)) -> linus.torvalds@kernel.org

Sheet _original_json
A1: { "$schema": "https://example.com/cmcc-schema/v1", "Name": "Customer CRM Demo", "Description": "Minimal CRM demo: customers with orders, lifetime sales rollup, and a VIP threshold flag.", "Users": { "Description": "Dev-login identities for the demo app. Email is the PK.", "schema": [ { "name": "Name", "datatype": "string", "type": "calculated", "nullable": false, "Description": "PK = Email", "formula": "={{Email}}" }, { "name": "UsersId", "datatype": "string", "type": "raw", "nullable": false, "Description": "Synthetic PK = Email." }, { "name": "Email", "datatype": "string", "type": "raw", "nullable": false, "Description": "Login email (PK source)." }, { "name": "FirstName", "datatype": "string", "type": "raw", "nullable": true, "Description": "Given name." }, { "name": "LastName", "datatype": "string", "type": "raw", "nullable": true, "Description": "Family name." }, { "name": "Role", "datatype": "string", "type": "raw", "nullable": false, "Description": "admin or viewer." }, { "name": "FullName", "datatype": "string", "type": "calculated", "nullable": true, "Description": "LastName, FirstName.", "formula": "=CONCAT({{LastName}}, \", \", {{FirstName}})" } ], "data": [ { "Name": "alice@example.com", "UsersId": "alice@example.com", "Email": "alice@example.com", "FirstName": "Alice", "LastName": "Anderson", "Role": "admin", "FullName": "Anderson, Alice" }, { "Name": "bob@example.com", "UsersId": "bob@example.com", "Email": "bob@example.com", "FirstName": "Bob", "LastName": "Baker", "Role": "viewer", "FullName": "Baker, Bob" } ] }, "Customers": { "Description": "A CRM contact. Email is the PK.", "schema": [ { "name": "Name", "datatype": "string", "type": "calculated", "nullable": false, "Description": "PK = Email", "formula": "={{Email}}" }, { "name": "CustomersId", "datatype": "string", "type": "raw", "nullable": false, "Description": "Synthetic PK = Email." }, { "name": "Email", "datatype": "string", "type": "raw", "nullable": false, "Description": "Customer email (PK source)." }, { "name": "FirstName", "datatype": "string", "type": "raw", "nullable": true, "Description": "Given name." }, { "name": "LastName", "datatype": "string", "type": "raw", "nullable": true, "Description": "Family name." }, { "name": "FullName", "datatype": "string", "type": "calculated", "nullable": true, "Description": "LastName, FirstName.", "formula": "=CONCAT({{LastName}}, \", \", {{FirstName}})" }, { "name": "LifetimeSales", "datatype": "number", "type": "aggregation", "nullable": true, "Description": "Sum of this customer's order totals from the last 60 days (orders older than 60 days do not count).", "formula": "=SUMIFS(Orders!{{RecentTotal}}, Orders!{{Customer}}, {{Name}})" }, { "name": "UnpaidOrderCount", "datatype": "number", "type": "aggregation", "nullable": true, "Description": "Number of this customer's orders that are not yet paid in full.", "formula": "=SUMIFS(Orders!{{UnpaidFlag}}, Orders!{{Customer}}, {{Name}})" }, { "name": "LargeOrderCount", "datatype": "number", "type": "aggregation", "nullable": true, "Description": "Number of this customer's orders with a Total over $500. SUMIFS expression-mode workaround: agg_range yields 1 per row, then a real WHERE clause filters via the operator criterion \">500\" (Program.cs ExtractCriteriaOp, supported on SUMIFS but not yet on COUNTIFS).", "formula": "=SUMIFS(Orders!{{Total}}*0+1, Orders!{{Customer}}, {{Name}}, Orders!{{Total}}, \">500\")" }, { "name": "IsVIP", "datatype": "boolean", "type": "calculated", "nullable": true, "Description": "True when LifetimeSales > 1500 AND the customer has no unpaid orders.", "formula": "=AND({{LifetimeSales}} > 1500, {{UnpaidOrderCount}} = 0)" } ], "data": [ { "Name": "ada.lovelace@analytical.engine", "CustomersId": "ada.lovelace@analytical.engine", "Email": "ada.lovelace@analytical.engine", "FirstName": "Ada", "LastName": "Lovelace", "FullName": "Lovelace, Ada", "LifetimeSales": "50.00", "UnpaidOrderCount": "0", "LargeOrderCount": "1.00", "IsVIP": false }, { "Name": "grace.hopper@nautical.mil", "CustomersId": "grace.hopper@nautical.mil", "Email": "grace.hopper@nautical.mil", "FirstName": "Grace", "LastName": "Hopper", "FullName": "Hopper, Grace", "LifetimeSales": "1820.49", "UnpaidOrderCount": "1", "LargeOrderCount": "1.00", "IsVIP": false }, { "Name": "alan.turing@bletchley.uk", "CustomersId": "alan.turing@bletchley.uk", "Email": "alan.turing@bletchley.uk", "FirstName": "Alan", "LastName": "Turing", "FullName": "Turing, Alan", "LifetimeSales": "99.00", "UnpaidOrderCount": "0", "LargeOrderCount": "0", "IsVIP": false }, { "Name": "katherine.johnson@nasa.gov", "CustomersId": "katherine.johnson@nasa.gov", "Email": "katherine.johnson@nasa.gov", "FirstName": "Katherine", "LastName": "Johnson", "FullName": "Johnson, Katherine", "LifetimeSales": "1152.00", "UnpaidOrderCount": "1", "LargeOrderCount": "2.00", "IsVIP": false }, { "Name": "linus.torvalds@kernel.org", "CustomersId": "linus.torvalds@kernel.org", "Email": "linus.torvalds@kernel.org", "FirstName": "Linus", "LastName": "Torvalds", "FullName": "Torvalds, Linus", "LifetimeSales": "2580.00", "UnpaidOrderCount": "0", "LargeOrderCount": "1.00", "IsVIP": true } ] }, "Orders": { "Description": "A customer order. OrderNumber is the PK.", "schema": [ { "name": "Name", "datatype": "string", "type": "calculated", "nullable": false, "Description": "PK = OrderNumber", "formula": "={{OrderNumber}}" }, { "name": "OrdersId", "datatype": "string", "type": "raw", "nullable": false, "Description": "Synthetic PK = OrderNumber." }, { "name": "OrderNumber", "datatype": "string", "type": "raw", "nullable": false, "Description": "Human-readable order number (PK source)." }, { "name": "OrderDate", "datatype": "date", "type": "raw", "nullable": false, "Description": "Date the order was placed." }, { "name": "Customer", "datatype": "string", "type": "raw", "nullable": false, "Description": "FK -> Customers.Name (the customer's email)." }, { "name": "CustomerFirstName", "datatype": "string", "type": "lookup", "nullable": true, "Description": "Customer's first name, looked up via Customer FK.", "formula": "=INDEX(Customers!{{FirstName}}, MATCH({{Customer}}, Customers!{{CustomersId}}, 0))" }, { "name": "CustomerLastName", "datatype": "string", "type": "lookup", "nullable": true, "Description": "Customer's last name, looked up via Customer FK.", "formula": "=INDEX(Customers!{{LastName}}, MATCH({{Customer}}, Customers!{{CustomersId}}, 0))" }, { "name": "CustomerFullName", "datatype": "string", "type": "lookup", "nullable": true, "Description": "Customer's full name, looked up via Customer FK.", "formula": "=INDEX(Customers!{{FullName}}, MATCH({{Customer}}, Customers!{{CustomersId}}, 0))" }, { "name": "CustomerEmail", "datatype": "string", "type": "lookup", "nullable": true, "Description": "Customer's email, looked up via Customer FK.", "formula": "=INDEX(Customers!{{Email}}, MATCH({{Customer}}, Customers!{{CustomersId}}, 0))" }, { "name": "Total", "datatype": "number", "type": "raw", "nullable": false, "Description": "Order total in dollars." }, { "name": "AmountPaid", "datatype": "number", "type": "aggregation", "nullable": true, "Description": "Sum of all payments recorded against this order.", "formula": "=SUMIFS(Payments!{{Amount}}, Payments!{{OrderId}}, {{Name}})" }, { "name": "Balance", "datatype": "number", "type": "calculated", "nullable": true, "Description": "Outstanding balance: Total - AmountPaid.", "formula": "={{Total}} - {{AmountPaid}}" }, { "name": "IsPaid", "datatype": "boolean", "type": "calculated", "nullable": true, "Description": "True when Balance <= 0.", "formula": "={{Balance}} <= 0" }, { "name": "UnpaidFlag", "datatype": "number", "type": "calculated", "nullable": true, "Description": "1 when the order is unpaid, 0 otherwise — summed by Customers.UnpaidOrderCount.", "formula": "=IF({{IsPaid}}, 0, 1)" }, { "name": "IsRecent", "datatype": "boolean", "type": "calculated", "nullable": true, "Description": "True when OrderDate is within the last 60 days. Drives the 60-day window on Customers.LifetimeSales.", "formula": "=DATEDIFF(TODAY(), {{OrderDate}}, \"days\") <= 90" }, { "name": "RecentTotal", "datatype": "number", "type": "calculated", "nullable": true, "Description": "Total if the order is recent, 0 otherwise — summed by Customers.LifetimeSales.", "formula": "=IF({{IsRecent}}, {{Total}}, 0)" } ], "data": [ { "Name": "ORD-1001", "OrdersId": "ORD-1001", "OrderNumber": "ORD-1001", "OrderDate": "2026-01-15T06:00:00.000Z", "Customer": "ada.lovelace@analytical.engine", "CustomerFirstName": "Ada", "CustomerLastName": "Lovelace", "CustomerFullName": "Lovelace, Ada", "CustomerEmail": "ada.lovelace@analytical.engine", "Total": "250.00", "AmountPaid": "250.00", "Balance": "0.00", "IsPaid": true, "UnpaidFlag": "0", "IsRecent": false, "RecentTotal": "0" }, { "Name": "ORD-1002", "OrdersId": "ORD-1002", "OrderNumber": "ORD-1002", "OrderDate": "2026-02-03T06:00:00.000Z", "Customer": "ada.lovelace@analytical.engine", "CustomerFirstName": "Ada", "CustomerLastName": "Lovelace", "CustomerFullName": "Lovelace, Ada", "CustomerEmail": "ada.lovelace@analytical.engine", "Total": "875.00", "AmountPaid": "875.00", "Balance": "0.00", "IsPaid": true, "UnpaidFlag": "0", "IsRecent": false, "RecentTotal": "0" }, { "Name": "ORD-1003", "OrdersId": "ORD-1003", "OrderNumber": "ORD-1003", "OrderDate": "2026-02-20T06:00:00.000Z", "Customer": "grace.hopper@nautical.mil", "CustomerFirstName": "Grace", "CustomerLastName": "Hopper", "CustomerFullName": "Hopper, Grace", "CustomerEmail": "grace.hopper@nautical.mil", "Total": "1499.99", "AmountPaid": "1000.00", "Balance": "499.99", "IsPaid": false, "UnpaidFlag": "1", "IsRecent": true, "RecentTotal": "1499.99" }, { "Name": "ORD-1004", "OrdersId": "ORD-1004", "OrderNumber": "ORD-1004", "OrderDate": "2026-03-10T05:00:00.000Z", "Customer": "grace.hopper@nautical.mil", "CustomerFirstName": "Grace", "CustomerLastName": "Hopper", "CustomerFullName": "Hopper, Grace", "CustomerEmail": "grace.hopper@nautical.mil", "Total": "320.50", "AmountPaid": "320.5", "Balance": "0.00", "IsPaid": true, "UnpaidFlag": "0", "IsRecent": true, "RecentTotal": "320.50" }, { "Name": "ORD-1005", "OrdersId": "ORD-1005", "OrderNumber": "ORD-1005", "OrderDate": "2026-03-22T05:00:00.000Z", "Customer": "alan.turing@bletchley.uk", "CustomerFirstName": "Alan", "CustomerLastName": "Turing", "CustomerFullName": "Turing, Alan", "CustomerEmail": "alan.turing@bletchley.uk", "Total": "99.00", "AmountPaid": "99.00", "Balance": "0.00", "IsPaid": true, "UnpaidFlag": "0", "IsRecent": true, "RecentTotal": "99.00" }, { "Name": "ORD-1006", "OrdersId": "ORD-1006", "OrderNumber": "ORD-1006", "OrderDate": "2026-04-01T05:00:00.000Z", "Customer": "katherine.johnson@nasa.gov", "CustomerFirstName": "Katherine", "CustomerLastName": "Johnson", "CustomerFullName": "Johnson, Katherine", "CustomerEmail": "katherine.johnson@nasa.gov", "Total": "540.00", "AmountPaid": "540.00", "Balance": "0.00", "IsPaid": true, "UnpaidFlag": "0", "IsRecent": true, "RecentTotal": "540.00" }, { "Name": "ORD-1007", "OrdersId": "ORD-1007", "OrderNumber": "ORD-1007", "OrderDate": "2026-04-12T05:00:00.000Z", "Customer": "katherine.johnson@nasa.gov", "CustomerFirstName": "Katherine", "CustomerLastName": "Johnson", "CustomerFullName": "Johnson, Katherine", "CustomerEmail": "katherine.johnson@nasa.gov", "Total": "612.00", "AmountPaid": "0", "Balance": "612.00", "IsPaid": false, "UnpaidFlag": "1", "IsRecent": true, "RecentTotal": "612.00" }, { "Name": "ORD-1008", "OrdersId": "ORD-1008", "OrderNumber": "ORD-1008", "OrderDate": "2026-04-28T05:00:00.000Z", "Customer": "linus.torvalds@kernel.org", "CustomerFirstName": "Linus", "CustomerLastName": "Torvalds", "CustomerFullName": "Torvalds, Linus", "CustomerEmail": "linus.torvalds@kernel.org", "Total": "2400.00", "AmountPaid": "2400.00", "Balance": "0.00", "IsPaid": true, "UnpaidFlag": "0", "IsRecent": true, "RecentTotal": "2400.00" }, { "Name": "ORD-1009", "OrdersId": "ORD-1009", "OrderNumber": "ORD-1009", "OrderDate": "2026-05-05T05:00:00.000Z", "Customer": "linus.torvalds@kernel.org", "CustomerFirstName": "Linus", "CustomerLastName": "Torvalds", "CustomerFullName": "Torvalds, Linus", "CustomerEmail": "linus.torvalds@kernel.org", "Total": "180.00", "AmountPaid": "180", "Balance": "0.00", "IsPaid": true, "UnpaidFlag": "0", "IsRecent": true, "RecentTotal": "180.00" }, { "Name": "ORD-1010", "OrdersId": "ORD-1010", "OrderNumber": "ORD-1010", "OrderDate": "2026-05-15T05:00:00.000Z", "Customer": "ada.lovelace@analytical.engine", "CustomerFirstName": "Ada", "CustomerLastName": "Lovelace", "CustomerFullName": "Lovelace, Ada", "CustomerEmail": "ada.lovelace@analytical.engine", "Total": "50.00", "AmountPaid": "50.00", "Balance": "0.00", "IsPaid": true, "UnpaidFlag": "0", "IsRecent": true, "RecentTotal": "50.00" } ] }, "Payments": { "Description": "A payment recorded against an order. PaymentNumber is the PK.", "schema": [ { "name": "Name", "datatype": "string", "type": "calculated", "nullable": false, "Description": "PK = PaymentNumber", "formula": "={{PaymentNumber}}" }, { "name": "PaymentsId", "datatype": "string", "type": "raw", "nullable": false, "Description": "Synthetic PK = PaymentNumber." }, { "name": "PaymentNumber", "datatype": "string", "type": "raw", "nullable": false, "Description": "Human-readable payment number (PK source)." }, { "name": "OrderId", "datatype": "string", "type": "raw", "nullable": false, "Description": "FK -> Orders.Name (the order number)." }, { "name": "PaymentDate", "datatype": "date", "type": "raw", "nullable": false, "Description": "Date the payment was received." }, { "name": "Amount", "datatype": "number", "type": "raw", "nullable": false, "Description": "Payment amount in dollars." }, { "name": "Method", "datatype": "string", "type": "raw", "nullable": false, "Description": "Payment method: card, check, cash, wire, ach." }, { "name": "OrderNumber", "datatype": "string", "type": "lookup", "nullable": true, "Description": "Parent order's human-readable number.", "formula": "=INDEX(Orders!{{OrderNumber}}, MATCH({{OrderId}}, Orders!{{OrdersId}}, 0))" }, { "name": "OrderDate", "datatype": "date", "type": "lookup", "nullable": true, "Description": "Parent order's date.", "formula": "=INDEX(Orders!{{OrderDate}}, MATCH({{OrderId}}, Orders!{{OrdersId}}, 0))" }, { "name": "OrderTotal", "datatype": "number", "type": "lookup", "nullable": true, "Description": "Parent order's total.", "formula": "=INDEX(Orders!{{Total}}, MATCH({{OrderId}}, Orders!{{OrdersId}}, 0))" }, { "name": "OrderAmountPaid", "datatype": "number", "type": "lookup", "nullable": true, "Description": "Parent order's total paid (across all its payments).", "formula": "=INDEX(Orders!{{AmountPaid}}, MATCH({{OrderId}}, Orders!{{OrdersId}}, 0))" }, { "name": "OrderBalance", "datatype": "number", "type": "lookup", "nullable": true, "Description": "Parent order's outstanding balance.", "formula": "=INDEX(Orders!{{Balance}}, MATCH({{OrderId}}, Orders!{{OrdersId}}, 0))" }, { "name": "OrderIsPaid", "datatype": "boolean", "type": "lookup", "nullable": true, "Description": "Parent order's paid-in-full flag.", "formula": "=INDEX(Orders!{{IsPaid}}, MATCH({{OrderId}}, Orders!{{OrdersId}}, 0))" }, { "name": "OrderCustomer", "datatype": "string", "type": "lookup", "nullable": true, "Description": "Parent order's customer FK (email).", "formula": "=INDEX(Orders!{{Customer}}, MATCH({{OrderId}}, Orders!{{OrdersId}}, 0))" }, { "name": "CustomerFullName", "datatype": "string", "type": "lookup", "nullable": true, "Description": "Parent order's customer full name (two-hop).", "formula": "=INDEX(Orders!{{CustomerFullName}}, MATCH({{OrderId}}, Orders!{{OrdersId}}, 0))" }, { "name": "CustomerEmail", "datatype": "string", "type": "lookup", "nullable": true, "Description": "Parent order's customer email (two-hop).", "formula": "=INDEX(Orders!{{CustomerEmail}}, MATCH({{OrderId}}, Orders!{{OrdersId}}, 0))" } ], "data": [ { "Name": "PMT-2001", "PaymentsId": "PMT-2001", "PaymentNumber": "PMT-2001", "OrderId": "ORD-1001", "PaymentDate": "2026-01-16T06:00:00.000Z", "Amount": "250.00", "Method": "card", "OrderNumber": "ORD-1001", "OrderDate": "2026-01-15T06:00:00.000Z", "OrderTotal": "250.00", "OrderAmountPaid": "250.00", "OrderBalance": "0.00", "OrderIsPaid": true, "OrderCustomer": "ada.lovelace@analytical.engine", "CustomerFullName": "Lovelace, Ada", "CustomerEmail": "ada.lovelace@analytical.engine" }, { "Name": "PMT-2002", "PaymentsId": "PMT-2002", "PaymentNumber": "PMT-2002", "OrderId": "ORD-1002", "PaymentDate": "2026-02-04T06:00:00.000Z", "Amount": "500.00", "Method": "card", "OrderNumber": "ORD-1002", "OrderDate": "2026-02-03T06:00:00.000Z", "OrderTotal": "875.00", "OrderAmountPaid": "875.00", "OrderBalance": "0.00", "OrderIsPaid": true, "OrderCustomer": "ada.lovelace@analytical.engine", "CustomerFullName": "Lovelace, Ada", "CustomerEmail": "ada.lovelace@analytical.engine" }, { "Name": "PMT-2003", "PaymentsId": "PMT-2003", "PaymentNumber": "PMT-2003", "OrderId": "ORD-1002", "PaymentDate": "2026-02-18T06:00:00.000Z", "Amount": "375.00", "Method": "ach", "OrderNumber": "ORD-1002", "OrderDate": "2026-02-03T06:00:00.000Z", "OrderTotal": "875.00", "OrderAmountPaid": "875.00", "OrderBalance": "0.00", "OrderIsPaid": true, "OrderCustomer": "ada.lovelace@analytical.engine", "CustomerFullName": "Lovelace, Ada", "CustomerEmail": "ada.lovelace@analytical.engine" }, { "Name": "PMT-2004", "PaymentsId": "PMT-2004", "PaymentNumber": "PMT-2004", "OrderId": "ORD-1003", "PaymentDate": "2026-02-21T06:00:00.000Z", "Amount": "1000.00", "Method": "wire", "OrderNumber": "ORD-1003", "OrderDate": "2026-02-20T06:00:00.000Z", "OrderTotal": "1499.99", "OrderAmountPaid": "1000.00", "OrderBalance": "499.99", "OrderIsPaid": false, "OrderCustomer": "grace.hopper@nautical.mil", "CustomerFullName": "Hopper, Grace", "CustomerEmail": "grace.hopper@nautical.mil" }, { "Name": "PMT-2005", "PaymentsId": "PMT-2005", "PaymentNumber": "PMT-2005", "OrderId": "ORD-1005", "PaymentDate": "2026-03-23T05:00:00.000Z", "Amount": "99.00", "Method": "cash", "OrderNumber": "ORD-1005", "OrderDate": "2026-03-22T05:00:00.000Z", "OrderTotal": "99.00", "OrderAmountPaid": "99.00", "OrderBalance": "0.00", "OrderIsPaid": true, "OrderCustomer": "alan.turing@bletchley.uk", "CustomerFullName": "Turing, Alan", "CustomerEmail": "alan.turing@bletchley.uk" }, { "Name": "PMT-2006", "PaymentsId": "PMT-2006", "PaymentNumber": "PMT-2006", "OrderId": "ORD-1006", "PaymentDate": "2026-04-02T05:00:00.000Z", "Amount": "540.00", "Method": "check", "OrderNumber": "ORD-1006", "OrderDate": "2026-04-01T05:00:00.000Z", "OrderTotal": "540.00", "OrderAmountPaid": "540.00", "OrderBalance": "0.00", "OrderIsPaid": true, "OrderCustomer": "katherine.johnson@nasa.gov", "CustomerFullName": "Johnson, Katherine", "CustomerEmail": "katherine.johnson@nasa.gov" }, { "Name": "PMT-2007", "PaymentsId": "PMT-2007", "PaymentNumber": "PMT-2007", "OrderId": "ORD-1008", "PaymentDate": "2026-04-29T05:00:00.000Z", "Amount": "1200.00", "Method": "wire", "OrderNumber": "ORD-1008", "OrderDate": "2026-04-28T05:00:00.000Z", "OrderTotal": "2400.00", "OrderAmountPaid": "2400.00", "OrderBalance": "0.00", "OrderIsPaid": true, "OrderCustomer": "linus.torvalds@kernel.org", "CustomerFullName": "Torvalds, Linus", "CustomerEmail": "linus.torvalds@kernel.org" }, { "Name": "PMT-2008", "PaymentsId": "PMT-2008", "PaymentNumber": "PMT-2008", "OrderId": "ORD-1008", "PaymentDate": "2026-05-10T05:00:00.000Z", "Amount": "1200.00", "Method": "wire", "OrderNumber": "ORD-1008", "OrderDate": "2026-04-28T05:00:00.000Z", "OrderTotal": "2400.00", "OrderAmountPaid": "2400.00", "OrderBalance": "0.00", "OrderIsPaid": true, "OrderCustomer": "linus.torvalds@kernel.org", "CustomerFullName": "Torvalds, Linus", "CustomerEmail": "linus.torvalds@kernel.org" }, { "Name": "PMT-2009", "PaymentsId": "PMT-2009", "PaymentNumber": "PMT-2009", "OrderId": "ORD-1010", "PaymentDate": "2026-05-16T05:00:00.000Z", "Amount": "50.00", "Method": "card", "OrderNumber": "ORD-1010", "OrderDate": "2026-05-15T05:00:00.000Z", "OrderTotal": "50.00", "OrderAmountPaid": "50.00", "OrderBalance": "0.00", "OrderIsPaid": true, "OrderCustomer": "ada.lovelace@analytical.engine", "CustomerFullName": "Lovelace, Ada", "CustomerEmail": "ada.lovelace@analytical.engine" }, { "Name": "PMT-525034", "PaymentsId": "PMT-525034", "PaymentNumber": "PMT-525034", "OrderId": "ORD-1004", "PaymentDate": "2026-05-20T05:00:00.000Z", "Amount": "320.5", "Method": "card", "OrderNumber": "ORD-1004", "OrderDate": "2026-03-10T05:00:00.000Z", "OrderTotal": "320.50", "OrderAmountPaid": "320.5", "OrderBalance": "0.00", "OrderIsPaid": true, "OrderCustomer": "grace.hopper@nautical.mil", "CustomerFullName": "Hopper, Grace", "CustomerEmail": "grace.hopper@nautical.mil" }, { "Name": "PMT-643977", "PaymentsId": "PMT-643977", "PaymentNumber": "PMT-643977", "OrderId": "ORD-1009", "PaymentDate": "2026-05-20T05:00:00.000Z", "Amount": "180", "Method": "card", "OrderNumber": "ORD-1009", "OrderDate": "2026-05-05T05:00:00.000Z", "OrderTotal": "180.00", "OrderAmountPaid": "180", "OrderBalance": "0.00", "OrderIsPaid": true, "OrderCustomer": "linus.torvalds@kernel.org", "CustomerFullName": "Torvalds, Linus", "CustomerEmail": "linus.torvalds@kernel.org" } ] }, "_meta": { "_CMCC_Summary": "Hand-authored minimal CRM demo rulebook for the effortless-demo-app skill.", "_conversion_metadata": { "tool_version": "demo-1.0", "export_mode": "hand_authored" } } }
