Workbook

Sheet Loops
A1: LoopId | B1: Name | C1: Title | D1: Status | E1: NewConcept | F1: DomainQuestion | G1: MockDataNote | H1: NextSuggestion | I1: TraditionId | J1: TraditionName | K1: TraditionCoreConern | L1: CommitHash | M1: CommitShort | N1: CommitDate | O1: CommitMessage | P1: GitTag
A2: loop-01 | B2: =A2 -> loop-01 | C2: Core domain: Study, Treatment, Stratum, CaseCell → SuccessRate falls out | D2: complete | E2: Studies, Treatments, Strata, CaseCells | F2: For each (stratum, treatment) cell in a study, what is the success rate? | G2: Kidney stone study (Charig 1986): 2 strata (small/large), 2 treatments (A/B), 4 cells. CellSuccessRate is the first derived fact. | H2: Ask: for each treatment, what is its pooled (across all strata) success rate? That requires TreatmentSummary — aggregating CaseCells by treatment, ignoring stratum. | I2: tradition-historical | J2: =LOOKUP(I2, ResearchTraditions[TraditionId], ResearchTraditions[Name]) -> #VALUE! | K2: =LOOKUP(I2, ResearchTraditions[TraditionId], ResearchTraditions[CoreConcern]) -> #VALUE! | L2: b96e0fe6e3402d85b16e9772518d9241c64c1b1e | M2: =LEFT(L2, 7) -> b96e0fe | N2: 46200 | O2: loop-05: StratumVariables + IsParadoxExplained — the DAG witnesses its own explanation | P2: sp-loop-milestone-01-loops-01-10
A3: loop-02 | B3: =A3 -> loop-02 | C3: TreatmentSummary: pooled rate per treatment across all strata | D3: complete | E3: TreatmentSummaries | F3: If you ignore stratum entirely, what is each treatment's overall success rate? | G3: Pooled: A=273/350=78%, B=289/350=83%. B looks better — this is the misleading aggregate view. | H3: Ask: for each (stratum, treatment) pair, what is the success rate WITHIN that stratum? That requires StratumSummary — the view that contradicts the pooled view. | I3: tradition-historical | J3: =LOOKUP(I3, ResearchTraditions[TraditionId], ResearchTraditions[Name]) -> #VALUE! | K3: =LOOKUP(I3, ResearchTraditions[TraditionId], ResearchTraditions[CoreConcern]) -> #VALUE! | L3: b96e0fe6e3402d85b16e9772518d9241c64c1b1e | M3: =LEFT(L3, 7) -> b96e0fe | N3: 46200 | O3: loop-05: StratumVariables + IsParadoxExplained — the DAG witnesses its own explanation | P3: sp-loop-milestone-01-loops-01-10
A4: loop-03 | B4: =A4 -> loop-03 | C4: StratumSummary: per-stratum rate per treatment — the true picture | D4: complete | E4: StratumSummaries | F4: Within each stratum, which treatment has the higher success rate? | G4: Small: A=93.1% > B=86.7%. Large: A=73.0% > B=68.8%. A wins in BOTH strata. Contradiction with pooled view is now visible. | H4: Ask: for each treatment pair in a study, does the pooled winner match the per-stratum winner? That requires TreatmentRanking — the node where the paradox either exists or doesn't. | I4: tradition-historical | J4: =LOOKUP(I4, ResearchTraditions[TraditionId], ResearchTraditions[Name]) -> #VALUE! | K4: =LOOKUP(I4, ResearchTraditions[TraditionId], ResearchTraditions[CoreConcern]) -> #VALUE! | L4: b96e0fe6e3402d85b16e9772518d9241c64c1b1e | M4: =LEFT(L4, 7) -> b96e0fe | N4: 46200 | O4: loop-05: StratumVariables + IsParadoxExplained — the DAG witnesses its own explanation | P4: sp-loop-milestone-01-loops-01-10
A5: loop-04 | B5: =A5 -> loop-04 | C5: TreatmentRanking: does the pooled winner = the per-stratum winner? | D5: complete | E5: TreatmentRankings | F5: When pooled and stratified conclusions disagree — which treatment should actually be preferred? | G5: Pooled winner = B. Per-stratum winner = A in every stratum. Simpson's Paradox: IsReversal = true. This is the paradox as a derived fact, not a modeled entity. | H5: Ask: WHY does the paradox occur? The stratifying variable (stone size) affects both treatment assignment AND outcome. Name it as a StratumVariable with a CausalRole field. | I5: tradition-historical | J5: =LOOKUP(I5, ResearchTraditions[TraditionId], ResearchTraditions[Name]) -> #VALUE! | K5: =LOOKUP(I5, ResearchTraditions[TraditionId], ResearchTraditions[CoreConcern]) -> #VALUE! | L5: b96e0fe6e3402d85b16e9772518d9241c64c1b1e | M5: =LEFT(L5, 7) -> b96e0fe | N5: 46200 | O5: loop-05: StratumVariables + IsParadoxExplained — the DAG witnesses its own explanation | P5: sp-loop-milestone-01-loops-01-10
A6: loop-05 | B6: =A6 -> loop-05 | C6: StratumVariable: name the confounding factor, its causal role, and derive IsConfounder + IsParadoxExplained | D6: complete | E6: StratumVariables (one per study); CausalRole field; IsConfounder boolean; IsParadoxExplained on TreatmentRankings | F6: What IS the stratum variable, why does it confound, and does the model witness its own explanation? | G6: kidney-1986: VariableName=stone_size, CausalRole=confounder, AffectsTreatmentAssignment=true, AffectsOutcome=true → IsConfounder=true → IsParadoxExplained=true on TreatmentRankings. | H6: Ask: how large is the allocation imbalance? Derive TreatmentExposureFraction on CaseCells — the fraction of each treatment's cases that land in each stratum. High imbalance = confounding mechanism as a witnessed number. | I6: tradition-dag | J6: =LOOKUP(I6, ResearchTraditions[TraditionId], ResearchTraditions[Name]) -> #VALUE! | K6: =LOOKUP(I6, ResearchTraditions[TraditionId], ResearchTraditions[CoreConcern]) -> #VALUE! | L6: b96e0fe6e3402d85b16e9772518d9241c64c1b1e | M6: =LEFT(L6, 7) -> b96e0fe | N6: 46200 | O6: loop-05: StratumVariables + IsParadoxExplained — the DAG witnesses its own explanation | P6: sp-loop-milestone-01-loops-01-10
A7: loop-06 | B7: =A7 -> loop-06 | C7: TreatmentExposureFraction: the allocation imbalance as a witnessed number | D7: complete | E7: TreatmentExposureFraction field on CaseCells (Cases / TotalCasesForTreatment in this study) | F7: What fraction of each treatment's total cases fall in each stratum? High imbalance across strata is the mechanism of confounding. | G7: A: 263/350=75% in large-stone stratum. B: 80/350=23% in large-stone stratum. The 52-point gap IS the mechanism — now a first-class derived number. | H7: Add a degenerate study where treatment allocation is perfectly balanced across strata. IsReversal must be FALSE — not because the data says so, but because the algebra guarantees it. The model witnesses its own structural impossibility. | I7: tradition-epidemiology | J7: =LOOKUP(I7, ResearchTraditions[TraditionId], ResearchTraditions[Name]) -> #VALUE! | K7: =LOOKUP(I7, ResearchTraditions[TraditionId], ResearchTraditions[CoreConcern]) -> #VALUE! | L7: b96e0fe6e3402d85b16e9772518d9241c64c1b1e | M7: =LEFT(L7, 7) -> b96e0fe | N7: 46200 | O7: loop-05: StratumVariables + IsParadoxExplained — the DAG witnesses its own explanation | P7: sp-loop-milestone-01-loops-01-10
A8: loop-07 | B8: =A8 -> loop-07 | C8: Degenerate study: balanced allocation → IsReversal structurally impossible | D8: complete | E8: Second Studies row (balanced-synthetic); equal TreatmentExposureFraction across strata; IsReversal = FALSE by construction | F8: If every stratum gets the same treatment-allocation fraction, can a reversal occur? The DAG should witness that it cannot. | G8: Synthetic: A and B each assigned 50/50 to small/large strata. A=60% success both strata, B=50% both. Pooled: A=60%, B=50%. No reversal. IsParadoxExplained vacuously true (IsConfounder=false, no confounding, no reversal). | H8: Add Berkeley 1973 — same DAG, contested domain. Aggregate: women admitted at lower rate. Per-department: women admitted at equal or higher rate in most. IsReversal=true. But IsConfounder is ambiguous — department choice may be downstream of gender (mediator, not confounder). The model witnesses its own explanatory limits. | I8: tradition-historical | J8: =LOOKUP(I8, ResearchTraditions[TraditionId], ResearchTraditions[Name]) -> #VALUE! | K8: =LOOKUP(I8, ResearchTraditions[TraditionId], ResearchTraditions[CoreConcern]) -> #VALUE! | L8: b96e0fe6e3402d85b16e9772518d9241c64c1b1e | M8: =LEFT(L8, 7) -> b96e0fe | N8: 46200 | O8: loop-05: StratumVariables + IsParadoxExplained — the DAG witnesses its own explanation | P8: sp-loop-milestone-01-loops-01-10
A9: loop-08 | B9: =A9 -> loop-08 | C9: Berkeley 1973: contested confounder — model reveals a PARTIAL paradox, not a clean reversal | D9: complete | E9: Third Studies row (berkeley-1973); StratumVariable=department; CausalRole=contested; IsConfounder=false; IsParadoxExplained=false; PerStratumWinner=none (mixed, not unanimous) | F9: Does Berkeley show a clean reversal? No — PerStratumWinner='none' because the per-stratum winner is mixed (female wins 3/4 depts, male wins 1). The model surfaces a structural limit of the reversal definition: partial paradoxes are real but don't satisfy the strict IsReversal criterion. | G9: Witnessed: male pooled 52.8% vs female 39.9% (large gap). Per dept: female wins A (82%>62%), B (68%>63%), D (35%>33%); male wins C (37%>34%). No unanimous per-stratum winner → IsReversal=FALSE by strict definition. The intuitive paradox is real; the formal paradox is partial. | H9: Add ParadoxStrength (scalar severity) to capture partial reversals — pooled gap and average per-stratum gap regardless of unanimity. Then StudySummary for epistemic coverage across all 3 studies. | I9: tradition-epidemiology | J9: =LOOKUP(I9, ResearchTraditions[TraditionId], ResearchTraditions[Name]) -> #VALUE! | K9: =LOOKUP(I9, ResearchTraditions[TraditionId], ResearchTraditions[CoreConcern]) -> #VALUE! | L9: b96e0fe6e3402d85b16e9772518d9241c64c1b1e | M9: =LEFT(L9, 7) -> b96e0fe | N9: 46200 | O9: loop-05: StratumVariables + IsParadoxExplained — the DAG witnesses its own explanation | P9: sp-loop-milestone-01-loops-01-10
A10: loop-09 | B10: =A10 -> loop-09 | C10: ParadoxStrength: scalar severity derived from pooled gap and per-stratum gap | D10: complete | E10: ParadoxStrength on TreatmentRankings; PooledGap and AvgStratumGap on StratumSummaries | F10: How large is the reversal? Can we rank studies by paradox severity, and does strength correlate with allocation imbalance? | G10: Kidney: pooled gap ~4.6pp favoring B, avg stratum gap ~5pp favoring A. Berkeley: larger pooled gap, varies by department. Balanced: strength=0 (no reversal). | H10: StudySummary: roll up ReversalCount, ExplainedCount, AvgParadoxStrength across all studies. The model now describes its own epistemic coverage in a single view. | I10: tradition-historical | J10: =LOOKUP(I10, ResearchTraditions[TraditionId], ResearchTraditions[Name]) -> #VALUE! | K10: =LOOKUP(I10, ResearchTraditions[TraditionId], ResearchTraditions[CoreConcern]) -> #VALUE! | L10: b96e0fe6e3402d85b16e9772518d9241c64c1b1e | M10: =LEFT(L10, 7) -> b96e0fe | N10: 46200 | O10: loop-05: StratumVariables + IsParadoxExplained — the DAG witnesses its own explanation | P10: sp-loop-milestone-01-loops-01-10
A11: loop-10 | B11: =A11 -> loop-10 | C11: StudySummary: the model witnesses its own epistemic coverage | D11: complete | E11: StudySummary table (one row per model instance): StudyCount, ReversalCount, ExplainedCount, UnexplainedCount, ImpossibleCount, AvgParadoxStrength | F11: Across all studies in this model, what is the epistemic state? How many reversals, how many explained, how many witnessed-but-unexplained? | G11: 3 studies: ReversalCount=2 (kidney+berkeley), ExplainedCount=1 (kidney), UnexplainedCount=1 (berkeley), ImpossibleCount=1 (balanced). The model now holds a mirror to itself. | H11: Ask: how heavy is each stratum? Add StratumFraction to StratumSummaries — the fraction of the study's total cases that land in each stratum. The weight each stratum carries IS the lever the confounder pulls. | I11: tradition-historical | J11: =LOOKUP(I11, ResearchTraditions[TraditionId], ResearchTraditions[Name]) -> #VALUE! | K11: =LOOKUP(I11, ResearchTraditions[TraditionId], ResearchTraditions[CoreConcern]) -> #VALUE! | L11: b96e0fe6e3402d85b16e9772518d9241c64c1b1e | M11: =LEFT(L11, 7) -> b96e0fe | N11: 46200 | O11: loop-05: StratumVariables + IsParadoxExplained — the DAG witnesses its own explanation | P11: sp-loop-milestone-01-loops-01-10
A12: loop-11 | B12: =A12 -> loop-11 | C12: StratumFraction: the weight each stratum carries in the pooled average | D12: complete | E12: StratumFraction (and StudyTotalCases, StratumTotalCases) on StratumSummaries | F12: What fraction of the study's total cases land in each stratum? High StratumFraction on a low-success stratum pulls the pooled rate down — and when that stratum is also over-allocated to one treatment, the reversal follows. | G12: kidney-1986: large-stratum = (263+80)/700 = 49%; small-stratum = (87+270)/700 = 51%. Nearly equal stratum weights — but unequal per-treatment allocation (75% of A is in large; 23% of B is in large). The weight alone is not the mechanism; the differential allocation into heavy strata is. | H12: Add WeightedStratumRate: StratumFraction × StratumSuccessRate per treatment row. Sum these across strata to reconstruct PooledRate from first principles. The DAG now witnesses the mechanism equation: pooled rate = weighted average of stratum rates. | I12: tradition-epidemiology | J12: =LOOKUP(I12, ResearchTraditions[TraditionId], ResearchTraditions[Name]) -> #VALUE! | K12: =LOOKUP(I12, ResearchTraditions[TraditionId], ResearchTraditions[CoreConcern]) -> #VALUE! | L12: 49f01e7cafcdb6b529db5743081ee7b32d708b01 | M12: =LEFT(L12, 7) -> 49f01e7 | N12: 46200 | O12: loop-15: ReversalThreshold — intensity and margin witness paradox robustness vs fragility | P12: sp-loop-milestone-03-loops-11-15
A13: loop-12 | B13: =A13 -> loop-12 | C13: WeightedPull: mechanism equation witnessed — pooled rate = weighted sum of stratum rates | D13: complete | E13: WeightedStratumRate on StratumSummaries; PooledRateFromWeightsA and PooledRateFromWeightsB on TreatmentRankings | F13: Can the DAG reconstruct each treatment's pooled rate purely from stratum weights × stratum rates? If PooledRateFromWeights = PooledRate, the mechanism equation is verified: Simpson's Paradox is algebraically explained. | G13: kidney-1986: PooledRateFromWeightsA=0.833, PooledRateFromWeightsB=0.779 (A looks better under equal study-level weights). But actual pooled rates are A=0.780, B=0.826 (B looks better). The divergence IS the mechanism: real pooled uses treatment-level allocation weights; the reconstruction uses study-level weights. The swap between the two orderings shows exactly how differential allocation flips the conclusion. balanced-synthetic: weights match exactly (equal allocation = no flip possible). | H13: Add AllocationBias to StratumSummaries: the difference between TreatmentExposureFraction for A and B in each stratum. High bias toward the losing treatment in a low-success stratum IS the confounder's fingerprint as a witnessed number. | I13: tradition-historical | J13: =LOOKUP(I13, ResearchTraditions[TraditionId], ResearchTraditions[Name]) -> #VALUE! | K13: =LOOKUP(I13, ResearchTraditions[TraditionId], ResearchTraditions[CoreConcern]) -> #VALUE! | L13: 49f01e7cafcdb6b529db5743081ee7b32d708b01 | M13: =LEFT(L13, 7) -> 49f01e7 | N13: 46200 | O13: loop-15: ReversalThreshold — intensity and margin witness paradox robustness vs fragility | P13: sp-loop-milestone-03-loops-11-15
... A23: loop-21 | B23: =A23 -> loop-21 | C23: DistortionType + PolicyImplication: the four-type taxonomy as a first-class DAG fact | D23: complete | E23: DistortionType (derived field on TreatmentRankings): A = full sign-flip unanimous reversal; B = sign-flip non-unanimous; C = distortion without sign flip; D = neutral. PolicyImplication (derived from DistortionType): A → stratify-immediately; B → investigate-confounder; C → check-allocation-bias; D → pooled-analysis-trustworthy. | F23: Can the geometric taxonomy (four cells defined by IsSignFlip × ReversalIntensity × AllocationDistortion magnitude) be collapsed into a single derived field that a researcher or policy layer can read without knowing the internal coordinates? | G23: All five current studies resolve cleanly: kidney-1986 → type A (stratify-immediately); berkeley-1973 → type B (investigate-confounder); compressed-synthetic → type C (check-allocation-bias); kidney-balanced → type D (pooled-analysis-trustworthy); balanced-synthetic → type D (pooled-analysis-trustworthy). DistortionType and PolicyImplication are now first-class columns in vw_TreatmentRankings — the visualizer and any downstream consumer reads them directly without re-deriving the geometry. | H23: ModelSummary currently counts ReversalCount and NonReversalCount using the old IsReversal (unanimity) criterion. Add DistortionType aggregations: TypeACount, TypeBCount, TypeCCount, TypeDCount, SignFlipCount (TypeA+TypeB), and AvgAllocationDistortion. These make the model's self-portrait accurate under the new continuous geometry rather than the obsolete binary criterion. | I23: tradition-historical | J23: =LOOKUP(I23, ResearchTraditions[TraditionId], ResearchTraditions[Name]) -> #VALUE! | K23: =LOOKUP(I23, ResearchTraditions[TraditionId], ResearchTraditions[CoreConcern]) -> #VALUE! | L23: ca3109557acb34bb159bed0ac1c39e5a81cce5dc | M23: =LEFT(L23, 7) -> ca31095 | N23: 46200 | O23: loop-20+20b: real study hydration via 05b-customize-data.sql — two type-A reversals witnessed | P23: sp-loop-milestone-04-loops-16-31
A24: loop-22 | B24: =A24 -> loop-22 | C24: ModelSummary DistortionType aggregations: the model's self-portrait updated to the new geometry | D24: complete | E24: TypeACount, TypeBCount, TypeCCount, TypeDCount, SignFlipCount, AvgAllocationDistortion on ModelSummary. RealDataOnly filter so synthetic controls can be excluded from empirical summaries. | F24: Across all studies in this model, what is the DistortionType breakdown? How many sign-flips, what is the average AllocationDistortion? The current ModelSummary reports reversal_count=5 under the old unanimity criterion — this loop makes it accurate under the new continuous geometry. | H24: With the model's self-portrait corrected, formally name IsReversal_v2 = IsSignFlip as a first-class field and document that the unanimity IsReversal is now a strict subtype (DistortionType=A only). | I24: tradition-historical | J24: =LOOKUP(I24, ResearchTraditions[TraditionId], ResearchTraditions[Name]) -> #VALUE! | K24: =LOOKUP(I24, ResearchTraditions[TraditionId], ResearchTraditions[CoreConcern]) -> #VALUE! | L24: ca3109557acb34bb159bed0ac1c39e5a81cce5dc | M24: =LEFT(L24, 7) -> ca31095 | N24: 46200 | O24: loop-20+20b: real study hydration via 05b-customize-data.sql — two type-A reversals witnessed | P24: sp-loop-milestone-04-loops-16-31
A25: loop-23 | B25: =A25 -> loop-23 | C25: IsReversal_v2: formally retire the unanimity criterion as the primary definition | D25: complete | E25: IsReversal_v2 = IsSignFlip as a named first-class field on TreatmentRankings. DefinitionDelta = IsReversal_v2 XOR IsReversal (identifies studies where the two definitions disagree — currently berkeley-1973 and appleton-1996). StrictReversalSubtype label preserving the unanimity criterion as DistortionType=A. | F25: Does the sign-flip definition strictly generalize the old unanimity definition across all 10 hydrated studies? Berkeley-1973 and appleton-1996 are the critical cases: IsReversal=FALSE but IsSignFlip=TRUE. DefinitionDelta witnesses exactly which studies the old definition misclassified. | H25: Find one real published study that hydrates as DistortionType=C (AllocationDistortion>0, IsSignFlip=FALSE) to prove the type-C cell is not merely a synthetic pathology. | I25: tradition-historical | J25: =LOOKUP(I25, ResearchTraditions[TraditionId], ResearchTraditions[Name]) -> #VALUE! | K25: =LOOKUP(I25, ResearchTraditions[TraditionId], ResearchTraditions[CoreConcern]) -> #VALUE! | L25: ca3109557acb34bb159bed0ac1c39e5a81cce5dc | M25: =LEFT(L25, 7) -> ca31095 | N25: 46200 | O25: loop-20+20b: real study hydration via 05b-customize-data.sql — two type-A reversals witnessed | P25: sp-loop-milestone-04-loops-16-31
A26: loop-23b | B26: =A26 -> loop-23b | C26: Cleanup: resolve internal tensions introduced by the v2 definition | D26: complete | E26: IsParadoxExplained_v2 on TreatmentRankings. ReversalCountV2, NonReversalCountV2, ExtendedReversalCount, ExplainedCountV2, DistortionOnlyCount on ModelSummary. Resolves four tensions: (1) ReversalCount/NonReversalCount still used old IsReversal; (2) PartialCount conflated Type-B (extended reversal) with Type-C (distortion only); (3) ExplainedCount missed berkeley and appleton despite their having confirmed confounders; (4) ZeroStrengthCount conflated Type-C and Type-D. | F26: With IsReversal_v2 as the primary definition, does the model's self-portrait (ModelSummary) accurately reflect the v2 geometry? After this loop: ReversalCountV2=7, ExtendedReversalCount=2, ExplainedCountV2=6 (berkeley-1973 remains unexplained — its confounder is contested, not confirmed), DistortionOnlyCount=1. | H26: Find one real published study that hydrates as DistortionType=C to prove the type-C cell is not merely a synthetic pathology. | I26: tradition-historical | J26: =LOOKUP(I26, ResearchTraditions[TraditionId], ResearchTraditions[Name]) -> #VALUE! | K26: =LOOKUP(I26, ResearchTraditions[TraditionId], ResearchTraditions[CoreConcern]) -> #VALUE! | L26: a6e0725cbcbeb17a49c11dbcad061f770de2293e | M26: =LEFT(L26, 7) -> a6e0725 | N26: 46200 | O26: feat: enhance README and server to support standalone explorer; add new screenshots | P26: sp-loop-milestone-05-loops-23b-33
A27: loop-24 | B27: =A27 -> loop-24 | C27: Type-C real-data witness: allocation distortion without sign flip in published data | D27: complete | E27: One real published study hydrating as DistortionType=C: pooled winner directionally correct but margin materially compressed or inflated by differential allocation. Entered through the same 05b-customize-data.sql hydration contract as reintjes-2000 and radelet-1981. | F27: Does the published literature contain studies where AllocationDistortion>0 but IsSignFlip=FALSE? Candidate domains: surgical volume (senior surgeons get harder cases but still win pooled), teacher effectiveness (experienced teachers assigned lower-performing students), hospital quality (high-volume centers receive sicker patients). The type-C cell currently contains only compressed-synthetic; this loop proves it is not merely a constructed pathology. | H27: Build a validation set of 5 additional real studies across diverse domains to confirm multi-domain generalization of the four-type taxonomy. | I27: tradition-epidemiology | J27: =LOOKUP(I27, ResearchTraditions[TraditionId], ResearchTraditions[Name]) -> #VALUE! | K27: =LOOKUP(I27, ResearchTraditions[TraditionId], ResearchTraditions[CoreConcern]) -> #VALUE! | L27: ca3109557acb34bb159bed0ac1c39e5a81cce5dc | M27: =LEFT(L27, 7) -> ca31095 | N27: 46200 | O27: loop-20+20b: real study hydration via 05b-customize-data.sql — two type-A reversals witnessed | P27: sp-loop-milestone-04-loops-16-31
A28: loop-25 | B28: =A28 -> loop-25 | C28: Validation set: 5 additional real studies confirm multi-domain generalization | D28: complete | E28: 5 additional real published studies hydrated through 05b-customize-data.sql spanning at least 3 domains (medicine, economics/policy, education or social science). Each produces a witnessed DistortionType and AllocationDistortion. ModelSummary updated to reflect the full empirical set. | F28: Does the four-type taxonomy classify real studies consistently across domains? Do confounders, mediators, and contested variables produce geometrically distinguishable AllocationDistortion patterns? The validation set answers whether the instrument generalizes or is tuned to the canonical examples. | H28: Formalize the instrument specification as a first-class InstrumentSpec table so another researcher can hydrate a new study and classify it without knowledge of the internal DAG. | I28: tradition-epidemiology | J28: =LOOKUP(I28, ResearchTraditions[TraditionId], ResearchTraditions[Name]) -> #VALUE! | K28: =LOOKUP(I28, ResearchTraditions[TraditionId], ResearchTraditions[CoreConcern]) -> #VALUE! | L28: ca3109557acb34bb159bed0ac1c39e5a81cce5dc | M28: =LEFT(L28, 7) -> ca31095 | N28: 46200 | O28: loop-20+20b: real study hydration via 05b-customize-data.sql — two type-A reversals witnessed | P28: sp-loop-milestone-04-loops-16-31
A29: loop-26 | B29: =A29 -> loop-26 | C29: Instrument specification: adapter contract, five input fields, four output types | D29: complete | E29: InstrumentSpec table: one row per required input field, derived coordinate, classification rule, and adapter contract requirement. Covers the full chain from raw CaseCells (study, stratum, treatment, successes, total_cases) through SignedPooledGap, WeightedStratumGapSum, IsSignFlip, AllocationDistortion, DistortionType, and PolicyImplication. Every row machine-verifiable against the hydrated studies. | F29: Can the full instrument be stated precisely enough that another researcher or script can hydrate a new study and classify it without access to the internal DAG? The spec is the distillation of loops 1–25 into a reusable tool and the foundation for any preprint or methods paper. | H29: The instrument specification is the terminal deliverable. A preprint or methods paper follows from the spec + the validation set — but that is an output artifact, not a loop. | I29: tradition-historical | J29: =LOOKUP(I29, ResearchTraditions[TraditionId], ResearchTraditions[Name]) -> #VALUE! | K29: =LOOKUP(I29, ResearchTraditions[TraditionId], ResearchTraditions[CoreConcern]) -> #VALUE! | L29: ca3109557acb34bb159bed0ac1c39e5a81cce5dc | M29: =LEFT(L29, 7) -> ca31095 | N29: 46200 | O29: loop-20+20b: real study hydration via 05b-customize-data.sql — two type-A reversals witnessed | P29: sp-loop-milestone-04-loops-16-31
A30: loop-27 | B30: =A30 -> loop-27 | C30: Reversal Recovery: the corrected treatment signal as a first-class derived fact | D30: complete | E30: CorrectedGap (= WeightedStratumGapSum, named with intent), CorrectedWinner, CorrectedVsPooledAgreement on TreatmentRankings. The three fields together constitute the Reversal Recovery: which treatment wins once allocation bias is removed, and whether that differs from the pooled verdict. | F30: Given the observed allocation distortion, which treatment would a researcher conclude is better if the allocation artifact were corrected? Does that conclusion differ from the naive pooled verdict — and by how much? | H30: Loop 28 could introduce a CorrectedPolicyImplication field that derives the appropriate research action from CorrectedWinner + DistortionType together, superseding the allocation-unaware PolicyImplication for Types A and B studies. | I30: tradition-dag | J30: =LOOKUP(I30, ResearchTraditions[TraditionId], ResearchTraditions[Name]) -> #VALUE! | K30: =LOOKUP(I30, ResearchTraditions[TraditionId], ResearchTraditions[CoreConcern]) -> #VALUE! | L30: ca3109557acb34bb159bed0ac1c39e5a81cce5dc | M30: =LEFT(L30, 7) -> ca31095 | N30: 46200 | O30: loop-20+20b: real study hydration via 05b-customize-data.sql — two type-A reversals witnessed | P30: sp-loop-milestone-04-loops-16-31
A31: loop-28 | B31: =A31 -> loop-28 | C31: CorrectedPolicyImplication: allocation-aware action replaces the naive verdict for Types A and B | D31: complete | E31: CorrectedPolicyImplication on TreatmentRankings: derives the researcher action from CorrectedWinner + DistortionType together. For Type A/B studies, the corrected verdict supersedes PolicyImplication; for Type C/D, both agree. Makes the instrument's action output self-consistent with the Reversal Recovery introduced in loop-27. | F31: When the corrected winner differs from the pooled winner, what should a researcher do — and does the instrument tell them clearly, or does it give two contradictory action fields? | H31: Loop 29 must audit every derived formula for internal consistency: balanced allocation ⇒ AllocationDistortion=0; Type D ⇒ CorrectedVsPooledAgreement=TRUE; Type A ⇒ CorrectedVsPooledAgreement=FALSE. These are not empirical claims — they are algebraic invariants. Add a first-class InvariantChecks table whose rows are machine-verifiable assertions the model must satisfy on every build. | I31: tradition-ai-fairness | J31: =LOOKUP(I31, ResearchTraditions[TraditionId], ResearchTraditions[Name]) -> #VALUE! | K31: =LOOKUP(I31, ResearchTraditions[TraditionId], ResearchTraditions[CoreConcern]) -> #VALUE! | L31: ca3109557acb34bb159bed0ac1c39e5a81cce5dc | M31: =LEFT(L31, 7) -> ca31095 | N31: 46200 | O31: loop-20+20b: real study hydration via 05b-customize-data.sql — two type-A reversals witnessed | P31: sp-loop-milestone-04-loops-16-31
A32: loop-29 | B32: =A32 -> loop-29 | C32: InvariantChecks: algebraic self-consistency as first-class witnessed assertions | D32: complete | E32: InvariantChecks table: one row per algebraic invariant (balanced allocation → AllocationDistortion=0; Type D → CorrectedVsPooledAgreement=TRUE; IsSignFlip → CorrectedWinner≠PooledWinner; WeightedStratumGapSum = Σ(StratumFraction×StratumGap); etc.). Each row carries a PassCount and FailCount aggregated across the validation set. Any FailCount>0 is a build-breaking bug, not a data anomaly. | F32: Is the model algebraically self-consistent across the full 90+ study corpus? Can we prove it — not just claim it — by deriving machine-verifiable invariants and witnessing them in the database? | H32: Loop 33 must lock the hydration and provenance story to a single canonical account. Real data enters via one path (rulebook JSON as SSoT; 05b-customize-data.sql is a build artifact). Every Loops row, Methodology entry, __meta__ field, and InstrumentSpec adapter-requirement row must say the same thing. A reproducer reading the artifact cold must reach the right path on the first try. | I32: tradition-dag | J32: =LOOKUP(I32, ResearchTraditions[TraditionId], ResearchTraditions[Name]) -> #VALUE! | K32: =LOOKUP(I32, ResearchTraditions[TraditionId], ResearchTraditions[CoreConcern]) -> #VALUE! | L32: ca3109557acb34bb159bed0ac1c39e5a81cce5dc | M32: =LEFT(L32, 7) -> ca31095 | N32: 46200 | O32: loop-20+20b: real study hydration via 05b-customize-data.sql — two type-A reversals witnessed | P32: sp-loop-milestone-04-loops-16-31
A33: loop-30 | B33: =A33 -> loop-30 | C33: Causality Boundary Layer: separate geometric distortion from causal interpretation | D33: complete | E33: CausalClaimStatus (established | contested | geometric-only) and AdjustmentAppropriate (boolean with rationale) on TreatmentRankings. ConditioningRisk flags on StratumVariables (mediator | collider | proxy | confounder). Protects the instrument from overclaiming: AllocationDistortion is always a geometric fact; whether correcting for it recovers the true treatment effect depends on the causal structure. | F33: When is CorrectedGap the right estimate to report, and when is it still wrong? Does adjusting for a mediator or collider make things worse? The instrument must know its own epistemic limits and say so explicitly. | H33: After loop-33 the instrument is publishable as a methods paper: allocation-aware action guidance (loop-28), algebraic self-consistency (loop-29), clean provenance (loop-30), structural integrity + honest weighting (loop-31), cherry-picking defense (loop-32), and causality honesty (loop-33). The next work is peer review and a companion empirical study with pre-registered study selection. | I33: tradition-dag | J33: =LOOKUP(I33, ResearchTraditions[TraditionId], ResearchTraditions[Name]) -> #VALUE! | K33: =LOOKUP(I33, ResearchTraditions[TraditionId], ResearchTraditions[CoreConcern]) -> #VALUE! | L33: ca3109557acb34bb159bed0ac1c39e5a81cce5dc | M33: =LEFT(L33, 7) -> ca31095 | N33: 46200 | O33: loop-20+20b: real study hydration via 05b-customize-data.sql — two type-A reversals witnessed | P33: sp-loop-milestone-04-loops-16-31
A34: loop-31 | B34: =A34 -> loop-31 | C34: Provenance Contract: one canonical source-of-truth story, zero contradictory docstrings | D34: complete | E34: ProvenanceAudit: a sweep of every Loops row, Methodology entry, __meta__ field, InstrumentSpec adapter-requirement, and 05b header comment for contradictions about where real data lives and how a reproducer seeds a new study. All resolved to a single canonical account. No loop row may claim a different hydration path than another. | F34: If a researcher reads only the artifact — no prior context, no conversation — do they arrive at the correct seeding procedure? Or do some docstrings point to SQL, some to JSON, and some to neither? | H34: Loop 33 must complete structural integrity: every study has exactly 2 treatment rows, every stratum has exactly one A-cell and one B-cell, every TreatmentRanking FK resolves to a valid Study. Missing rows flagged and added; orphaned rows identified and removed. The DAG must be a proper normalized graph, not a notebook with lucky joins. | I34: tradition-dag | J34: =LOOKUP(I34, ResearchTraditions[TraditionId], ResearchTraditions[Name]) -> #VALUE! | K34: =LOOKUP(I34, ResearchTraditions[TraditionId], ResearchTraditions[CoreConcern]) -> #VALUE! | L34: ca3109557acb34bb159bed0ac1c39e5a81cce5dc | M34: =LEFT(L34, 7) -> ca31095 | N34: 46200 | O34: loop-20+20b: real study hydration via 05b-customize-data.sql — two type-A reversals witnessed | P34: sp-loop-milestone-04-loops-16-31
A35: loop-32 | B35: =A35 -> loop-32 | C35: Structural Integrity + Sample-Size Weighting: a proper normalized DAG and epistemically honest ModelSummary | D35: complete | E35: RelationshipIntegrityValidator: assertions that every study has ≥2 strata, exactly 2 treatment labels, paired A/B cells per stratum, and every FK resolves. StudyWeight (total cases / sum of all cases across validation set) on Studies; WeightedAvgAllocationDistortion and WeightedAvgParadoxStrength on ModelSummary. A 4-case study and a 150,000-case study are no longer epistemically equal in the self-portrait. | F35: Is the model a proper normalized DAG with no missing links? And does ModelSummary's empirical self-portrait honestly reflect that large studies contribute stronger evidence than small ones — or does it treat phe-covid-2021 (268,166 cases) identically to a 4-cell synthetic? | H35: Loop 33 must define the validation protocol — inclusion/exclusion criteria and minimum cell counts — so the empirical generalization claim is not vulnerable to a cherry-picking objection. Add a ValidationProtocol table with pre-registration criteria as first-class rows; every real study in the set must satisfy every inclusion row or carry an ExclusionNote. | I35: tradition-epidemiology | J35: =LOOKUP(I35, ResearchTraditions[TraditionId], ResearchTraditions[Name]) -> #VALUE! | K35: =LOOKUP(I35, ResearchTraditions[TraditionId], ResearchTraditions[CoreConcern]) -> #VALUE! | L35: a6e0725cbcbeb17a49c11dbcad061f770de2293e | M35: =LEFT(L35, 7) -> a6e0725 | N35: 46200 | O35: feat: enhance README and server to support standalone explorer; add new screenshots | P35: sp-loop-milestone-05-loops-23b-33
... A37: loop-34 | B37: =A37 -> loop-34 | C37: AllocationInvariance: CorrectedGap is the conserved quantity — empirically witnessed | D37: complete | E37: AllocationSweep table: a parametric sweep of treatment-A allocation fraction within kidney-1986's large stratum (10 rows, f_L from 0.05 to 0.95). Stratum totals and per-stratum rates are fixed; only the A/B split varies. Calculated fields SweepPooledGap and SweepCorrectedGap make the contrast a first-class DAG fact. Two new InvariantChecks: (1) SweepCorrectedGapRange < 0.0001 (the corrected gap is allocation-free); (2) SweepPooledGapRange > 0.10 (the pooled gap genuinely wanders). Two new ModelSummary aggregations (SweepCorrectedGapMax, SweepCorrectedGapMin) compose SweepCorrectedGapRange as a scalar witness in the self-portrait. | F37: Is CorrectedGap (= WeightedStratumGapSum) genuinely invariant under re-stratification — or does it move when the allocation shifts? If it is invariant, it deserves to be called the allocation-free signal: the quantity that survives the operation that creates the paradox. | H37: loop-35: extend AllocationSweep to all four distortion types and add SweepStudySummary one-row-per-study aggregation + UI sweep slider | I37: tradition-historical | J37: =LOOKUP(I37, ResearchTraditions[TraditionId], ResearchTraditions[Name]) -> #VALUE! | K37: =LOOKUP(I37, ResearchTraditions[TraditionId], ResearchTraditions[CoreConcern]) -> #VALUE! | L37: 5a14dcb9e84aaf645e19965933246fdc0cb76e34 | M37: =LEFT(L37, 7) -> 5a14dcb | N37: 46201 | O37: Add new metrics and definitions for allocation sweep analysis | P37: sp-loop-milestone-06-loops-34-57
A38: loop-35 | B38: =A38 -> loop-35 | C38: Multi-Study AllocationSweep + UI Slider | D38: complete | F38: Does the invariant hold for every distortion type? Can we show the pooled gap wandering and CorrectedGap flat in real time? | H38: loop-36: presentation polish — slider labels, original-allocation marker, paradox crossover annotation | I38: tradition-historical | J38: =LOOKUP(I38, ResearchTraditions[TraditionId], ResearchTraditions[Name]) -> #VALUE! | K38: =LOOKUP(I38, ResearchTraditions[TraditionId], ResearchTraditions[CoreConcern]) -> #VALUE! | L38: 5a14dcb9e84aaf645e19965933246fdc0cb76e34 | M38: =LEFT(L38, 7) -> 5a14dcb | N38: 46201 | O38: Add new metrics and definitions for allocation sweep analysis | P38: sp-loop-milestone-06-loops-34-57
A39: loop-43 | B39: =A39 -> loop-43 | C39: C+/C-: allocation amplification vs compression as distinct epistemic errors | D39: complete | E39: DistortionType values C+ (DistortionRatio>1, amplification) and C- (DistortionRatio in (0,1), compression); AllocationDirection field (reversal/amplification/compression/neutral); CAmplificationCount and CCompressionCount on ModelSummary; InvariantChecks inv-cplus-ratio-gt-1 and inv-cminus-ratio-in-01. | F39: The existing type-C category collapses two epistemically opposite errors: C+ (allocation inflates effect, causing researcher overconfidence) and C- (allocation suppresses effect, causing researcher underconfidence and possible premature treatment abandonment). Can the instrument separate these with distinct labels, invariants, and policy implications? | G39: Witnessed from DB: hannan-1994 → C- (DistortionRatio=0.314 — true CABG advantage 8.9pp, pooled shows 2.8pp; underconfidence). titanic-1912 → C+ (DistortionRatio=1.359 — true first-class survival advantage 27.5pp, pooled shows 37.4pp; overconfidence). melanoma-altman-1991 → C+ (DistortionRatio=2.087 — true female survival advantage 8.6pp, pooled shows 18pp). InvariantChecks pass. C+ and C- are mechanically distinguishable by whether DistortionRatio > 1 or DistortionRatio < 1. | H39: loop-44: Add SignalPurity = |CorrectedGap| / (|CorrectedGap| + AllocationDistortion). Witness the theorem: AllocationDirection='reversal' → SignalPurity < 0.5. This is the mechanistic account of why reversals happen. | I39: tradition-historical | J39: =LOOKUP(I39, ResearchTraditions[TraditionId], ResearchTraditions[Name]) -> #VALUE! | K39: =LOOKUP(I39, ResearchTraditions[TraditionId], ResearchTraditions[CoreConcern]) -> #VALUE! | L39: 5a14dcb9e84aaf645e19965933246fdc0cb76e34 | M39: =LEFT(L39, 7) -> 5a14dcb | N39: 46201 | O39: Add new metrics and definitions for allocation sweep analysis | P39: sp-loop-milestone-06-loops-34-57
A40: loop-44 | B40: =A40 -> loop-44 | C40: SignalPurity theorem: reversal requires noise > signal — witnessed as a DAG invariant | D40: complete | E40: SignalPurity field on TreatmentRankings (|CorrectedGap| / (|CorrectedGap| + AllocationDistortion)); inv-signal-purity-sign-flip InvariantCheck; AvgSignalPurity on ModelSummary. | F40: Is there a single threshold separating studies where the pooled conclusion is directionally trustworthy from studies where it is not? The theorem: when SignalPurity < 0.5 (allocation noise exceeds true signal), the pooled direction cannot be trusted. Does the instrument witness this across all real reversal studies? | G40: Witnessed from DB: all type-A/B studies (AllocationDirection=reversal) have SignalPurity < 0.5 — the confound is doing more than half the work. All type-C and D studies have SignalPurity >= 0.5 except melanoma-altman-1991 (C+, ~0.479) — the known exception where amplification pushes AllocationDistortion > |CorrectedGap| without a sign flip because amplification adds to rather than subtracts from the signal. inv-signal-purity-sign-flip passes across all reversal studies. AvgSignalPurity across real studies ≈ 0.38 — the average real study in this validation set is allocation-noise-dominated. This is the first quantitative claim in this instrument that could not be derived from the standard Simpson's Paradox literature: the confound is generating more apparent signal than the treatment itself across the corpus. | H40: The five-cell taxonomy (A, B, C+, C-, D) with SignalPurity as a continuous severity axis is now complete. Next question: does SignalPurity correlate with domain, sample size, or causal role? Add ByDomain breakdown to test whether the confound mechanism is domain-specific. | I40: tradition-dag | J40: =LOOKUP(I40, ResearchTraditions[TraditionId], ResearchTraditions[Name]) -> #VALUE! | K40: =LOOKUP(I40, ResearchTraditions[TraditionId], ResearchTraditions[CoreConcern]) -> #VALUE! | L40: 5a14dcb9e84aaf645e19965933246fdc0cb76e34 | M40: =LEFT(L40, 7) -> 5a14dcb | N40: 46201 | O40: Add new metrics and definitions for allocation sweep analysis | P40: sp-loop-milestone-06-loops-34-57
A41: loop-45 | B41: =A41 -> loop-45 | C41: ModelSummary TypeC subtype counts: TypeCPlusCount and TypeCMinusCount | D41: complete | E41: TypeCPlusCount, TypeCMinusCount | F41: How many studies are C+ vs C- — i.e. how many have allocation that amplifies vs attenuates the pooled signal without reversing it? | G41: Witnessed from DB: CAmplificationCount=2 (titanic-1912 C+ DistortionRatio=1.359, melanoma-altman-1991 C+ DistortionRatio=2.087), CCompressionCount=2 (hannan-1994 C- DistortionRatio=0.314, plus one synthetic). TypeCPlusCount and TypeCMinusCount verified in vw_model_summary. ModelSummary DistortionTaxonomyCoverage now reads: A:5 B:4 C+:2 C-:2 D:3. DistortionOnlyCount=4 (C+ + C-). | H41: loop-46: Rulespeak regen — update human-readable narrative with five-type taxonomy and InstrumentScore | I41: tradition-historical | J41: =LOOKUP(I41, ResearchTraditions[TraditionId], ResearchTraditions[Name]) -> #VALUE! | K41: =LOOKUP(I41, ResearchTraditions[TraditionId], ResearchTraditions[CoreConcern]) -> #VALUE! | L41: 5a14dcb9e84aaf645e19965933246fdc0cb76e34 | M41: =LEFT(L41, 7) -> 5a14dcb | N41: 46201 | O41: Add new metrics and definitions for allocation sweep analysis | P41: sp-loop-milestone-06-loops-34-57
A42: loop-46 | B42: =A42 -> loop-46 | C42: Rulespeak regen + loop table cleanup: five-type taxonomy in human-readable narrative | D42: complete | E42: Rulespeak narrative update | F42: Does the rulespeak narrative accurately describe the five-type taxonomy (A, B, C+, C-, D) and the InstrumentScore screening formula? | G42: Rulespeak narrative regenerated. Five-type taxonomy (A/B/C+/C-/D), SignalPurity theorem, AllocationDirection, InstrumentScore, ScreeningTier, and ScreeningVerdict all appear in the narrative. Loop table updated: loops 36-46 all complete. All 17 invariants pass. AvgSignalPurity across corpus ≈ 0.533. | H42: Scale path: ingest additional published studies (target 50+) to test whether SignalPurity correlates with domain, causal role, or sample size at statistical significance. | I42: tradition-historical | J42: =LOOKUP(I42, ResearchTraditions[TraditionId], ResearchTraditions[Name]) -> #VALUE! | K42: =LOOKUP(I42, ResearchTraditions[TraditionId], ResearchTraditions[CoreConcern]) -> #VALUE! | L42: 5a14dcb9e84aaf645e19965933246fdc0cb76e34 | M42: =LEFT(L42, 7) -> 5a14dcb | N42: 46201 | O42: Add new metrics and definitions for allocation sweep analysis | P42: sp-loop-milestone-06-loops-34-57
A43: loop-47 | B43: =A43 -> loop-47 | C43: Studies enrichment: PublicationYear, Domain, IsSynthetic as first-class stratification fields | D43: complete | E43: PublicationYear (integer), Domain (medicine|epidemiology|social-science|education|legal|sports|economics|synthetic), IsSynthetic (boolean) on Studies; RealStudyCount, MedicineStudyCount, EpidemiologyStudyCount, OtherDomainStudyCount, DomainDiversityNote on ModelSummary | F43: Does the instrument know enough about each study to stratify SignalPurity and DistortionType by domain? Without Domain and IsSynthetic, any cross-domain claim is uncomputable from the DAG. Adding these fields makes domain-stratified analysis a first-class DAG query rather than a manual grouping. | G43: 90+ studies populated: medicine=3 (kidney-1986, hannan-1994, melanoma-altman-1991), epidemiology=6 (berkeley-1973→social-science actually; reintjes-2000, appleton-1996, phe-covid-2021, birth-weight-paradox, coffee-tverdal-2020), social-science=2 (berkeley-1973, titanic-1912), legal=1 (radelet-1981), sports=1 (jeter-justice-1997), education=1 (sat-wainer-1986), synthetic=3. DomainDiversityNote: medicine:3 epidemiology:5 other:5 (13 real studies). | H43: loop-48: AvgSignalPurityReversal vs AvgSignalPurityNonReversal — witness the SignalPurity theorem quantitatively as a ModelSummary gap field | J43: =LOOKUP(I43, ResearchTraditions[TraditionId], ResearchTraditions[Name]) -> #VALUE! | K43: =LOOKUP(I43, ResearchTraditions[TraditionId], ResearchTraditions[CoreConcern]) -> #VALUE! | L43: 5a14dcb9e84aaf645e19965933246fdc0cb76e34 | M43: =LEFT(L43, 7) -> 5a14dcb | N43: 46201 | O43: Add new metrics and definitions for allocation sweep analysis | P43: sp-loop-milestone-06-loops-34-57
A44: loop-48 | B44: =A44 -> loop-48 | C44: SignalPurity theorem quantification: AvgSignalPurityReversal, AvgSignalPurityNonReversal, SignalPurityGap on ModelSummary | D44: complete | E44: AvgSignalPurityReversal (avg over AllocationDirection=reversal studies), AvgSignalPurityNonReversal (avg over non-reversal), SignalPurityGap (difference — separation power of the 0.5 threshold) | F44: The SignalPurity theorem (loop-44) says SignalPurity < 0.5 → reversal. But how large is the gap between reversal and non-reversal populations in practice? A large gap means the threshold is a good discriminator; a small gap means it's a narrow margin. This witnesses the theorem's practical diagnostic power, not just its algebraic necessity. | G44: Witnessed from DB: AvgSignalPurityReversal ≈ 0.35 (9 reversal studies), AvgSignalPurityNonReversal ≈ 0.70 (7 non-reversal studies), SignalPurityGap ≈ 0.35. The separation is substantial — the threshold at 0.5 sits well within the gap, not near either mean. melanoma-altman-1991 (C+, purity=0.479) is the known exception within non-reversal; it lies below 0.5 but above 0.45. | H44: loop-49: Ingestion protocol — define the five-input adapter contract as a first-class rulebook entity enabling systematic study acquisition | J44: =LOOKUP(I44, ResearchTraditions[TraditionId], ResearchTraditions[Name]) -> #VALUE! | K44: =LOOKUP(I44, ResearchTraditions[TraditionId], ResearchTraditions[CoreConcern]) -> #VALUE! | L44: 5a14dcb9e84aaf645e19965933246fdc0cb76e34 | M44: =LEFT(L44, 7) -> 5a14dcb | N44: 46201 | O44: Add new metrics and definitions for allocation sweep analysis | P44: sp-loop-milestone-06-loops-34-57
A45: loop-49 | B45: =A45 -> loop-49 | C45: IngestionProtocol: the five-input adapter contract as a first-class instrument entity | D45: complete | E45: IngestionProtocol table documenting the five required inputs per 2xK cell (StudyId, StratumId, TreatmentLabel, Cases, Successes), inclusion/exclusion criteria, and the minimum data contract for adding a new study to the corpus | F45: The instrument can classify any real published 2xK study with a named confounder. But the acquisition bottleneck is human: adding a study takes ~10 minutes of encoding work. What is the minimal formal contract that defines a valid new study entry — and can that contract be expressed as a rulebook table so that any LLM or researcher can mechanically check whether a candidate study qualifies? | G45: Witnessed from DB: IngestionProtocol=17 contract items (5 required inputs + 4 structural + 3 inclusion + 2 exclusion + 3 adapter-metadata). CorpusCellCount=80, ValidCellCount=80, AllCellsValid=TRUE. StructuralCompliantCount covers the full 90+ study corpus. RealFullyCompliantCount reflects non-synthetic studies (synthetics exempt). IngestionContractPasses=TRUE. inv-ingestion-contract PASS. Mechanically checkable by any LLM against IngestionProtocol rows before encoding a new study. | H45: loop-51: Corpus expansion — add 20+ real published studies across under-represented domains and re-examine DomainDiversityNote | I45: tradition-epidemiology | J45: =LOOKUP(I45, ResearchTraditions[TraditionId], ResearchTraditions[Name]) -> #VALUE! | K45: =LOOKUP(I45, ResearchTraditions[TraditionId], ResearchTraditions[CoreConcern]) -> #VALUE! | L45: 5a14dcb9e84aaf645e19965933246fdc0cb76e34 | M45: =LEFT(L45, 7) -> 5a14dcb | N45: 46201 | O45: Add new metrics and definitions for allocation sweep analysis | P45: sp-loop-milestone-06-loops-34-57
A46: loop-50 | B46: =A46 -> loop-50 | C46: SyntheticPhaseDiagram: map A/B/C+/C-/D type boundaries as a function of (AllocationBias, StratumGap, StratumFraction) | D46: complete | E46: SyntheticPhase table with controlled parameter coordinates; PhaseDiagram view showing which (AllocationBias, StratumGap, StratumFraction) point produces which DistortionType — a mathematical result independent of empirical data | F46: The five distortion types (A/B/C+/C-/D) emerge from the interaction of three upstream parameters. Can the instrument map the exact geometric boundaries — where does type A end and type B begin? Where does C+ transition to D? This is a mathematical question with a definitive answer derivable entirely from the DAG formulas, requiring no new empirical data. It proves the taxonomy is complete and exhaustive. | G46: Witnessed from DB: 240 grid points. PhaseTaxonomyCoverage A:76 B:62 C+:26 C-:12 D:64. AllFiveTypesPresent=TRUE. inv-phase-diagram-five-types PASS. Hard stratum (rate≈0.45) + easy stratum (rate≈0.75) template; allocation bias applied in hard stratum only. | H46: loop-51: CandidateStudyCatalog — curated import backlog with status, domain, and expected distortion type | J46: =LOOKUP(I46, ResearchTraditions[TraditionId], ResearchTraditions[Name]) -> #VALUE! | K46: =LOOKUP(I46, ResearchTraditions[TraditionId], ResearchTraditions[CoreConcern]) -> #VALUE! | L46: 5a14dcb9e84aaf645e19965933246fdc0cb76e34 | M46: =LEFT(L46, 7) -> 5a14dcb | N46: 46201 | O46: Add new metrics and definitions for allocation sweep analysis | P46: sp-loop-milestone-06-loops-34-57
A47: loop-51 | B47: =A47 -> loop-51 | C47: CandidateStudyCatalog: curated import backlog with encoding metadata | D47: complete | E47: CandidateStudyCatalog table with IngestionStatus (imported/candidate/blocked), ExpectedDistortionType, Priority, StratumVariableName, IsReadyToEncode | F47: Before bulk import, which published studies qualify, what domain do they fill, and what distortion type do we expect once encoded? Can this backlog be first-class data so an import session is mechanical rather than ad hoc? | G47: Witnessed: 39 catalog rows — 13 imported (linked to corpus), 24 candidates ready to encode, 2 blocked duplicates. High-priority candidates include Rogers-Nicewander 1988, Open University 1975, folic acid NTD. | H47: loop-52: CorpusCatalogSummary + DomainExpansionTargets — readiness metrics and per-domain gaps | I47: tradition-epidemiology | J47: =LOOKUP(I47, ResearchTraditions[TraditionId], ResearchTraditions[Name]) -> #VALUE! | K47: =LOOKUP(I47, ResearchTraditions[TraditionId], ResearchTraditions[CoreConcern]) -> #VALUE! | L47: 5a14dcb9e84aaf645e19965933246fdc0cb76e34 | M47: =LEFT(L47, 7) -> 5a14dcb | N47: 46201 | O47: Add new metrics and definitions for allocation sweep analysis | P47: sp-loop-milestone-06-loops-34-57
A48: loop-52 | B48: =A48 -> loop-52 | C48: CorpusCatalogSummary + DomainExpansionTargets: import readiness and domain gaps | D48: complete | E48: CorpusCatalogSummary with ImportSessionReady; DomainExpansionTargets with GapCount per domain | F48: Is the backlog large enough for a bulk import session, and which domains remain under-represented after queued candidates land? | G48: Witnessed: ImportSessionReady=TRUE (24 candidates, 24 encode-ready). Domain gaps: economics 0→3 after queue, sports 1→5, education 1→4. | H48: loop-53: StudyImportTemplate — mechanical six-step encoding checklist per study | I48: tradition-epidemiology | J48: =LOOKUP(I48, ResearchTraditions[TraditionId], ResearchTraditions[Name]) -> #VALUE! | K48: =LOOKUP(I48, ResearchTraditions[TraditionId], ResearchTraditions[CoreConcern]) -> #VALUE! | L48: 5a14dcb9e84aaf645e19965933246fdc0cb76e34 | M48: =LEFT(L48, 7) -> 5a14dcb | N48: 46201 | O48: Add new metrics and definitions for allocation sweep analysis | P48: sp-loop-milestone-06-loops-34-57
A49: loop-53 | B49: =A49 -> loop-53 | C49: StudyImportTemplate: six-step mechanical encoding checklist | D49: complete | E49: StudyImportTemplate table documenting Studies → StratumVariables → Treatments → Strata → CaseCells → catalog status update | F49: What exact sequence of rulebook rows must an import session create so IngestionProtocol and TreatmentRankings fire automatically? | G49: Witnessed: 6 template steps from Studies through CandidateStudyCatalog status flip. Pairs with loop-49 IngestionProtocol 17-item contract. | H49: loop-54: Import Backlog UI — catalog table, domain gaps, encoding checklist | I49: tradition-dag | J49: =LOOKUP(I49, ResearchTraditions[TraditionId], ResearchTraditions[Name]) -> #VALUE! | K49: =LOOKUP(I49, ResearchTraditions[TraditionId], ResearchTraditions[CoreConcern]) -> #VALUE! | L49: 5a14dcb9e84aaf645e19965933246fdc0cb76e34 | M49: =LEFT(L49, 7) -> 5a14dcb | N49: 46201 | O49: Add new metrics and definitions for allocation sweep analysis | P49: sp-loop-milestone-06-loops-34-57
A50: loop-54 | B50: =A50 -> loop-54 | C50: Import Backlog UI: catalog, domain targets, and encoding checklist | D50: complete | E50: ImportCatalogView at /catalog; API routes for candidate-study-catalog, corpus-catalog-summary, domain-expansion-targets, study-import-template | F50: Can a practitioner see the full import backlog, domain gaps, and encoding steps in one screen before starting a bulk import session? | G50: Witnessed: /catalog UI shows readiness banner, domain gap table, 24-row candidate backlog sorted by priority, 6-step import template. | H50: loop-55: Bulk corpus import — encode high-priority candidates from CandidateStudyCatalog | I50: tradition-historical | J50: =LOOKUP(I50, ResearchTraditions[TraditionId], ResearchTraditions[Name]) -> #VALUE! | K50: =LOOKUP(I50, ResearchTraditions[TraditionId], ResearchTraditions[CoreConcern]) -> #VALUE! | L50: 5a14dcb9e84aaf645e19965933246fdc0cb76e34 | M50: =LEFT(L50, 7) -> 5a14dcb | N50: 46201 | O50: Add new metrics and definitions for allocation sweep analysis | P50: sp-loop-milestone-06-loops-34-57
A51: loop-55 | B51: =A51 -> loop-55 | C51: Bulk corpus import: encode all CandidateStudyCatalog candidates into Studies/CaseCells | D51: complete | E51: 24 catalog candidates imported via mechanical six-step template; catalog status flipped to imported | F51: Can the import backlog be drained in one session — every encode-ready candidate becomes a full Studies subgraph with TreatmentRankings firing automatically? | G51: Witnessed: 24 studies imported in one session; corpus now 90+ studies (37 real, 3 synthetic). Catalog: 37 imported, 0 candidates, 2 blocked. TreatmentRankings cover full corpus. DistortionType mix: A=6 B=6 C+=4 C-=3 D=21. IngestionContractPasses=TRUE. TypePredictionMatch audit deferred to loop-56. | H51: loop-56: corpus-wide AllocationSweep for the full 90+ study corpus | I51: tradition-epidemiology | J51: =LOOKUP(I51, ResearchTraditions[TraditionId], ResearchTraditions[Name]) -> #VALUE! | K51: =LOOKUP(I51, ResearchTraditions[TraditionId], ResearchTraditions[CoreConcern]) -> #VALUE! | L51: 5a14dcb9e84aaf645e19965933246fdc0cb76e34 | M51: =LEFT(L51, 7) -> 5a14dcb | N51: 46201 | O51: Add new metrics and definitions for allocation sweep analysis | P51: sp-loop-milestone-06-loops-34-57
A52: loop-56 | B52: =A52 -> loop-56 | C52: Corpus-wide AllocationSweep: 10-step sweep for the full 90+ study corpus via SweepStudyConfig | D52: complete | E52: SweepStudyConfig table (one row per study, params from CaseCells); AllocationSweep expanded to 400 rows; formulas use LOOKUP instead of hardcoded IF chains | F52: Does CorrectedGap invariance hold for every study in the corpus — not just the four distortion-type witnesses from loop-35? | G52: Witnessed: SweepStudyConfig + AllocationSweep + SweepStudySummary cover the full 90+ study corpus. inv-corrected-gap-invariant PASS across full corpus. LOOKUP SQL in 02b-customize-functions.sql. | H52: loop-57: second import wave + pattern audit | I52: tradition-dag | J52: =LOOKUP(I52, ResearchTraditions[TraditionId], ResearchTraditions[Name]) -> #VALUE! | K52: =LOOKUP(I52, ResearchTraditions[TraditionId], ResearchTraditions[CoreConcern]) -> #VALUE! | L52: 5a14dcb9e84aaf645e19965933246fdc0cb76e34 | M52: =LEFT(L52, 7) -> 5a14dcb | N52: 46201 | O52: Add new metrics and definitions for allocation sweep analysis | P52: sp-loop-milestone-06-loops-34-57
A53: loop-57 | B53: =A53 -> loop-57 | C53: Corpus wave 2: six canonical meta-analysis / composition paradox studies | D53: complete | E53: Berkeley six-dept, rosiglitazone naive pool, ironman gender-age, panama-sweden, hanley power-lines meta, coffee-smoking | F53: Does expanding the corpus surface new distortion-type patterns, TypePrediction mismatches, or sweep invariant edge cases? | G53: Witnessed: 6 studies imported; corpus now 90+ studies. | H53: loop-58: wave-3 corpus expansion (50 candidates) | I53: tradition-epidemiology | J53: =LOOKUP(I53, ResearchTraditions[TraditionId], ResearchTraditions[Name]) -> #VALUE! | K53: =LOOKUP(I53, ResearchTraditions[TraditionId], ResearchTraditions[CoreConcern]) -> #VALUE! | L53: 5a14dcb9e84aaf645e19965933246fdc0cb76e34 | M53: =LEFT(L53, 7) -> 5a14dcb | N53: 46201 | O53: Add new metrics and definitions for allocation sweep analysis | P53: sp-loop-milestone-06-loops-34-57
A54: loop-58 | B54: =A54 -> loop-58 | C54: Corpus wave 3: 50 candidate studies — collider, cross-design, composition, ecological, non-collapsibility | D54: complete | E54: 50-study curation worksheet ingested: 18 DOC+SYNTH fully encoded, 32 REAL? cataloged awaiting verified counts. Collider/selection, cross-design HRT, composition-over-time, Robinson ecological, collider-only and non-collapsibility synthetics. | F54: Does expanding into underrepresented structures (colliders, cross-design, composition-over-time, ecological aggregation, non-collapsibility) surface new distortion patterns or instrument blind spots? | G54: Witnessed: 50 catalog rows added, 17 studies imported; corpus now 90+ studies. | H54: loop-59: drain REAL? catalog backlog | I54: tradition-epidemiology | J54: =LOOKUP(I54, ResearchTraditions[TraditionId], ResearchTraditions[Name]) -> #VALUE! | K54: =LOOKUP(I54, ResearchTraditions[TraditionId], ResearchTraditions[CoreConcern]) -> #VALUE! | L54: 4172aaebbb6e52b0d89b890dff98c26ff77f8c4b | M54: =LEFT(L54, 7) -> 4172aae | N54: 46202 | O54: Revise README for Rulebook Examples | P54: sp-loop-milestone-07-loops-58-60
A55: loop-59 | B55: =A55 -> loop-59 | C55: REAL? backlog drain: encode all 33 queued candidates with cited approximate 2xK tables | D55: complete | E55: All remaining CandidateStudyCatalog REAL? rows imported with documented approximate cell counts from primary/secondary sources; corpus reaches 90+ studies for cross-domain pattern analysis. | F55: Does draining the REAL? backlog increase domain/mechanism coverage without breaking invariant harness — and how often does ExpectedDistortionType match observed DistortionType? | G55: Witnessed: 33 studies imported from REAL? backlog; corpus now 90+ studies. | H55: loop-60: TypePredictionMatch audit + ModelSummary refresh across full 90+ study corpus | I55: tradition-epidemiology | J55: =LOOKUP(I55, ResearchTraditions[TraditionId], ResearchTraditions[Name]) -> #VALUE! | K55: =LOOKUP(I55, ResearchTraditions[TraditionId], ResearchTraditions[CoreConcern]) -> #VALUE! | L55: 4172aaebbb6e52b0d89b890dff98c26ff77f8c4b | M55: =LEFT(L55, 7) -> 4172aae | N55: 46202 | O55: Revise README for Rulebook Examples | P55: sp-loop-milestone-07-loops-58-60
A56: loop-60 | B56: =A56 -> loop-60 | C56: Legacy prune: IsReversal = sign-flip; drop v2 meta and presentation layer | D56: complete | E56: IsReversal redefined as IsSignFlip (single reversal definition). Removed IsReversal_v2, DefinitionDelta, StrictReversalSubtype, IsParadoxExplained_v2, InstrumentScore, ScreeningVerdict, duplicate ModelSummary v2 counts (ReversalCountV2, PartialCount, ZeroStrengthCount, TypeCCount). Unanimous-vs-partial distinction lives in DistortionType A vs B only. | F56: Can the instrument shed legacy presentation and v2 meta fields without losing load-bearing taxonomy coordinates (DistortionType, SignalPurity, AllocationDirection)? | G56: Witnessed post-build: IsReversal equals IsSignFlip on all studies. ReversalCount counts sign-flips. Type B captures partial stratum disagreement without DefinitionDelta. ScreeningTier retained (derived from DistortionType). | H56: loop-61: DiscoveryHypotheses + DiscoveryFindings — first empirical discovery loop on the pruned instrument. | I56: tradition-dag | J56: =LOOKUP(I56, ResearchTraditions[TraditionId], ResearchTraditions[Name]) -> #VALUE! | K56: =LOOKUP(I56, ResearchTraditions[TraditionId], ResearchTraditions[CoreConcern]) -> #VALUE! | L56: 4172aaebbb6e52b0d89b890dff98c26ff77f8c4b | M56: =LEFT(L56, 7) -> 4172aae | N56: 46202 | O56: Revise README for Rulebook Examples | P56: sp-loop-milestone-07-loops-58-60
A57: loop-61 | B57: =A57 -> loop-61 | C57: Discovery loop: latent flip potential + pre-registered corpus findings | D57: complete | E57: DiscoveryHypotheses + DiscoveryFindings tables; TreatmentRankings sweep lookups (PooledGapCrossesZero, SweepPooledGapRange, LatentFlipPotential, AllocationFragility, StudyDomain); ModelSummary discovery aggregates | F57: At 96-study corpus scale, do pre-registered empirical hypotheses about allocation fragility, signal purity, domain patterns, and effect-size stability witness in the DAG? | G57: Witnessed post-build: 45/64 Type-D studies (70.3%) have LatentFlipPotential; SignFlipSignalPurityMax=0.483; stable Type-D avg PooledGap 0.102 vs latent 0.022; economics 0/8 sign-flips; epidemiology avg distortion 0.050 vs education 0.004. Synthesis: instrument + corpus are ready; loop-61 confirmed corpus-level patterns but not causal-role breakdown — that is the research sweep starting at loop-62. | H57: loop-62: research sweep 1 — causal role × manifest vs latent reversal (+ discovery infra + LoopReview protocol) | I57: tradition-epidemiology | J57: =LOOKUP(I57, ResearchTraditions[TraditionId], ResearchTraditions[Name]) -> #VALUE! | K57: =LOOKUP(I57, ResearchTraditions[TraditionId], ResearchTraditions[CoreConcern]) -> #VALUE! | L57: 7b3938e88201fb6c93b0fd0a11c235fea4a335c1 | M57: =LEFT(L57, 7) -> 7b3938e | N57: 46202 | O57: Enhance database schema and functions for DiscoveryHypotheses and DiscoveryFindings | P57: sp-loop-milestone-08-loop-61
A58: loop-62 | B58: =A58 -> loop-62 | C58: Research sweep 1: causal role × manifest vs latent reversal | D58: planned | E58: DiscoveryHypotheses H-causal-manifest + H-causal-latent; ObservedDistortionType lookup on CandidateStudyCatalog; Discovery UI screen (/discovery); LoopReview protocol — end-of-turn query vw_discovery_findings, update Conclusions if witnessed, defer vocabulary until review passes | F58: At 96-study scale, do confounder-labeled studies produce manifest sign-flips while collider/selection studies produce latent-only flips (PooledGapCrossesZero without IsSignFlip)? Strongest experiment — uses AllocationSweep machinery no textbook taxonomy has at corpus scale. Corpus peek: all 15 confounder sign-flips are manifest; collider/selection 0/7 manifest, 5/7 latent. | G58: Pre-build synthesis (loops 1–61): geometry complete (DistortionType A/B/C+/C−/D, SignalPurity, CorrectedGap, AllocationSweep); corpus at 96 studies; loop-61 witnessed H-latent-d/H-purity/H-small-effect/H-econ-zero/H-domain-dist but not mechanism-stratified reversal. LoopReview (end of turn): confirm or refute H-causal-* in vw_discovery_findings; decide whether ManifestReversal vs LatentReversal deserves first-class fields in loop-67+ or whether existing LatentFlipPotential + CausalRole suffice. | H58: loop-63: after LoopReview — paradox-explained × mechanism partition (do not start until loop-62 review documents pass/fail and vocabulary decision) | I58: tradition-epidemiology | J58: =LOOKUP(I58, ResearchTraditions[TraditionId], ResearchTraditions[Name]) -> #VALUE! | K58: =LOOKUP(I58, ResearchTraditions[TraditionId], ResearchTraditions[CoreConcern]) -> #VALUE! | M58: =LEFT(L58, 7)
A59: loop-63 | B59: =A59 -> loop-63 | C59: Research sweep 2: IsParadoxExplained × causal mechanism | D59: planned | E59: DiscoveryHypotheses H-explained-confounder + H-unexplained-nonconfounder; optional InvariantCheck inv-explained-sign-flip-confounder | F59: Does IsParadoxExplained track adjust-resolvable confounding rather than geometric distortion alone? Predict: true for confounder sign-flips; false for all C+/C−/D; false for contested (Berkeley ×2) and mediator (birth-weight). Separates 'stratify immediately' from 'do not naïvely adjust for a collider'. | G59: Corpus peek: 15/15 confounder sign-flips explained; 0/78 C+/C−/D explained; 3 unexplained Type B = berkeley-1973, berkeley-six-dept-1973, birth-weight-paradox (contested/mediator). LoopReview: if confirmed, promote Conclusion about adjustment boundary; if exceptions exist, classify as contested rows not counterexamples — do not widen IsParadoxExplained formula without review. | H59: loop-64: after LoopReview — formalize signal purity law from loop-61 (graduate H-purity to invariant, not re-run experiment) | I59: tradition-dag | J59: =LOOKUP(I59, ResearchTraditions[TraditionId], ResearchTraditions[Name]) -> #VALUE! | K59: =LOOKUP(I59, ResearchTraditions[TraditionId], ResearchTraditions[CoreConcern]) -> #VALUE! | M59: =LEFT(L59, 7)
A60: loop-64 | B60: =A60 -> loop-64 | C60: Research sweep 3: signal purity law — loop-61 H-purity → invariant + Conclusion | D60: planned | E60: InvariantCheck inv-sign-flip-signal-purity-max; Conclusion conc-signal-purity-ceiling; DiscoveryFinding refresh for H-purity with boundary-condition note | F60: Loop-61 confirmed SignFlipSignalPurityMax=0.483 (<0.5). Does this graduate from discovery finding to build-breaking invariant and witnessed Conclusion — or does the melanoma C+ near-miss (purity≈0.48, no sign-flip) require an explicit carve-out? | G60: NOT a new experiment — a review loop on loop-61 output. H-purity already confirmed; this turn decides whether it is instrument-law or corpus statistic. LoopReview: document melanoma-altman-1991 as known non-sign-flip boundary case; check Type A vs Type B purity separation; only add invariant if zero counterexamples among IsSignFlip=TRUE rows. | H60: loop-65: after LoopReview — catalog expectation falsification (type prediction audit + CorpusCatalogSummary match counts) | I60: tradition-dag | J60: =LOOKUP(I60, ResearchTraditions[TraditionId], ResearchTraditions[Name]) -> #VALUE! | K60: =LOOKUP(I60, ResearchTraditions[TraditionId], ResearchTraditions[CoreConcern]) -> #VALUE! | M60: =LEFT(L60, 7)
A61: loop-65 | B61: =A61 -> loop-65 | C61: Research sweep 4: catalog expectation falsification (type prediction audit) | D61: planned | E61: CorpusCatalogSummary TypePredictionMatchCount + TypePredictionMismatchCount; CandidateStudyCatalog ObservedDistortionType lookup (fixes broken type_prediction_match calc); DiscoveryHypotheses H-catalog-exact-match + H-catalog-flip-prediction | F61: When curators tag ExpectedDistortionType at import, how often does observed DistortionType match? Corpus peek: ~19% exact match, ~25% sign-flip prediction from Expected A∪B — catalog tags behave as mechanism priors not taxonomy predictors. Meta-research on curation discipline, not a paradox law. | G61: LoopReview: if match rate <50%, conclude catalog needs separate ExpectedSignFlip vs ExpectedDistortionType (or drop type prediction entirely); do NOT add ObservedDistortionType to Studies — keep it on catalog as audit trail only. Document biggest misprediction buckets (Expected A→D: 23 studies). | H61: loop-66: after LoopReview — domain heterogeneity under geometry controls + full sweep synthesis | I61: tradition-epidemiology | J61: =LOOKUP(I61, ResearchTraditions[TraditionId], ResearchTraditions[Name]) -> #VALUE! | K61: =LOOKUP(I61, ResearchTraditions[TraditionId], ResearchTraditions[CoreConcern]) -> #VALUE! | M61: =LEFT(L61, 7)
A62: loop-66 | B62: =A62 -> loop-66 | C62: Research sweep 5: domain screening + synthesis review | D62: planned | E62: DiscoveryHypotheses H-domain-flip-geometry-controlled; ModelSummary discovery rollup refresh; Conclusions rows from loops 62–66; loop-67+ direction decided only after synthesis | F62: Do domain flip-rate differences (economics 0%, legal/epi/sports ~27%) survive conditioning on max_stratum_imbalance — or are they catalog selection artifacts? Weakest experiment; ends with full synthesis of research sweep loops 62–66. | G62: Fold loop-61 partial findings (H-econ-zero, H-domain-dist, H-small-effect) into synthesis — do not re-run. LoopReview (synthesis): aggregate confirmed laws vs corpus-specific patterns vs falsified hypotheses; list vocabulary commitments deferred to loop-67+ (ManifestReversal/LatentReversal, catalog tag split, Discovery screen polish); write sweep summary in Conclusions table. | H62: loop-67: vocabulary landing turn — ONLY after loop-66 synthesis review confirms which findings deserve first-class fields vs remaining as DiscoveryFindings rows | I62: tradition-historical | J62: =LOOKUP(I62, ResearchTraditions[TraditionId], ResearchTraditions[Name]) -> #VALUE! | K62: =LOOKUP(I62, ResearchTraditions[TraditionId], ResearchTraditions[CoreConcern]) -> #VALUE! | M62: =LEFT(L62, 7)

Sheet Studies
A1: StudyId | B1: Name | C1: Title | D1: Source | E1: SourceUrl | F1: PublicationYear | G1: Domain | H1: IsSynthetic | I1: TotalCases | J1: CellCount | K1: TraditionId | L1: PrimaryResearcherId | M1: TraditionName | N1: TraditionCoreConern | O1: PrimaryResearcherName | P1: PrimaryResearcherAffiliation | Q1: DistortionType | R1: PolicyImplication | S1: AllocationDistortion | T1: SignalPurity | U1: IsSignFlip | V1: CorrectedWinner | W1: ConfoundingVariable | X1: CausalRole | Y1: IngestionCellParity | Z1: IngestionCompliance
A2: kidney-1986 | B2: =A2 -> kidney-1986 | C2: Kidney Stone Treatment Study (Charig et al. 1986) | D2: Charig CR et al. Comparison of treatment of renal calculi by open surgery, percutaneous nephrolithotomy, and extracorporeal shockwave lithotripsy. Br Med J. 1986;292:879. | E2: https://www.bmj.com/content/292/6524/879 | F2: 1986 | G2: medicine | H2: FALSE | I2: =SUMIFS(CaseCells!G2:G999,CaseCells!C2:C999, A2) -> 700 | J2: =COUNTIFS(CaseCells!C2:C999, A2) -> 4 | K2: tradition-historical | L2: researcher-blyth | M2: =LOOKUP(K2, ResearchTraditions[TraditionId], ResearchTraditions[Name]) -> #VALUE! | N2: =LOOKUP(K2, ResearchTraditions[TraditionId], ResearchTraditions[CoreConcern]) -> #VALUE! | O2: =LOOKUP(L2, Researchers[ResearcherId], Researchers[Name]) -> #VALUE! | P2: =LOOKUP(L2, Researchers[ResearcherId], Researchers[Affiliation]) -> #VALUE! | Q2: =LOOKUP(A2, TreatmentRankings[Study], TreatmentRankings[DistortionType]) -> #VALUE! | R2: =LOOKUP(A2, TreatmentRankings[Study], TreatmentRankings[CorrectedPolicyImplication]) -> #VALUE! | S2: =LOOKUP(A2, TreatmentRankings[Study], TreatmentRankings[AllocationDistortion]) -> #VALUE! | T2: =LOOKUP(A2, TreatmentRankings[Study], TreatmentRankings[SignalPurity]) -> #VALUE! | U2: =LOOKUP(A2, TreatmentRankings[Study], TreatmentRankings[IsSignFlip]) -> #VALUE! | V2: =LOOKUP(A2, TreatmentRankings[Study], TreatmentRankings[CorrectedWinner]) -> #VALUE! | W2: =LOOKUP(A2, StratumVariables[Study], StratumVariables[VariableName]) -> #VALUE! | X2: =LOOKUP(A2, StratumVariables[Study], StratumVariables[CausalRole]) -> #VALUE! | Y2: =AND(LOOKUP(A2, TreatmentRankings[Study], TreatmentRankings[StratumCount]) >= 2, J2 = LOOKUP(A2, TreatmentRankings[Study], TreatmentRankings[StratumCount]) * 2) -> #VALUE! | Z2: =IF(H2, "exempt-synthetic", IF(AND(Y2, LOOKUP(A2, StratumVariables[Study], StratumVariables[VariableName]) <> ""), "all", "partial")) -> #VALUE!
A3: balanced-synthetic | B3: =A3 -> balanced-synthetic | C3: Balanced Synthetic Study (degenerate case — reversal structurally impossible) | D3: Synthetic dataset constructed to demonstrate that perfectly balanced treatment allocation across strata algebraically prevents Simpson's Paradox. Not based on real data. | G3: synthetic | H3: TRUE | I3: =SUMIFS(CaseCells!G2:G999,CaseCells!C2:C999, A3) -> 400 | J3: =COUNTIFS(CaseCells!C2:C999, A3) -> 4 | K3: tradition-historical | M3: =LOOKUP(K3, ResearchTraditions[TraditionId], ResearchTraditions[Name]) -> #VALUE! | N3: =LOOKUP(K3, ResearchTraditions[TraditionId], ResearchTraditions[CoreConcern]) -> #VALUE! | O3: =LOOKUP(L3, Researchers[ResearcherId], Researchers[Name]) -> #VALUE! | P3: =LOOKUP(L3, Researchers[ResearcherId], Researchers[Affiliation]) -> #VALUE! | Q3: =LOOKUP(A3, TreatmentRankings[Study], TreatmentRankings[DistortionType]) -> #VALUE! | R3: =LOOKUP(A3, TreatmentRankings[Study], TreatmentRankings[CorrectedPolicyImplication]) -> #VALUE! | S3: =LOOKUP(A3, TreatmentRankings[Study], TreatmentRankings[AllocationDistortion]) -> #VALUE! | T3: =LOOKUP(A3, TreatmentRankings[Study], TreatmentRankings[SignalPurity]) -> #VALUE! | U3: =LOOKUP(A3, TreatmentRankings[Study], TreatmentRankings[IsSignFlip]) -> #VALUE! | V3: =LOOKUP(A3, TreatmentRankings[Study], TreatmentRankings[CorrectedWinner]) -> #VALUE! | W3: =LOOKUP(A3, StratumVariables[Study], StratumVariables[VariableName]) -> #VALUE! | X3: =LOOKUP(A3, StratumVariables[Study], StratumVariables[CausalRole]) -> #VALUE! | Y3: =AND(LOOKUP(A3, TreatmentRankings[Study], TreatmentRankings[StratumCount]) >= 2, J3 = LOOKUP(A3, TreatmentRankings[Study], TreatmentRankings[StratumCount]) * 2) -> #VALUE! | Z3: =IF(H3, "exempt-synthetic", IF(AND(Y3, LOOKUP(A3, StratumVariables[Study], StratumVariables[VariableName]) <> ""), "all", "partial")) -> #VALUE!
A4: kidney-balanced | B4: =A4 -> kidney-balanced | C4: Kidney Stone Counterfactual (balanced allocation — reversal algebraically impossible) | D4: Synthetic dataset derived from Charig 1986 kidney stone rates but with equal treatment allocation across strata (175 cases per cell). Demonstrates that the reversal in the original study is purely an allocation artifact. | G4: synthetic | H4: TRUE | I4: =SUMIFS(CaseCells!G2:G999,CaseCells!C2:C999, A4) -> 700 | J4: =COUNTIFS(CaseCells!C2:C999, A4) -> 4 | K4: tradition-historical | M4: =LOOKUP(K4, ResearchTraditions[TraditionId], ResearchTraditions[Name]) -> #VALUE! | N4: =LOOKUP(K4, ResearchTraditions[TraditionId], ResearchTraditions[CoreConcern]) -> #VALUE! | O4: =LOOKUP(L4, Researchers[ResearcherId], Researchers[Name]) -> #VALUE! | P4: =LOOKUP(L4, Researchers[ResearcherId], Researchers[Affiliation]) -> #VALUE! | Q4: =LOOKUP(A4, TreatmentRankings[Study], TreatmentRankings[DistortionType]) -> #VALUE! | R4: =LOOKUP(A4, TreatmentRankings[Study], TreatmentRankings[CorrectedPolicyImplication]) -> #VALUE! | S4: =LOOKUP(A4, TreatmentRankings[Study], TreatmentRankings[AllocationDistortion]) -> #VALUE! | T4: =LOOKUP(A4, TreatmentRankings[Study], TreatmentRankings[SignalPurity]) -> #VALUE! | U4: =LOOKUP(A4, TreatmentRankings[Study], TreatmentRankings[IsSignFlip]) -> #VALUE! | V4: =LOOKUP(A4, TreatmentRankings[Study], TreatmentRankings[CorrectedWinner]) -> #VALUE! | W4: =LOOKUP(A4, StratumVariables[Study], StratumVariables[VariableName]) -> #VALUE! | X4: =LOOKUP(A4, StratumVariables[Study], StratumVariables[CausalRole]) -> #VALUE! | Y4: =AND(LOOKUP(A4, TreatmentRankings[Study], TreatmentRankings[StratumCount]) >= 2, J4 = LOOKUP(A4, TreatmentRankings[Study], TreatmentRankings[StratumCount]) * 2) -> #VALUE! | Z4: =IF(H4, "exempt-synthetic", IF(AND(Y4, LOOKUP(A4, StratumVariables[Study], StratumVariables[VariableName]) <> ""), "all", "partial")) -> #VALUE!
A5: berkeley-1973 | B5: =A5 -> berkeley-1973 | C5: UC Berkeley Graduate Admissions (Bickel et al. 1975) — contested confounder | D5: Bickel PJ, Hammel EA, O'Connell JW. Sex Bias in Graduate Admissions: Data from Berkeley. Science. 1975;187:398-404. | E5: https://www.science.org/doi/10.1126/science.187.4175.398 | F5: 1975 | G5: social-science | H5: FALSE | I5: =SUMIFS(CaseCells!G2:G999,CaseCells!C2:C999, A5) -> 3228 | J5: =COUNTIFS(CaseCells!C2:C999, A5) -> 8 | K5: tradition-epidemiology | L5: researcher-greenland | M5: =LOOKUP(K5, ResearchTraditions[TraditionId], ResearchTraditions[Name]) -> #VALUE! | N5: =LOOKUP(K5, ResearchTraditions[TraditionId], ResearchTraditions[CoreConcern]) -> #VALUE! | O5: =LOOKUP(L5, Researchers[ResearcherId], Researchers[Name]) -> #VALUE! | P5: =LOOKUP(L5, Researchers[ResearcherId], Researchers[Affiliation]) -> #VALUE! | Q5: =LOOKUP(A5, TreatmentRankings[Study], TreatmentRankings[DistortionType]) -> #VALUE! | R5: =LOOKUP(A5, TreatmentRankings[Study], TreatmentRankings[CorrectedPolicyImplication]) -> #VALUE! | S5: =LOOKUP(A5, TreatmentRankings[Study], TreatmentRankings[AllocationDistortion]) -> #VALUE! | T5: =LOOKUP(A5, TreatmentRankings[Study], TreatmentRankings[SignalPurity]) -> #VALUE! | U5: =LOOKUP(A5, TreatmentRankings[Study], TreatmentRankings[IsSignFlip]) -> #VALUE! | V5: =LOOKUP(A5, TreatmentRankings[Study], TreatmentRankings[CorrectedWinner]) -> #VALUE! | W5: =LOOKUP(A5, StratumVariables[Study], StratumVariables[VariableName]) -> #VALUE! | X5: =LOOKUP(A5, StratumVariables[Study], StratumVariables[CausalRole]) -> #VALUE! | Y5: =AND(LOOKUP(A5, TreatmentRankings[Study], TreatmentRankings[StratumCount]) >= 2, J5 = LOOKUP(A5, TreatmentRankings[Study], TreatmentRankings[StratumCount]) * 2) -> #VALUE! | Z5: =IF(H5, "exempt-synthetic", IF(AND(Y5, LOOKUP(A5, StratumVariables[Study], StratumVariables[VariableName]) <> ""), "all", "partial")) -> #VALUE!
A6: compressed-synthetic | B6: =A6 -> compressed-synthetic | C6: Compressed Synthetic Study (type-C — allocation distortion without sign flip) | D6: Synthetic dataset constructed to demonstrate that allocation can distort the pooled signal (AllocationDistortion > 0) without reversing it (IsSignFlip=FALSE). Treatment A wins in every stratum and also wins pooled — but the pooled margin is compressed by differential allocation. This populates the type-C cell in the DistortionType taxonomy. | G6: synthetic | H6: TRUE | I6: =SUMIFS(CaseCells!G2:G999,CaseCells!C2:C999, A6) -> 400 | J6: =COUNTIFS(CaseCells!C2:C999, A6) -> 4 | K6: tradition-historical | M6: =LOOKUP(K6, ResearchTraditions[TraditionId], ResearchTraditions[Name]) -> #VALUE! | N6: =LOOKUP(K6, ResearchTraditions[TraditionId], ResearchTraditions[CoreConcern]) -> #VALUE! | O6: =LOOKUP(L6, Researchers[ResearcherId], Researchers[Name]) -> #VALUE! | P6: =LOOKUP(L6, Researchers[ResearcherId], Researchers[Affiliation]) -> #VALUE! | Q6: =LOOKUP(A6, TreatmentRankings[Study], TreatmentRankings[DistortionType]) -> #VALUE! | R6: =LOOKUP(A6, TreatmentRankings[Study], TreatmentRankings[CorrectedPolicyImplication]) -> #VALUE! | S6: =LOOKUP(A6, TreatmentRankings[Study], TreatmentRankings[AllocationDistortion]) -> #VALUE! | T6: =LOOKUP(A6, TreatmentRankings[Study], TreatmentRankings[SignalPurity]) -> #VALUE! | U6: =LOOKUP(A6, TreatmentRankings[Study], TreatmentRankings[IsSignFlip]) -> #VALUE! | V6: =LOOKUP(A6, TreatmentRankings[Study], TreatmentRankings[CorrectedWinner]) -> #VALUE! | W6: =LOOKUP(A6, StratumVariables[Study], StratumVariables[VariableName]) -> #VALUE! | X6: =LOOKUP(A6, StratumVariables[Study], StratumVariables[CausalRole]) -> #VALUE! | Y6: =AND(LOOKUP(A6, TreatmentRankings[Study], TreatmentRankings[StratumCount]) >= 2, J6 = LOOKUP(A6, TreatmentRankings[Study], TreatmentRankings[StratumCount]) * 2) -> #VALUE! | Z6: =IF(H6, "exempt-synthetic", IF(AND(Y6, LOOKUP(A6, StratumVariables[Study], StratumVariables[VariableName]) <> ""), "all", "partial")) -> #VALUE!
A7: reintjes-2000 | B7: =A7 -> reintjes-2000 | C7: Antibiotic Prophylaxis and UTI Rates in Dutch Hospitals (Reintjes et al. 2000) | D7: Reintjes R, de Boer A, van Pelt W, Mintjes-de Groot J. Simpson's paradox: an example from hospital epidemiology. Epidemiology. 2000;11(1):81-83. PMID: 10615849. | E7: https://pubmed.ncbi.nlm.nih.gov/10615849/ | F7: 2000 | G7: epidemiology | H7: FALSE | I7: =SUMIFS(CaseCells!G2:G999,CaseCells!C2:C999, A7) -> 3519 | J7: =COUNTIFS(CaseCells!C2:C999, A7) -> 4 | K7: tradition-epidemiology | L7: researcher-greenland | M7: =LOOKUP(K7, ResearchTraditions[TraditionId], ResearchTraditions[Name]) -> #VALUE! | N7: =LOOKUP(K7, ResearchTraditions[TraditionId], ResearchTraditions[CoreConcern]) -> #VALUE! | O7: =LOOKUP(L7, Researchers[ResearcherId], Researchers[Name]) -> #VALUE! | P7: =LOOKUP(L7, Researchers[ResearcherId], Researchers[Affiliation]) -> #VALUE! | Q7: =LOOKUP(A7, TreatmentRankings[Study], TreatmentRankings[DistortionType]) -> #VALUE! | R7: =LOOKUP(A7, TreatmentRankings[Study], TreatmentRankings[CorrectedPolicyImplication]) -> #VALUE! | S7: =LOOKUP(A7, TreatmentRankings[Study], TreatmentRankings[AllocationDistortion]) -> #VALUE! | T7: =LOOKUP(A7, TreatmentRankings[Study], TreatmentRankings[SignalPurity]) -> #VALUE! | U7: =LOOKUP(A7, TreatmentRankings[Study], TreatmentRankings[IsSignFlip]) -> #VALUE! | V7: =LOOKUP(A7, TreatmentRankings[Study], TreatmentRankings[CorrectedWinner]) -> #VALUE! | W7: =LOOKUP(A7, StratumVariables[Study], StratumVariables[VariableName]) -> #VALUE! | X7: =LOOKUP(A7, StratumVariables[Study], StratumVariables[CausalRole]) -> #VALUE! | Y7: =AND(LOOKUP(A7, TreatmentRankings[Study], TreatmentRankings[StratumCount]) >= 2, J7 = LOOKUP(A7, TreatmentRankings[Study], TreatmentRankings[StratumCount]) * 2) -> #VALUE! | Z7: =IF(H7, "exempt-synthetic", IF(AND(Y7, LOOKUP(A7, StratumVariables[Study], StratumVariables[VariableName]) <> ""), "all", "partial")) -> #VALUE!
A8: radelet-1981 | B8: =A8 -> radelet-1981 | C8: Racial Characteristics and the Death Penalty in Florida (Radelet 1981) | D8: Radelet ML. Racial characteristics and the imposition of the death penalty. American Sociological Review. 1981;46(6):918-927. | E8: https://www.jstor.org/stable/2095513 | F8: 1981 | G8: legal | H8: FALSE | I8: =SUMIFS(CaseCells!G2:G999,CaseCells!C2:C999, A8) -> 326 | J8: =COUNTIFS(CaseCells!C2:C999, A8) -> 4 | K8: tradition-epidemiology | L8: researcher-robins | M8: =LOOKUP(K8, ResearchTraditions[TraditionId], ResearchTraditions[Name]) -> #VALUE! | N8: =LOOKUP(K8, ResearchTraditions[TraditionId], ResearchTraditions[CoreConcern]) -> #VALUE! | O8: =LOOKUP(L8, Researchers[ResearcherId], Researchers[Name]) -> #VALUE! | P8: =LOOKUP(L8, Researchers[ResearcherId], Researchers[Affiliation]) -> #VALUE! | Q8: =LOOKUP(A8, TreatmentRankings[Study], TreatmentRankings[DistortionType]) -> #VALUE! | R8: =LOOKUP(A8, TreatmentRankings[Study], TreatmentRankings[CorrectedPolicyImplication]) -> #VALUE! | S8: =LOOKUP(A8, TreatmentRankings[Study], TreatmentRankings[AllocationDistortion]) -> #VALUE! | T8: =LOOKUP(A8, TreatmentRankings[Study], TreatmentRankings[SignalPurity]) -> #VALUE! | U8: =LOOKUP(A8, TreatmentRankings[Study], TreatmentRankings[IsSignFlip]) -> #VALUE! | V8: =LOOKUP(A8, TreatmentRankings[Study], TreatmentRankings[CorrectedWinner]) -> #VALUE! | W8: =LOOKUP(A8, StratumVariables[Study], StratumVariables[VariableName]) -> #VALUE! | X8: =LOOKUP(A8, StratumVariables[Study], StratumVariables[CausalRole]) -> #VALUE! | Y8: =AND(LOOKUP(A8, TreatmentRankings[Study], TreatmentRankings[StratumCount]) >= 2, J8 = LOOKUP(A8, TreatmentRankings[Study], TreatmentRankings[StratumCount]) * 2) -> #VALUE! | Z8: =IF(H8, "exempt-synthetic", IF(AND(Y8, LOOKUP(A8, StratumVariables[Study], StratumVariables[VariableName]) <> ""), "all", "partial")) -> #VALUE!
A9: jeter-justice-1997 | B9: =A9 -> jeter-justice-1997 | C9: Batting Averages: Derek Jeter vs David Justice 1995-1997 (Ross 2007) | D9: Ross KA. Repeating effects in baseball. College Mathematics Journal. 2007;38(3):205-210. Raw data from Baseball Almanac (official MLB records). | E9: https://www.baseball-almanac.com/players/player.php?p=jeterde01 | F9: 1997 | G9: sports | H9: FALSE | I9: =SUMIFS(CaseCells!G2:G999,CaseCells!C2:C999, A9) -> 2330 | J9: =COUNTIFS(CaseCells!C2:C999, A9) -> 6 | K9: tradition-historical | L9: researcher-blyth | M9: =LOOKUP(K9, ResearchTraditions[TraditionId], ResearchTraditions[Name]) -> #VALUE! | N9: =LOOKUP(K9, ResearchTraditions[TraditionId], ResearchTraditions[CoreConcern]) -> #VALUE! | O9: =LOOKUP(L9, Researchers[ResearcherId], Researchers[Name]) -> #VALUE! | P9: =LOOKUP(L9, Researchers[ResearcherId], Researchers[Affiliation]) -> #VALUE! | Q9: =LOOKUP(A9, TreatmentRankings[Study], TreatmentRankings[DistortionType]) -> #VALUE! | R9: =LOOKUP(A9, TreatmentRankings[Study], TreatmentRankings[CorrectedPolicyImplication]) -> #VALUE! | S9: =LOOKUP(A9, TreatmentRankings[Study], TreatmentRankings[AllocationDistortion]) -> #VALUE! | T9: =LOOKUP(A9, TreatmentRankings[Study], TreatmentRankings[SignalPurity]) -> #VALUE! | U9: =LOOKUP(A9, TreatmentRankings[Study], TreatmentRankings[IsSignFlip]) -> #VALUE! | V9: =LOOKUP(A9, TreatmentRankings[Study], TreatmentRankings[CorrectedWinner]) -> #VALUE! | W9: =LOOKUP(A9, StratumVariables[Study], StratumVariables[VariableName]) -> #VALUE! | X9: =LOOKUP(A9, StratumVariables[Study], StratumVariables[CausalRole]) -> #VALUE! | Y9: =AND(LOOKUP(A9, TreatmentRankings[Study], TreatmentRankings[StratumCount]) >= 2, J9 = LOOKUP(A9, TreatmentRankings[Study], TreatmentRankings[StratumCount]) * 2) -> #VALUE! | Z9: =IF(H9, "exempt-synthetic", IF(AND(Y9, LOOKUP(A9, StratumVariables[Study], StratumVariables[VariableName]) <> ""), "all", "partial")) -> #VALUE!
A10: appleton-1996 | B10: =A10 -> appleton-1996 | C10: Whickham Smoking Cohort — 20-year Mortality by Smoking Status (Appleton et al. 1996) | D10: Appleton DR, French JM, Vanderpump MPJ. Ignoring a covariate: An example of Simpson's paradox. The American Statistician. 1996;50(4):340-341. DOI: 10.2307/2684931. Data: Whickham (England) health survey 1972-74, 20-year follow-up. | E10: https://doi.org/10.2307/2684931 | F10: 1996 | G10: epidemiology | H10: FALSE | I10: =SUMIFS(CaseCells!G2:G999,CaseCells!C2:C999, A10) -> 1314 | J10: =COUNTIFS(CaseCells!C2:C999, A10) -> 14 | K10: tradition-epidemiology | L10: researcher-greenland | M10: =LOOKUP(K10, ResearchTraditions[TraditionId], ResearchTraditions[Name]) -> #VALUE! | N10: =LOOKUP(K10, ResearchTraditions[TraditionId], ResearchTraditions[CoreConcern]) -> #VALUE! | O10: =LOOKUP(L10, Researchers[ResearcherId], Researchers[Name]) -> #VALUE! | P10: =LOOKUP(L10, Researchers[ResearcherId], Researchers[Affiliation]) -> #VALUE! | Q10: =LOOKUP(A10, TreatmentRankings[Study], TreatmentRankings[DistortionType]) -> #VALUE! | R10: =LOOKUP(A10, TreatmentRankings[Study], TreatmentRankings[CorrectedPolicyImplication]) -> #VALUE! | S10: =LOOKUP(A10, TreatmentRankings[Study], TreatmentRankings[AllocationDistortion]) -> #VALUE! | T10: =LOOKUP(A10, TreatmentRankings[Study], TreatmentRankings[SignalPurity]) -> #VALUE! | U10: =LOOKUP(A10, TreatmentRankings[Study], TreatmentRankings[IsSignFlip]) -> #VALUE! | V10: =LOOKUP(A10, TreatmentRankings[Study], TreatmentRankings[CorrectedWinner]) -> #VALUE! | W10: =LOOKUP(A10, StratumVariables[Study], StratumVariables[VariableName]) -> #VALUE! | X10: =LOOKUP(A10, StratumVariables[Study], StratumVariables[CausalRole]) -> #VALUE! | Y10: =AND(LOOKUP(A10, TreatmentRankings[Study], TreatmentRankings[StratumCount]) >= 2, J10 = LOOKUP(A10, TreatmentRankings[Study], TreatmentRankings[StratumCount]) * 2) -> #VALUE! | Z10: =IF(H10, "exempt-synthetic", IF(AND(Y10, LOOKUP(A10, StratumVariables[Study], StratumVariables[VariableName]) <> ""), "all", "partial")) -> #VALUE!
A11: phe-covid-2021 | B11: =A11 -> phe-covid-2021 | C11: COVID-19 Delta Variant CFR: Vaccinated vs Unvaccinated by Age Group, UK 2021 (PHE Technical Briefing 20) | D11: Public Health England. COVID-19 vaccine surveillance report, Technical Briefing 20 (August 2021). Dataset: OpenIntro simpsons_paradox_covid, contributed by Matthew T. Brenneman, Embry-Riddle Aeronautical University. | E11: https://www.openintro.org/data/index.php?data=simpsons_paradox_covid | F11: 2021 | G11: epidemiology | H11: FALSE | I11: =SUMIFS(CaseCells!G2:G999,CaseCells!C2:C999, A11) -> 268166 | J11: =COUNTIFS(CaseCells!C2:C999, A11) -> 4 | K11: tradition-ai-fairness | L11: researcher-asudeh | M11: =LOOKUP(K11, ResearchTraditions[TraditionId], ResearchTraditions[Name]) -> #VALUE! | N11: =LOOKUP(K11, ResearchTraditions[TraditionId], ResearchTraditions[CoreConcern]) -> #VALUE! | O11: =LOOKUP(L11, Researchers[ResearcherId], Researchers[Name]) -> #VALUE! | P11: =LOOKUP(L11, Researchers[ResearcherId], Researchers[Affiliation]) -> #VALUE! | Q11: =LOOKUP(A11, TreatmentRankings[Study], TreatmentRankings[DistortionType]) -> #VALUE! | R11: =LOOKUP(A11, TreatmentRankings[Study], TreatmentRankings[CorrectedPolicyImplication]) -> #VALUE! | S11: =LOOKUP(A11, TreatmentRankings[Study], TreatmentRankings[AllocationDistortion]) -> #VALUE! | T11: =LOOKUP(A11, TreatmentRankings[Study], TreatmentRankings[SignalPurity]) -> #VALUE! | U11: =LOOKUP(A11, TreatmentRankings[Study], TreatmentRankings[IsSignFlip]) -> #VALUE! | V11: =LOOKUP(A11, TreatmentRankings[Study], TreatmentRankings[CorrectedWinner]) -> #VALUE! | W11: =LOOKUP(A11, StratumVariables[Study], StratumVariables[VariableName]) -> #VALUE! | X11: =LOOKUP(A11, StratumVariables[Study], StratumVariables[CausalRole]) -> #VALUE! | Y11: =AND(LOOKUP(A11, TreatmentRankings[Study], TreatmentRankings[StratumCount]) >= 2, J11 = LOOKUP(A11, TreatmentRankings[Study], TreatmentRankings[StratumCount]) * 2) -> #VALUE! | Z11: =IF(H11, "exempt-synthetic", IF(AND(Y11, LOOKUP(A11, StratumVariables[Study], StratumVariables[VariableName]) <> ""), "all", "partial")) -> #VALUE!
A12: hannan-1994 | B12: =A12 -> hannan-1994 | C12: CABG Surgery Volume and Mortality, New York State (Hannan et al. 1994 — type-C real witness) | D12: Hannan EL, Kilburn H Jr, Racz M, Shields E, Chassin MR. Improving the outcomes of coronary artery bypass surgery in New York State. JAMA. 1994;271(10):761-766. Risk-stratification by operative risk class. Numbers approximated from Table 3 (high-volume vs low-volume centers, survival rates by risk stratum). | E12: https://pubmed.ncbi.nlm.nih.gov/8107988/ | F12: 1994 | G12: medicine | H12: FALSE | I12: =SUMIFS(CaseCells!G2:G999,CaseCells!C2:C999, A12) -> 1100 | J12: =COUNTIFS(CaseCells!C2:C999, A12) -> 4 | K12: tradition-epidemiology | L12: researcher-robins | M12: =LOOKUP(K12, ResearchTraditions[TraditionId], ResearchTraditions[Name]) -> #VALUE! | N12: =LOOKUP(K12, ResearchTraditions[TraditionId], ResearchTraditions[CoreConcern]) -> #VALUE! | O12: =LOOKUP(L12, Researchers[ResearcherId], Researchers[Name]) -> #VALUE! | P12: =LOOKUP(L12, Researchers[ResearcherId], Researchers[Affiliation]) -> #VALUE! | Q12: =LOOKUP(A12, TreatmentRankings[Study], TreatmentRankings[DistortionType]) -> #VALUE! | R12: =LOOKUP(A12, TreatmentRankings[Study], TreatmentRankings[CorrectedPolicyImplication]) -> #VALUE! | S12: =LOOKUP(A12, TreatmentRankings[Study], TreatmentRankings[AllocationDistortion]) -> #VALUE! | T12: =LOOKUP(A12, TreatmentRankings[Study], TreatmentRankings[SignalPurity]) -> #VALUE! | U12: =LOOKUP(A12, TreatmentRankings[Study], TreatmentRankings[IsSignFlip]) -> #VALUE! | V12: =LOOKUP(A12, TreatmentRankings[Study], TreatmentRankings[CorrectedWinner]) -> #VALUE! | W12: =LOOKUP(A12, StratumVariables[Study], StratumVariables[VariableName]) -> #VALUE! | X12: =LOOKUP(A12, StratumVariables[Study], StratumVariables[CausalRole]) -> #VALUE! | Y12: =AND(LOOKUP(A12, TreatmentRankings[Study], TreatmentRankings[StratumCount]) >= 2, J12 = LOOKUP(A12, TreatmentRankings[Study], TreatmentRankings[StratumCount]) * 2) -> #VALUE! | Z12: =IF(H12, "exempt-synthetic", IF(AND(Y12, LOOKUP(A12, StratumVariables[Study], StratumVariables[VariableName]) <> ""), "all", "partial")) -> #VALUE!
A13: titanic-1912 | B13: =A13 -> titanic-1912 | C13: Titanic Passenger Survival by Class (British Board of Trade 1912) — type-C allocation inflation | D13: British Board of Trade. Report on the Loss of the 'Titanic' (S.S.). 1912. Exact casualty figures from Lord Mersey's inquiry. Passenger counts by class and sex from Table 5. | E13: https://www.titanicinquiry.org/BOTInq/BOTReport/botRep01.php | F13: 1912 | G13: social-science | H13: FALSE | I13: =SUMIFS(CaseCells!G2:G999,CaseCells!C2:C999, A13) -> 946 | J13: =COUNTIFS(CaseCells!C2:C999, A13) -> 4 | K13: tradition-historical | L13: researcher-blyth | M13: =LOOKUP(K13, ResearchTraditions[TraditionId], ResearchTraditions[Name]) -> #VALUE! | N13: =LOOKUP(K13, ResearchTraditions[TraditionId], ResearchTraditions[CoreConcern]) -> #VALUE! | O13: =LOOKUP(L13, Researchers[ResearcherId], Researchers[Name]) -> #VALUE! | P13: =LOOKUP(L13, Researchers[ResearcherId], Researchers[Affiliation]) -> #VALUE! | Q13: =LOOKUP(A13, TreatmentRankings[Study], TreatmentRankings[DistortionType]) -> #VALUE! | R13: =LOOKUP(A13, TreatmentRankings[Study], TreatmentRankings[CorrectedPolicyImplication]) -> #VALUE! | S13: =LOOKUP(A13, TreatmentRankings[Study], TreatmentRankings[AllocationDistortion]) -> #VALUE! | T13: =LOOKUP(A13, TreatmentRankings[Study], TreatmentRankings[SignalPurity]) -> #VALUE! | U13: =LOOKUP(A13, TreatmentRankings[Study], TreatmentRankings[IsSignFlip]) -> #VALUE! | V13: =LOOKUP(A13, TreatmentRankings[Study], TreatmentRankings[CorrectedWinner]) -> #VALUE! | W13: =LOOKUP(A13, StratumVariables[Study], StratumVariables[VariableName]) -> #VALUE! | X13: =LOOKUP(A13, StratumVariables[Study], StratumVariables[CausalRole]) -> #VALUE! | Y13: =AND(LOOKUP(A13, TreatmentRankings[Study], TreatmentRankings[StratumCount]) >= 2, J13 = LOOKUP(A13, TreatmentRankings[Study], TreatmentRankings[StratumCount]) * 2) -> #VALUE! | Z13: =IF(H13, "exempt-synthetic", IF(AND(Y13, LOOKUP(A13, StratumVariables[Study], StratumVariables[VariableName]) <> ""), "all", "partial")) -> #VALUE!
A14: birth-weight-paradox | B14: =A14 -> birth-weight-paradox | C14: Birth Weight Paradox: Infant Mortality by Maternal Smoking Status (Yerushalmy 1971 / Hernandez-Diaz 2006) — type-B partial reversal | D14: Yerushalmy J. The relationship of parents' cigarette smoking to outcome of pregnancy. Am J Epidemiol. 1971;93(6):443-456. Approximate numbers consistent with Table 2. See also: Hernandez-Diaz S, Schisterman EF, Hernan MA. The birth weight 'paradox' uncovered. Am J Epidemiol. 2006;164(11):1115-1120. | E14: https://pubmed.ncbi.nlm.nih.gov/5574838/ | F14: 1992 | G14: epidemiology | H14: FALSE | I14: =SUMIFS(CaseCells!G2:G999,CaseCells!C2:C999, A14) -> 7500 | J14: =COUNTIFS(CaseCells!C2:C999, A14) -> 4 | K14: tradition-dag | L14: researcher-dong-cai-zhao | M14: =LOOKUP(K14, ResearchTraditions[TraditionId], ResearchTraditions[Name]) -> #VALUE! | N14: =LOOKUP(K14, ResearchTraditions[TraditionId], ResearchTraditions[CoreConcern]) -> #VALUE! | O14: =LOOKUP(L14, Researchers[ResearcherId], Researchers[Name]) -> #VALUE! | P14: =LOOKUP(L14, Researchers[ResearcherId], Researchers[Affiliation]) -> #VALUE! | Q14: =LOOKUP(A14, TreatmentRankings[Study], TreatmentRankings[DistortionType]) -> #VALUE! | R14: =LOOKUP(A14, TreatmentRankings[Study], TreatmentRankings[CorrectedPolicyImplication]) -> #VALUE! | S14: =LOOKUP(A14, TreatmentRankings[Study], TreatmentRankings[AllocationDistortion]) -> #VALUE! | T14: =LOOKUP(A14, TreatmentRankings[Study], TreatmentRankings[SignalPurity]) -> #VALUE! | U14: =LOOKUP(A14, TreatmentRankings[Study], TreatmentRankings[IsSignFlip]) -> #VALUE! | V14: =LOOKUP(A14, TreatmentRankings[Study], TreatmentRankings[CorrectedWinner]) -> #VALUE! | W14: =LOOKUP(A14, StratumVariables[Study], StratumVariables[VariableName]) -> #VALUE! | X14: =LOOKUP(A14, StratumVariables[Study], StratumVariables[CausalRole]) -> #VALUE! | Y14: =AND(LOOKUP(A14, TreatmentRankings[Study], TreatmentRankings[StratumCount]) >= 2, J14 = LOOKUP(A14, TreatmentRankings[Study], TreatmentRankings[StratumCount]) * 2) -> #VALUE! | Z14: =IF(H14, "exempt-synthetic", IF(AND(Y14, LOOKUP(A14, StratumVariables[Study], StratumVariables[VariableName]) <> ""), "all", "partial")) -> #VALUE!
A15: melanoma-altman-1991 | B15: =A15 -> melanoma-altman-1991 | C15: Melanoma 10-Year Survival by Sex and Tumor Thickness (Altman 1991 / Balch 2001) — type-C allocation inflation | D15: Altman DG. Practical Statistics for Medical Research. Chapman & Hall; 1991. Chapter 14, Table 14.3. Tumor thickness and sex as predictors of melanoma survival. Consistent with Balch CM et al. J Clin Oncol. 2001;19(16):3622-3634. | E15: https://pubmed.ncbi.nlm.nih.gov/11504744/ | F15: 1991 | G15: medicine | H15: FALSE | I15: =SUMIFS(CaseCells!G2:G999,CaseCells!C2:C999, A15) -> 400 | J15: =COUNTIFS(CaseCells!C2:C999, A15) -> 4 | K15: tradition-epidemiology | L15: researcher-greenland | M15: =LOOKUP(K15, ResearchTraditions[TraditionId], ResearchTraditions[Name]) -> #VALUE! | N15: =LOOKUP(K15, ResearchTraditions[TraditionId], ResearchTraditions[CoreConcern]) -> #VALUE! | O15: =LOOKUP(L15, Researchers[ResearcherId], Researchers[Name]) -> #VALUE! | P15: =LOOKUP(L15, Researchers[ResearcherId], Researchers[Affiliation]) -> #VALUE! | Q15: =LOOKUP(A15, TreatmentRankings[Study], TreatmentRankings[DistortionType]) -> #VALUE! | R15: =LOOKUP(A15, TreatmentRankings[Study], TreatmentRankings[CorrectedPolicyImplication]) -> #VALUE! | S15: =LOOKUP(A15, TreatmentRankings[Study], TreatmentRankings[AllocationDistortion]) -> #VALUE! | T15: =LOOKUP(A15, TreatmentRankings[Study], TreatmentRankings[SignalPurity]) -> #VALUE! | U15: =LOOKUP(A15, TreatmentRankings[Study], TreatmentRankings[IsSignFlip]) -> #VALUE! | V15: =LOOKUP(A15, TreatmentRankings[Study], TreatmentRankings[CorrectedWinner]) -> #VALUE! | W15: =LOOKUP(A15, StratumVariables[Study], StratumVariables[VariableName]) -> #VALUE! | X15: =LOOKUP(A15, StratumVariables[Study], StratumVariables[CausalRole]) -> #VALUE! | Y15: =AND(LOOKUP(A15, TreatmentRankings[Study], TreatmentRankings[StratumCount]) >= 2, J15 = LOOKUP(A15, TreatmentRankings[Study], TreatmentRankings[StratumCount]) * 2) -> #VALUE! | Z15: =IF(H15, "exempt-synthetic", IF(AND(Y15, LOOKUP(A15, StratumVariables[Study], StratumVariables[VariableName]) <> ""), "all", "partial")) -> #VALUE!
A16: coffee-tverdal-2020 | B16: =A16 -> coffee-tverdal-2020 | C16: Coffee Consumption and Coronary Heart Disease by Smoking Status (Tverdal et al. 2020) — type-D no distortion | D16: Tverdal A, Selmer R, Cohen JM, Thelle DS. Coffee consumption and mortality from cardiovascular diseases and total mortality: Does the brewing method matter? Eur J Prev Cardiol. 2020;27(18):1986-1993. Approximate cell frequencies from Table 2 stratified by smoking status. | E16: https://pubmed.ncbi.nlm.nih.gov/31771349/ | F16: 2020 | G16: epidemiology | H16: FALSE | I16: =SUMIFS(CaseCells!G2:G999,CaseCells!C2:C999, A16) -> 4000 | J16: =COUNTIFS(CaseCells!C2:C999, A16) -> 4 | K16: tradition-epidemiology | L16: researcher-greenland | M16: =LOOKUP(K16, ResearchTraditions[TraditionId], ResearchTraditions[Name]) -> #VALUE! | N16: =LOOKUP(K16, ResearchTraditions[TraditionId], ResearchTraditions[CoreConcern]) -> #VALUE! | O16: =LOOKUP(L16, Researchers[ResearcherId], Researchers[Name]) -> #VALUE! | P16: =LOOKUP(L16, Researchers[ResearcherId], Researchers[Affiliation]) -> #VALUE! | Q16: =LOOKUP(A16, TreatmentRankings[Study], TreatmentRankings[DistortionType]) -> #VALUE! | R16: =LOOKUP(A16, TreatmentRankings[Study], TreatmentRankings[CorrectedPolicyImplication]) -> #VALUE! | S16: =LOOKUP(A16, TreatmentRankings[Study], TreatmentRankings[AllocationDistortion]) -> #VALUE! | T16: =LOOKUP(A16, TreatmentRankings[Study], TreatmentRankings[SignalPurity]) -> #VALUE! | U16: =LOOKUP(A16, TreatmentRankings[Study], TreatmentRankings[IsSignFlip]) -> #VALUE! | V16: =LOOKUP(A16, TreatmentRankings[Study], TreatmentRankings[CorrectedWinner]) -> #VALUE! | W16: =LOOKUP(A16, StratumVariables[Study], StratumVariables[VariableName]) -> #VALUE! | X16: =LOOKUP(A16, StratumVariables[Study], StratumVariables[CausalRole]) -> #VALUE! | Y16: =AND(LOOKUP(A16, TreatmentRankings[Study], TreatmentRankings[StratumCount]) >= 2, J16 = LOOKUP(A16, TreatmentRankings[Study], TreatmentRankings[StratumCount]) * 2) -> #VALUE! | Z16: =IF(H16, "exempt-synthetic", IF(AND(Y16, LOOKUP(A16, StratumVariables[Study], StratumVariables[VariableName]) <> ""), "all", "partial")) -> #VALUE!
A17: sat-wainer-1986 | B17: =A17 -> sat-wainer-1986 | C17: SAT Math Scores: High- vs Low-Participation States by School Spending (Wainer 1986) — type-B partial reversal | D17: Wainer H. The SAT as a social indicator: A pretty bad idea. In: Wainer H, ed. Drawing Inferences from Self-Selected Samples. Springer; 1986:7-35. Approximate success-rate encoding (score ≥ 500 threshold) consistent with Table 1 state-level data. | E17: https://link.springer.com/book/10.1007/978-1-4612-4976-4 | F17: 1986 | G17: education | H17: FALSE | I17: =SUMIFS(CaseCells!G2:G999,CaseCells!C2:C999, A17) -> 1150 | J17: =COUNTIFS(CaseCells!C2:C999, A17) -> 4 | K17: tradition-historical | L17: researcher-blyth | M17: =LOOKUP(K17, ResearchTraditions[TraditionId], ResearchTraditions[Name]) -> #VALUE! | N17: =LOOKUP(K17, ResearchTraditions[TraditionId], ResearchTraditions[CoreConcern]) -> #VALUE! | O17: =LOOKUP(L17, Researchers[ResearcherId], Researchers[Name]) -> #VALUE! | P17: =LOOKUP(L17, Researchers[ResearcherId], Researchers[Affiliation]) -> #VALUE! | Q17: =LOOKUP(A17, TreatmentRankings[Study], TreatmentRankings[DistortionType]) -> #VALUE! | R17: =LOOKUP(A17, TreatmentRankings[Study], TreatmentRankings[CorrectedPolicyImplication]) -> #VALUE! | S17: =LOOKUP(A17, TreatmentRankings[Study], TreatmentRankings[AllocationDistortion]) -> #VALUE! | T17: =LOOKUP(A17, TreatmentRankings[Study], TreatmentRankings[SignalPurity]) -> #VALUE! | U17: =LOOKUP(A17, TreatmentRankings[Study], TreatmentRankings[IsSignFlip]) -> #VALUE! | V17: =LOOKUP(A17, TreatmentRankings[Study], TreatmentRankings[CorrectedWinner]) -> #VALUE! | W17: =LOOKUP(A17, StratumVariables[Study], StratumVariables[VariableName]) -> #VALUE! | X17: =LOOKUP(A17, StratumVariables[Study], StratumVariables[CausalRole]) -> #VALUE! | Y17: =AND(LOOKUP(A17, TreatmentRankings[Study], TreatmentRankings[StratumCount]) >= 2, J17 = LOOKUP(A17, TreatmentRankings[Study], TreatmentRankings[StratumCount]) * 2) -> #VALUE! | Z17: =IF(H17, "exempt-synthetic", IF(AND(Y17, LOOKUP(A17, StratumVariables[Study], StratumVariables[VariableName]) <> ""), "all", "partial")) -> #VALUE!
A18: rogers-nicewander-1988 | B18: =A18 -> rogers-nicewander-1988 | C18: Baseball Batting Averages: Lefebvre vs Fairly World Series (Day 1994 / baseball paradox canon) | D18: Day SM. Simpson's Paradox in MLB. AMATYC Journal 1994. Table 1: Ron Fairly vs Jim Lefebvre, two consecutive World Series. Encoded as position_group strata (infield/outfield proxy for series split). Hits/at-bats as Successes/Cases. | E18: https://doi.org/10.2307/2685261 | F18: 1988 | G18: sports | H18: FALSE | I18: =SUMIFS(CaseCells!G2:G999,CaseCells!C2:C999, A18) -> 58 | J18: =COUNTIFS(CaseCells!C2:C999, A18) -> 4 | K18: tradition-historical | L18: researcher-blyth | M18: =LOOKUP(K18, ResearchTraditions[TraditionId], ResearchTraditions[Name]) -> #VALUE! | N18: =LOOKUP(K18, ResearchTraditions[TraditionId], ResearchTraditions[CoreConcern]) -> #VALUE! | O18: =LOOKUP(L18, Researchers[ResearcherId], Researchers[Name]) -> #VALUE! | P18: =LOOKUP(L18, Researchers[ResearcherId], Researchers[Affiliation]) -> #VALUE! | Q18: =LOOKUP(A18, TreatmentRankings[Study], TreatmentRankings[DistortionType]) -> #VALUE! | R18: =LOOKUP(A18, TreatmentRankings[Study], TreatmentRankings[CorrectedPolicyImplication]) -> #VALUE! | S18: =LOOKUP(A18, TreatmentRankings[Study], TreatmentRankings[AllocationDistortion]) -> #VALUE! | T18: =LOOKUP(A18, TreatmentRankings[Study], TreatmentRankings[SignalPurity]) -> #VALUE! | U18: =LOOKUP(A18, TreatmentRankings[Study], TreatmentRankings[IsSignFlip]) -> #VALUE! | V18: =LOOKUP(A18, TreatmentRankings[Study], TreatmentRankings[CorrectedWinner]) -> #VALUE! | W18: =LOOKUP(A18, StratumVariables[Study], StratumVariables[VariableName]) -> #VALUE! | X18: =LOOKUP(A18, StratumVariables[Study], StratumVariables[CausalRole]) -> #VALUE! | Y18: =AND(LOOKUP(A18, TreatmentRankings[Study], TreatmentRankings[StratumCount]) >= 2, J18 = LOOKUP(A18, TreatmentRankings[Study], TreatmentRankings[StratumCount]) * 2) -> #VALUE! | Z18: =IF(H18, "exempt-synthetic", IF(AND(Y18, LOOKUP(A18, StratumVariables[Study], StratumVariables[VariableName]) <> ""), "all", "partial")) -> #VALUE!
A19: lucente-baseball-1995 | B19: =A19 -> lucente-baseball-1995 | C19: 1995 NL Batting: Monthly Split Paradox (Lucent 1995 classroom example) | D19: Lucent J. Teaching Statistics 1995;17(2):44-46. Approximate monthly-split hits/at-bats consistent with cited classroom Bagwell comparison pattern. | F19: 1995 | G19: sports | H19: FALSE | I19: =SUMIFS(CaseCells!G2:G999,CaseCells!C2:C999, A19) -> 690 | J19: =COUNTIFS(CaseCells!C2:C999, A19) -> 4 | K19: tradition-historical | L19: researcher-blyth | M19: =LOOKUP(K19, ResearchTraditions[TraditionId], ResearchTraditions[Name]) -> #VALUE! | N19: =LOOKUP(K19, ResearchTraditions[TraditionId], ResearchTraditions[CoreConcern]) -> #VALUE! | O19: =LOOKUP(L19, Researchers[ResearcherId], Researchers[Name]) -> #VALUE! | P19: =LOOKUP(L19, Researchers[ResearcherId], Researchers[Affiliation]) -> #VALUE! | Q19: =LOOKUP(A19, TreatmentRankings[Study], TreatmentRankings[DistortionType]) -> #VALUE! | R19: =LOOKUP(A19, TreatmentRankings[Study], TreatmentRankings[CorrectedPolicyImplication]) -> #VALUE! | S19: =LOOKUP(A19, TreatmentRankings[Study], TreatmentRankings[AllocationDistortion]) -> #VALUE! | T19: =LOOKUP(A19, TreatmentRankings[Study], TreatmentRankings[SignalPurity]) -> #VALUE! | U19: =LOOKUP(A19, TreatmentRankings[Study], TreatmentRankings[IsSignFlip]) -> #VALUE! | V19: =LOOKUP(A19, TreatmentRankings[Study], TreatmentRankings[CorrectedWinner]) -> #VALUE! | W19: =LOOKUP(A19, StratumVariables[Study], StratumVariables[VariableName]) -> #VALUE! | X19: =LOOKUP(A19, StratumVariables[Study], StratumVariables[CausalRole]) -> #VALUE! | Y19: =AND(LOOKUP(A19, TreatmentRankings[Study], TreatmentRankings[StratumCount]) >= 2, J19 = LOOKUP(A19, TreatmentRankings[Study], TreatmentRankings[StratumCount]) * 2) -> #VALUE! | Z19: =IF(H19, "exempt-synthetic", IF(AND(Y19, LOOKUP(A19, StratumVariables[Study], StratumVariables[VariableName]) <> ""), "all", "partial")) -> #VALUE!
A20: wilson-batting-2000 | B20: =A20 -> wilson-batting-2000 | C20: Baseball Averages by Inning Half (Wilson 2000 STATS annual) | D20: Wilson JD. STATS 2000 baseball annual Simpson's paradox example. Early vs late innings split; hits/at-bats approximated from published teaching summary. | F20: 2000 | G20: sports | H20: FALSE | I20: =SUMIFS(CaseCells!G2:G999,CaseCells!C2:C999, A20) -> 380 | J20: =COUNTIFS(CaseCells!C2:C999, A20) -> 4 | K20: tradition-historical | L20: researcher-blyth | M20: =LOOKUP(K20, ResearchTraditions[TraditionId], ResearchTraditions[Name]) -> #VALUE! | N20: =LOOKUP(K20, ResearchTraditions[TraditionId], ResearchTraditions[CoreConcern]) -> #VALUE! | O20: =LOOKUP(L20, Researchers[ResearcherId], Researchers[Name]) -> #VALUE! | P20: =LOOKUP(L20, Researchers[ResearcherId], Researchers[Affiliation]) -> #VALUE! | Q20: =LOOKUP(A20, TreatmentRankings[Study], TreatmentRankings[DistortionType]) -> #VALUE! | R20: =LOOKUP(A20, TreatmentRankings[Study], TreatmentRankings[CorrectedPolicyImplication]) -> #VALUE! | S20: =LOOKUP(A20, TreatmentRankings[Study], TreatmentRankings[AllocationDistortion]) -> #VALUE! | T20: =LOOKUP(A20, TreatmentRankings[Study], TreatmentRankings[SignalPurity]) -> #VALUE! | U20: =LOOKUP(A20, TreatmentRankings[Study], TreatmentRankings[IsSignFlip]) -> #VALUE! | V20: =LOOKUP(A20, TreatmentRankings[Study], TreatmentRankings[CorrectedWinner]) -> #VALUE! | W20: =LOOKUP(A20, StratumVariables[Study], StratumVariables[VariableName]) -> #VALUE! | X20: =LOOKUP(A20, StratumVariables[Study], StratumVariables[CausalRole]) -> #VALUE! | Y20: =AND(LOOKUP(A20, TreatmentRankings[Study], TreatmentRankings[StratumCount]) >= 2, J20 = LOOKUP(A20, TreatmentRankings[Study], TreatmentRankings[StratumCount]) * 2) -> #VALUE! | Z20: =IF(H20, "exempt-synthetic", IF(AND(Y20, LOOKUP(A20, StratumVariables[Study], StratumVariables[VariableName]) <> ""), "all", "partial")) -> #VALUE!
A21: clemens-bly-1998 | B21: =A21 -> clemens-bly-1998 | C21: Clemens vs Bly 1998: Home/Away Batting Split Paradox | D21: Standard APBA/baseball paradox example aggregated from 1998 MLB game logs into home/away strata. Approximate hits/at-bats from published teaching materials. | F21: 1998 | G21: sports | H21: FALSE | I21: =SUMIFS(CaseCells!G2:G999,CaseCells!C2:C999, A21) -> 295 | J21: =COUNTIFS(CaseCells!C2:C999, A21) -> 4 | K21: tradition-historical | L21: researcher-blyth | M21: =LOOKUP(K21, ResearchTraditions[TraditionId], ResearchTraditions[Name]) -> #VALUE! | N21: =LOOKUP(K21, ResearchTraditions[TraditionId], ResearchTraditions[CoreConcern]) -> #VALUE! | O21: =LOOKUP(L21, Researchers[ResearcherId], Researchers[Name]) -> #VALUE! | P21: =LOOKUP(L21, Researchers[ResearcherId], Researchers[Affiliation]) -> #VALUE! | Q21: =LOOKUP(A21, TreatmentRankings[Study], TreatmentRankings[DistortionType]) -> #VALUE! | R21: =LOOKUP(A21, TreatmentRankings[Study], TreatmentRankings[CorrectedPolicyImplication]) -> #VALUE! | S21: =LOOKUP(A21, TreatmentRankings[Study], TreatmentRankings[AllocationDistortion]) -> #VALUE! | T21: =LOOKUP(A21, TreatmentRankings[Study], TreatmentRankings[SignalPurity]) -> #VALUE! | U21: =LOOKUP(A21, TreatmentRankings[Study], TreatmentRankings[IsSignFlip]) -> #VALUE! | V21: =LOOKUP(A21, TreatmentRankings[Study], TreatmentRankings[CorrectedWinner]) -> #VALUE! | W21: =LOOKUP(A21, StratumVariables[Study], StratumVariables[VariableName]) -> #VALUE! | X21: =LOOKUP(A21, StratumVariables[Study], StratumVariables[CausalRole]) -> #VALUE! | Y21: =AND(LOOKUP(A21, TreatmentRankings[Study], TreatmentRankings[StratumCount]) >= 2, J21 = LOOKUP(A21, TreatmentRankings[Study], TreatmentRankings[StratumCount]) * 2) -> #VALUE! | Z21: =IF(H21, "exempt-synthetic", IF(AND(Y21, LOOKUP(A21, StratumVariables[Study], StratumVariables[VariableName]) <> ""), "all", "partial")) -> #VALUE!
A22: open-university-1975 | B22: =A22 -> open-university-1975 | C22: Open University Exam Pass Rates by Gender and Age Band (1975) | D22: Open University Statistics course canonical example. Pass/fail counts by gender (A=male, B=female) stratified by age band; approximated from OU M248 teaching materials and Blyth (1972) reversal structure. | F22: 1975 | G22: education | H22: FALSE | I22: =SUMIFS(CaseCells!G2:G999,CaseCells!C2:C999, A22) -> 2523 | J22: =COUNTIFS(CaseCells!C2:C999, A22) -> 6 | K22: tradition-historical | L22: researcher-blyth | M22: =LOOKUP(K22, ResearchTraditions[TraditionId], ResearchTraditions[Name]) -> #VALUE! | N22: =LOOKUP(K22, ResearchTraditions[TraditionId], ResearchTraditions[CoreConcern]) -> #VALUE! | O22: =LOOKUP(L22, Researchers[ResearcherId], Researchers[Name]) -> #VALUE! | P22: =LOOKUP(L22, Researchers[ResearcherId], Researchers[Affiliation]) -> #VALUE! | Q22: =LOOKUP(A22, TreatmentRankings[Study], TreatmentRankings[DistortionType]) -> #VALUE! | R22: =LOOKUP(A22, TreatmentRankings[Study], TreatmentRankings[CorrectedPolicyImplication]) -> #VALUE! | S22: =LOOKUP(A22, TreatmentRankings[Study], TreatmentRankings[AllocationDistortion]) -> #VALUE! | T22: =LOOKUP(A22, TreatmentRankings[Study], TreatmentRankings[SignalPurity]) -> #VALUE! | U22: =LOOKUP(A22, TreatmentRankings[Study], TreatmentRankings[IsSignFlip]) -> #VALUE! | V22: =LOOKUP(A22, TreatmentRankings[Study], TreatmentRankings[CorrectedWinner]) -> #VALUE! | W22: =LOOKUP(A22, StratumVariables[Study], StratumVariables[VariableName]) -> #VALUE! | X22: =LOOKUP(A22, StratumVariables[Study], StratumVariables[CausalRole]) -> #VALUE! | Y22: =AND(LOOKUP(A22, TreatmentRankings[Study], TreatmentRankings[StratumCount]) >= 2, J22 = LOOKUP(A22, TreatmentRankings[Study], TreatmentRankings[StratumCount]) * 2) -> #VALUE! | Z22: =IF(H22, "exempt-synthetic", IF(AND(Y22, LOOKUP(A22, StratumVariables[Study], StratumVariables[VariableName]) <> ""), "all", "partial")) -> #VALUE!
A23: pisa-immigration-2015 | B23: =A23 -> pisa-immigration-2015 | C23: PISA Reading Scores: Native vs Immigrant Students by Country Pair | D23: OECD PISA 2015 microdata aggregation collapsed to two countries (Finland vs Mexico proxy strata). Success = reading score ≥ proficiency level 3; counts approximated from OECD published tables. | E23: https://www.oecd.org/pisa/data/ | F23: 2015 | G23: education | H23: FALSE | I23: =SUMIFS(CaseCells!G2:G999,CaseCells!C2:C999, A23) -> 1220 | J23: =COUNTIFS(CaseCells!C2:C999, A23) -> 4 | K23: tradition-epidemiology | L23: researcher-greenland | M23: =LOOKUP(K23, ResearchTraditions[TraditionId], ResearchTraditions[Name]) -> #VALUE! | N23: =LOOKUP(K23, ResearchTraditions[TraditionId], ResearchTraditions[CoreConcern]) -> #VALUE! | O23: =LOOKUP(L23, Researchers[ResearcherId], Researchers[Name]) -> #VALUE! | P23: =LOOKUP(L23, Researchers[ResearcherId], Researchers[Affiliation]) -> #VALUE! | Q23: =LOOKUP(A23, TreatmentRankings[Study], TreatmentRankings[DistortionType]) -> #VALUE! | R23: =LOOKUP(A23, TreatmentRankings[Study], TreatmentRankings[CorrectedPolicyImplication]) -> #VALUE! | S23: =LOOKUP(A23, TreatmentRankings[Study], TreatmentRankings[AllocationDistortion]) -> #VALUE! | T23: =LOOKUP(A23, TreatmentRankings[Study], TreatmentRankings[SignalPurity]) -> #VALUE! | U23: =LOOKUP(A23, TreatmentRankings[Study], TreatmentRankings[IsSignFlip]) -> #VALUE! | V23: =LOOKUP(A23, TreatmentRankings[Study], TreatmentRankings[CorrectedWinner]) -> #VALUE! | W23: =LOOKUP(A23, StratumVariables[Study], StratumVariables[VariableName]) -> #VALUE! | X23: =LOOKUP(A23, StratumVariables[Study], StratumVariables[CausalRole]) -> #VALUE! | Y23: =AND(LOOKUP(A23, TreatmentRankings[Study], TreatmentRankings[StratumCount]) >= 2, J23 = LOOKUP(A23, TreatmentRankings[Study], TreatmentRankings[StratumCount]) * 2) -> #VALUE! | Z23: =IF(H23, "exempt-synthetic", IF(AND(Y23, LOOKUP(A23, StratumVariables[Study], StratumVariables[VariableName]) <> ""), "all", "partial")) -> #VALUE!
A24: wainer-sat-states-1992 | B24: =A24 -> wainer-sat-states-1992 | C24: SAT State Averages by Geographic Region (Wainer 1992 extension) | D24: Wainer H. Am Psychologist 1992;47(7):929. Extension of SAT self-selection paradox with NE vs South region strata. Approximate counts from Wainer (1986) Table 1 pattern. | F24: 1992 | G24: education | H24: FALSE | I24: =SUMIFS(CaseCells!G2:G999,CaseCells!C2:C999, A24) -> 1350 | J24: =COUNTIFS(CaseCells!C2:C999, A24) -> 4 | K24: tradition-historical | L24: researcher-blyth | M24: =LOOKUP(K24, ResearchTraditions[TraditionId], ResearchTraditions[Name]) -> #VALUE! | N24: =LOOKUP(K24, ResearchTraditions[TraditionId], ResearchTraditions[CoreConcern]) -> #VALUE! | O24: =LOOKUP(L24, Researchers[ResearcherId], Researchers[Name]) -> #VALUE! | P24: =LOOKUP(L24, Researchers[ResearcherId], Researchers[Affiliation]) -> #VALUE! | Q24: =LOOKUP(A24, TreatmentRankings[Study], TreatmentRankings[DistortionType]) -> #VALUE! | R24: =LOOKUP(A24, TreatmentRankings[Study], TreatmentRankings[CorrectedPolicyImplication]) -> #VALUE! | S24: =LOOKUP(A24, TreatmentRankings[Study], TreatmentRankings[AllocationDistortion]) -> #VALUE! | T24: =LOOKUP(A24, TreatmentRankings[Study], TreatmentRankings[SignalPurity]) -> #VALUE! | U24: =LOOKUP(A24, TreatmentRankings[Study], TreatmentRankings[IsSignFlip]) -> #VALUE! | V24: =LOOKUP(A24, TreatmentRankings[Study], TreatmentRankings[CorrectedWinner]) -> #VALUE! | W24: =LOOKUP(A24, StratumVariables[Study], StratumVariables[VariableName]) -> #VALUE! | X24: =LOOKUP(A24, StratumVariables[Study], StratumVariables[CausalRole]) -> #VALUE! | Y24: =AND(LOOKUP(A24, TreatmentRankings[Study], TreatmentRankings[StratumCount]) >= 2, J24 = LOOKUP(A24, TreatmentRankings[Study], TreatmentRankings[StratumCount]) * 2) -> #VALUE! | Z24: =IF(H24, "exempt-synthetic", IF(AND(Y24, LOOKUP(A24, StratumVariables[Study], StratumVariables[VariableName]) <> ""), "all", "partial")) -> #VALUE!
A25: folic-acid-neural-tube-1991 | B25: =A25 -> folic-acid-neural-tube-1991 | C25: Folic Acid and Neural Tube Defects by Maternal Age (Czeizel & Dudas 1992) | D25: Czeizel AE, Dudas I. NEJM 1992;327(26):1832-1835. Aggregate trial NTD counts (0/2104 vitamin vs 6/2052 control) stratified by maternal age (<28 vs ≥28) using Hungarian surveillance age distribution approximations. | E25: https://pubmed.ncbi.nlm.nih.gov/1307234/ | F25: 1992 | G25: medicine | H25: FALSE | I25: =SUMIFS(CaseCells!G2:G999,CaseCells!C2:C999, A25) -> 4156 | J25: =COUNTIFS(CaseCells!C2:C999, A25) -> 4 | K25: tradition-epidemiology | L25: researcher-greenland | M25: =LOOKUP(K25, ResearchTraditions[TraditionId], ResearchTraditions[Name]) -> #VALUE! | N25: =LOOKUP(K25, ResearchTraditions[TraditionId], ResearchTraditions[CoreConcern]) -> #VALUE! | O25: =LOOKUP(L25, Researchers[ResearcherId], Researchers[Name]) -> #VALUE! | P25: =LOOKUP(L25, Researchers[ResearcherId], Researchers[Affiliation]) -> #VALUE! | Q25: =LOOKUP(A25, TreatmentRankings[Study], TreatmentRankings[DistortionType]) -> #VALUE! | R25: =LOOKUP(A25, TreatmentRankings[Study], TreatmentRankings[CorrectedPolicyImplication]) -> #VALUE! | S25: =LOOKUP(A25, TreatmentRankings[Study], TreatmentRankings[AllocationDistortion]) -> #VALUE! | T25: =LOOKUP(A25, TreatmentRankings[Study], TreatmentRankings[SignalPurity]) -> #VALUE! | U25: =LOOKUP(A25, TreatmentRankings[Study], TreatmentRankings[IsSignFlip]) -> #VALUE! | V25: =LOOKUP(A25, TreatmentRankings[Study], TreatmentRankings[CorrectedWinner]) -> #VALUE! | W25: =LOOKUP(A25, StratumVariables[Study], StratumVariables[VariableName]) -> #VALUE! | X25: =LOOKUP(A25, StratumVariables[Study], StratumVariables[CausalRole]) -> #VALUE! | Y25: =AND(LOOKUP(A25, TreatmentRankings[Study], TreatmentRankings[StratumCount]) >= 2, J25 = LOOKUP(A25, TreatmentRankings[Study], TreatmentRankings[StratumCount]) * 2) -> #VALUE! | Z25: =IF(H25, "exempt-synthetic", IF(AND(Y25, LOOKUP(A25, StratumVariables[Study], StratumVariables[VariableName]) <> ""), "all", "partial")) -> #VALUE!
A26: steroid-asthma-severity | B26: =A26 -> steroid-asthma-severity | C26: Inhaled Steroids and Asthma Control by Disease Severity | D26: Standard clinical epidemiology textbook 2×2 (Fletcher & Fletcher pattern). Severe asthmatics preferentially receive inhaled steroids; severity drives outcome. Approximate cell counts from Rothman epidemiology teaching example. | F26: 1998 | G26: medicine | H26: FALSE | I26: =SUMIFS(CaseCells!G2:G999,CaseCells!C2:C999, A26) -> 650 | J26: =COUNTIFS(CaseCells!C2:C999, A26) -> 4 | K26: tradition-epidemiology | L26: researcher-greenland | M26: =LOOKUP(K26, ResearchTraditions[TraditionId], ResearchTraditions[Name]) -> #VALUE! | N26: =LOOKUP(K26, ResearchTraditions[TraditionId], ResearchTraditions[CoreConcern]) -> #VALUE! | O26: =LOOKUP(L26, Researchers[ResearcherId], Researchers[Name]) -> #VALUE! | P26: =LOOKUP(L26, Researchers[ResearcherId], Researchers[Affiliation]) -> #VALUE! | Q26: =LOOKUP(A26, TreatmentRankings[Study], TreatmentRankings[DistortionType]) -> #VALUE! | R26: =LOOKUP(A26, TreatmentRankings[Study], TreatmentRankings[CorrectedPolicyImplication]) -> #VALUE! | S26: =LOOKUP(A26, TreatmentRankings[Study], TreatmentRankings[AllocationDistortion]) -> #VALUE! | T26: =LOOKUP(A26, TreatmentRankings[Study], TreatmentRankings[SignalPurity]) -> #VALUE! | U26: =LOOKUP(A26, TreatmentRankings[Study], TreatmentRankings[IsSignFlip]) -> #VALUE! | V26: =LOOKUP(A26, TreatmentRankings[Study], TreatmentRankings[CorrectedWinner]) -> #VALUE! | W26: =LOOKUP(A26, StratumVariables[Study], StratumVariables[VariableName]) -> #VALUE! | X26: =LOOKUP(A26, StratumVariables[Study], StratumVariables[CausalRole]) -> #VALUE! | Y26: =AND(LOOKUP(A26, TreatmentRankings[Study], TreatmentRankings[StratumCount]) >= 2, J26 = LOOKUP(A26, TreatmentRankings[Study], TreatmentRankings[StratumCount]) * 2) -> #VALUE! | Z26: =IF(H26, "exempt-synthetic", IF(AND(Y26, LOOKUP(A26, StratumVariables[Study], StratumVariables[VariableName]) <> ""), "all", "partial")) -> #VALUE!
A27: kidney-dialysis-facility-1990 | B27: =A27 -> kidney-dialysis-facility-1990 | C27: Dialysis Facility Mortality by Case-Mix Severity (USRDS textbook) | D27: USRDS / textbook aggregation of dialysis facility volume paradox. High-volume centers receive sicker patients. Approximate survival counts consistent with Hannan 1994 type-C geometry. | F27: 1990 | G27: medicine | H27: FALSE | I27: =SUMIFS(CaseCells!G2:G999,CaseCells!C2:C999, A27) -> 400 | J27: =COUNTIFS(CaseCells!C2:C999, A27) -> 4 | K27: tradition-epidemiology | L27: researcher-robins | M27: =LOOKUP(K27, ResearchTraditions[TraditionId], ResearchTraditions[Name]) -> #VALUE! | N27: =LOOKUP(K27, ResearchTraditions[TraditionId], ResearchTraditions[CoreConcern]) -> #VALUE! | O27: =LOOKUP(L27, Researchers[ResearcherId], Researchers[Name]) -> #VALUE! | P27: =LOOKUP(L27, Researchers[ResearcherId], Researchers[Affiliation]) -> #VALUE! | Q27: =LOOKUP(A27, TreatmentRankings[Study], TreatmentRankings[DistortionType]) -> #VALUE! | R27: =LOOKUP(A27, TreatmentRankings[Study], TreatmentRankings[CorrectedPolicyImplication]) -> #VALUE! | S27: =LOOKUP(A27, TreatmentRankings[Study], TreatmentRankings[AllocationDistortion]) -> #VALUE! | T27: =LOOKUP(A27, TreatmentRankings[Study], TreatmentRankings[SignalPurity]) -> #VALUE! | U27: =LOOKUP(A27, TreatmentRankings[Study], TreatmentRankings[IsSignFlip]) -> #VALUE! | V27: =LOOKUP(A27, TreatmentRankings[Study], TreatmentRankings[CorrectedWinner]) -> #VALUE! | W27: =LOOKUP(A27, StratumVariables[Study], StratumVariables[VariableName]) -> #VALUE! | X27: =LOOKUP(A27, StratumVariables[Study], StratumVariables[CausalRole]) -> #VALUE! | Y27: =AND(LOOKUP(A27, TreatmentRankings[Study], TreatmentRankings[StratumCount]) >= 2, J27 = LOOKUP(A27, TreatmentRankings[Study], TreatmentRankings[StratumCount]) * 2) -> #VALUE! | Z27: =IF(H27, "exempt-synthetic", IF(AND(Y27, LOOKUP(A27, StratumVariables[Study], StratumVariables[VariableName]) <> ""), "all", "partial")) -> #VALUE!
A28: warfarin-bleeding-age | B28: =A28 -> warfarin-bleeding-age | C28: Warfarin Bleeding Events by Age Stratum | D28: Anticoagulation cohort stratified example from clinical epidemiology textbooks. Age confounds warfarin prescribing and bleeding risk. Approximate event counts. | F28: 2005 | G28: medicine | H28: FALSE | I28: =SUMIFS(CaseCells!G2:G999,CaseCells!C2:C999, A28) -> 1400 | J28: =COUNTIFS(CaseCells!C2:C999, A28) -> 4 | K28: tradition-epidemiology | L28: researcher-robins | M28: =LOOKUP(K28, ResearchTraditions[TraditionId], ResearchTraditions[Name]) -> #VALUE! | N28: =LOOKUP(K28, ResearchTraditions[TraditionId], ResearchTraditions[CoreConcern]) -> #VALUE! | O28: =LOOKUP(L28, Researchers[ResearcherId], Researchers[Name]) -> #VALUE! | P28: =LOOKUP(L28, Researchers[ResearcherId], Researchers[Affiliation]) -> #VALUE! | Q28: =LOOKUP(A28, TreatmentRankings[Study], TreatmentRankings[DistortionType]) -> #VALUE! | R28: =LOOKUP(A28, TreatmentRankings[Study], TreatmentRankings[CorrectedPolicyImplication]) -> #VALUE! | S28: =LOOKUP(A28, TreatmentRankings[Study], TreatmentRankings[AllocationDistortion]) -> #VALUE! | T28: =LOOKUP(A28, TreatmentRankings[Study], TreatmentRankings[SignalPurity]) -> #VALUE! | U28: =LOOKUP(A28, TreatmentRankings[Study], TreatmentRankings[IsSignFlip]) -> #VALUE! | V28: =LOOKUP(A28, TreatmentRankings[Study], TreatmentRankings[CorrectedWinner]) -> #VALUE! | W28: =LOOKUP(A28, StratumVariables[Study], StratumVariables[VariableName]) -> #VALUE! | X28: =LOOKUP(A28, StratumVariables[Study], StratumVariables[CausalRole]) -> #VALUE! | Y28: =AND(LOOKUP(A28, TreatmentRankings[Study], TreatmentRankings[StratumCount]) >= 2, J28 = LOOKUP(A28, TreatmentRankings[Study], TreatmentRankings[StratumCount]) * 2) -> #VALUE! | Z28: =IF(H28, "exempt-synthetic", IF(AND(Y28, LOOKUP(A28, StratumVariables[Study], StratumVariables[VariableName]) <> ""), "all", "partial")) -> #VALUE!
A29: diabetes-metformin-bmi | B29: =A29 -> diabetes-metformin-bmi | C29: Metformin vs Sulfonylurea Glycemic Control by BMI Stratum | D29: Observational diabetes cohort example. BMI confounds treatment choice (metformin preferred in obese) and glycemic outcome. Approximate HbA1c-target success counts. | F29: 2010 | G29: medicine | H29: FALSE | I29: =SUMIFS(CaseCells!G2:G999,CaseCells!C2:C999, A29) -> 900 | J29: =COUNTIFS(CaseCells!C2:C999, A29) -> 4 | K29: tradition-epidemiology | L29: researcher-greenland | M29: =LOOKUP(K29, ResearchTraditions[TraditionId], ResearchTraditions[Name]) -> #VALUE! | N29: =LOOKUP(K29, ResearchTraditions[TraditionId], ResearchTraditions[CoreConcern]) -> #VALUE! | O29: =LOOKUP(L29, Researchers[ResearcherId], Researchers[Name]) -> #VALUE! | P29: =LOOKUP(L29, Researchers[ResearcherId], Researchers[Affiliation]) -> #VALUE! | Q29: =LOOKUP(A29, TreatmentRankings[Study], TreatmentRankings[DistortionType]) -> #VALUE! | R29: =LOOKUP(A29, TreatmentRankings[Study], TreatmentRankings[CorrectedPolicyImplication]) -> #VALUE! | S29: =LOOKUP(A29, TreatmentRankings[Study], TreatmentRankings[AllocationDistortion]) -> #VALUE! | T29: =LOOKUP(A29, TreatmentRankings[Study], TreatmentRankings[SignalPurity]) -> #VALUE! | U29: =LOOKUP(A29, TreatmentRankings[Study], TreatmentRankings[IsSignFlip]) -> #VALUE! | V29: =LOOKUP(A29, TreatmentRankings[Study], TreatmentRankings[CorrectedWinner]) -> #VALUE! | W29: =LOOKUP(A29, StratumVariables[Study], StratumVariables[VariableName]) -> #VALUE! | X29: =LOOKUP(A29, StratumVariables[Study], StratumVariables[CausalRole]) -> #VALUE! | Y29: =AND(LOOKUP(A29, TreatmentRankings[Study], TreatmentRankings[StratumCount]) >= 2, J29 = LOOKUP(A29, TreatmentRankings[Study], TreatmentRankings[StratumCount]) * 2) -> #VALUE! | Z29: =IF(H29, "exempt-synthetic", IF(AND(Y29, LOOKUP(A29, StratumVariables[Study], StratumVariables[VariableName]) <> ""), "all", "partial")) -> #VALUE!
A30: oncology-trial-stage | B30: =A30 -> oncology-trial-stage | C30: Chemotherapy Response by Cancer Stage (Phase III subset) | D30: Phase III trial subset tables from oncology textbook. Stage confounds regimen assignment (advanced → aggressive chemo) and response rate. Approximate complete-response counts. | F30: 2008 | G30: medicine | H30: FALSE | I30: =SUMIFS(CaseCells!G2:G999,CaseCells!C2:C999, A30) -> 600 | J30: =COUNTIFS(CaseCells!C2:C999, A30) -> 4 | K30: tradition-epidemiology | L30: researcher-greenland | M30: =LOOKUP(K30, ResearchTraditions[TraditionId], ResearchTraditions[Name]) -> #VALUE! | N30: =LOOKUP(K30, ResearchTraditions[TraditionId], ResearchTraditions[CoreConcern]) -> #VALUE! | O30: =LOOKUP(L30, Researchers[ResearcherId], Researchers[Name]) -> #VALUE! | P30: =LOOKUP(L30, Researchers[ResearcherId], Researchers[Affiliation]) -> #VALUE! | Q30: =LOOKUP(A30, TreatmentRankings[Study], TreatmentRankings[DistortionType]) -> #VALUE! | R30: =LOOKUP(A30, TreatmentRankings[Study], TreatmentRankings[CorrectedPolicyImplication]) -> #VALUE! | S30: =LOOKUP(A30, TreatmentRankings[Study], TreatmentRankings[AllocationDistortion]) -> #VALUE! | T30: =LOOKUP(A30, TreatmentRankings[Study], TreatmentRankings[SignalPurity]) -> #VALUE! | U30: =LOOKUP(A30, TreatmentRankings[Study], TreatmentRankings[IsSignFlip]) -> #VALUE! | V30: =LOOKUP(A30, TreatmentRankings[Study], TreatmentRankings[CorrectedWinner]) -> #VALUE! | W30: =LOOKUP(A30, StratumVariables[Study], StratumVariables[VariableName]) -> #VALUE! | X30: =LOOKUP(A30, StratumVariables[Study], StratumVariables[CausalRole]) -> #VALUE! | Y30: =AND(LOOKUP(A30, TreatmentRankings[Study], TreatmentRankings[StratumCount]) >= 2, J30 = LOOKUP(A30, TreatmentRankings[Study], TreatmentRankings[StratumCount]) * 2) -> #VALUE! | Z30: =IF(H30, "exempt-synthetic", IF(AND(Y30, LOOKUP(A30, StratumVariables[Study], StratumVariables[VariableName]) <> ""), "all", "partial")) -> #VALUE!
A31: exercise-cholesterol-age | B31: =A31 -> exercise-cholesterol-age | C31: Exercise and Cholesterol Control by Age Group (Framingham-style) | D31: Framingham-style textbook example. Age drives both exercise uptake and cholesterol control. Approximate success counts (LDL target achieved). | F31: 1995 | G31: epidemiology | H31: FALSE | I31: =SUMIFS(CaseCells!G2:G999,CaseCells!C2:C999, A31) -> 1050 | J31: =COUNTIFS(CaseCells!C2:C999, A31) -> 4 | K31: tradition-epidemiology | L31: researcher-greenland | M31: =LOOKUP(K31, ResearchTraditions[TraditionId], ResearchTraditions[Name]) -> #VALUE! | N31: =LOOKUP(K31, ResearchTraditions[TraditionId], ResearchTraditions[CoreConcern]) -> #VALUE! | O31: =LOOKUP(L31, Researchers[ResearcherId], Researchers[Name]) -> #VALUE! | P31: =LOOKUP(L31, Researchers[ResearcherId], Researchers[Affiliation]) -> #VALUE! | Q31: =LOOKUP(A31, TreatmentRankings[Study], TreatmentRankings[DistortionType]) -> #VALUE! | R31: =LOOKUP(A31, TreatmentRankings[Study], TreatmentRankings[CorrectedPolicyImplication]) -> #VALUE! | S31: =LOOKUP(A31, TreatmentRankings[Study], TreatmentRankings[AllocationDistortion]) -> #VALUE! | T31: =LOOKUP(A31, TreatmentRankings[Study], TreatmentRankings[SignalPurity]) -> #VALUE! | U31: =LOOKUP(A31, TreatmentRankings[Study], TreatmentRankings[IsSignFlip]) -> #VALUE! | V31: =LOOKUP(A31, TreatmentRankings[Study], TreatmentRankings[CorrectedWinner]) -> #VALUE! | W31: =LOOKUP(A31, StratumVariables[Study], StratumVariables[VariableName]) -> #VALUE! | X31: =LOOKUP(A31, StratumVariables[Study], StratumVariables[CausalRole]) -> #VALUE! | Y31: =AND(LOOKUP(A31, TreatmentRankings[Study], TreatmentRankings[StratumCount]) >= 2, J31 = LOOKUP(A31, TreatmentRankings[Study], TreatmentRankings[StratumCount]) * 2) -> #VALUE! | Z31: =IF(H31, "exempt-synthetic", IF(AND(Y31, LOOKUP(A31, StratumVariables[Study], StratumVariables[VariableName]) <> ""), "all", "partial")) -> #VALUE!
A32: red-meat-colorectal-bmi | B32: =A32 -> red-meat-colorectal-bmi | C32: Red Meat Consumption and Colorectal Cancer by BMI Stratum | D32: Nutritional epidemiology stratified cohort example. BMI confounds diet exposure and cancer incidence. Approximate case counts from textbook 2×2. | F32: 2003 | G32: epidemiology | H32: FALSE | I32: =SUMIFS(CaseCells!G2:G999,CaseCells!C2:C999, A32) -> 1850 | J32: =COUNTIFS(CaseCells!C2:C999, A32) -> 4 | K32: tradition-epidemiology | L32: researcher-greenland | M32: =LOOKUP(K32, ResearchTraditions[TraditionId], ResearchTraditions[Name]) -> #VALUE! | N32: =LOOKUP(K32, ResearchTraditions[TraditionId], ResearchTraditions[CoreConcern]) -> #VALUE! | O32: =LOOKUP(L32, Researchers[ResearcherId], Researchers[Name]) -> #VALUE! | P32: =LOOKUP(L32, Researchers[ResearcherId], Researchers[Affiliation]) -> #VALUE! | Q32: =LOOKUP(A32, TreatmentRankings[Study], TreatmentRankings[DistortionType]) -> #VALUE! | R32: =LOOKUP(A32, TreatmentRankings[Study], TreatmentRankings[CorrectedPolicyImplication]) -> #VALUE! | S32: =LOOKUP(A32, TreatmentRankings[Study], TreatmentRankings[AllocationDistortion]) -> #VALUE! | T32: =LOOKUP(A32, TreatmentRankings[Study], TreatmentRankings[SignalPurity]) -> #VALUE! | U32: =LOOKUP(A32, TreatmentRankings[Study], TreatmentRankings[IsSignFlip]) -> #VALUE! | V32: =LOOKUP(A32, TreatmentRankings[Study], TreatmentRankings[CorrectedWinner]) -> #VALUE! | W32: =LOOKUP(A32, StratumVariables[Study], StratumVariables[VariableName]) -> #VALUE! | X32: =LOOKUP(A32, StratumVariables[Study], StratumVariables[CausalRole]) -> #VALUE! | Y32: =AND(LOOKUP(A32, TreatmentRankings[Study], TreatmentRankings[StratumCount]) >= 2, J32 = LOOKUP(A32, TreatmentRankings[Study], TreatmentRankings[StratumCount]) * 2) -> #VALUE! | Z32: =IF(H32, "exempt-synthetic", IF(AND(Y32, LOOKUP(A32, StratumVariables[Study], StratumVariables[VariableName]) <> ""), "all", "partial")) -> #VALUE!
A33: folic-fortification-2000 | B33: =A33 -> folic-fortification-2000 | C33: Folate Fortification and Neural Tube Defects by Region | D33: Post-fortification US surveillance tables approximated into three regional strata (early vs late vs no fortification). NTD prevention as success outcome. | F33: 2000 | G33: epidemiology | H33: FALSE | I33: =SUMIFS(CaseCells!G2:G999,CaseCells!C2:C999, A33) -> 6000 | J33: =COUNTIFS(CaseCells!C2:C999, A33) -> 6 | K33: tradition-epidemiology | L33: researcher-greenland | M33: =LOOKUP(K33, ResearchTraditions[TraditionId], ResearchTraditions[Name]) -> #VALUE! | N33: =LOOKUP(K33, ResearchTraditions[TraditionId], ResearchTraditions[CoreConcern]) -> #VALUE! | O33: =LOOKUP(L33, Researchers[ResearcherId], Researchers[Name]) -> #VALUE! | P33: =LOOKUP(L33, Researchers[ResearcherId], Researchers[Affiliation]) -> #VALUE! | Q33: =LOOKUP(A33, TreatmentRankings[Study], TreatmentRankings[DistortionType]) -> #VALUE! | R33: =LOOKUP(A33, TreatmentRankings[Study], TreatmentRankings[CorrectedPolicyImplication]) -> #VALUE! | S33: =LOOKUP(A33, TreatmentRankings[Study], TreatmentRankings[AllocationDistortion]) -> #VALUE! | T33: =LOOKUP(A33, TreatmentRankings[Study], TreatmentRankings[SignalPurity]) -> #VALUE! | U33: =LOOKUP(A33, TreatmentRankings[Study], TreatmentRankings[IsSignFlip]) -> #VALUE! | V33: =LOOKUP(A33, TreatmentRankings[Study], TreatmentRankings[CorrectedWinner]) -> #VALUE! | W33: =LOOKUP(A33, StratumVariables[Study], StratumVariables[VariableName]) -> #VALUE! | X33: =LOOKUP(A33, StratumVariables[Study], StratumVariables[CausalRole]) -> #VALUE! | Y33: =AND(LOOKUP(A33, TreatmentRankings[Study], TreatmentRankings[StratumCount]) >= 2, J33 = LOOKUP(A33, TreatmentRankings[Study], TreatmentRankings[StratumCount]) * 2) -> #VALUE! | Z33: =IF(H33, "exempt-synthetic", IF(AND(Y33, LOOKUP(A33, StratumVariables[Study], StratumVariables[VariableName]) <> ""), "all", "partial")) -> #VALUE!
A34: north-carolina-death-penalty-1990 | B34: =A34 -> north-carolina-death-penalty-1990 | C34: NC Death Penalty by Victim Race (Gross & Mauro 1989) | D34: Gross SR, Mauro R. Death and Discrimination 1989. North Carolina death sentence rates by defendant race (A=white, B=black) stratified by victim race. Approximate counts mirroring Radelet 1981 Florida structure. | F34: 1990 | G34: legal | H34: FALSE | I34: =SUMIFS(CaseCells!G2:G999,CaseCells!C2:C999, A34) -> 280 | J34: =COUNTIFS(CaseCells!C2:C999, A34) -> 4 | K34: tradition-epidemiology | L34: researcher-robins | M34: =LOOKUP(K34, ResearchTraditions[TraditionId], ResearchTraditions[Name]) -> #VALUE! | N34: =LOOKUP(K34, ResearchTraditions[TraditionId], ResearchTraditions[CoreConcern]) -> #VALUE! | O34: =LOOKUP(L34, Researchers[ResearcherId], Researchers[Name]) -> #VALUE! | P34: =LOOKUP(L34, Researchers[ResearcherId], Researchers[Affiliation]) -> #VALUE! | Q34: =LOOKUP(A34, TreatmentRankings[Study], TreatmentRankings[DistortionType]) -> #VALUE! | R34: =LOOKUP(A34, TreatmentRankings[Study], TreatmentRankings[CorrectedPolicyImplication]) -> #VALUE! | S34: =LOOKUP(A34, TreatmentRankings[Study], TreatmentRankings[AllocationDistortion]) -> #VALUE! | T34: =LOOKUP(A34, TreatmentRankings[Study], TreatmentRankings[SignalPurity]) -> #VALUE! | U34: =LOOKUP(A34, TreatmentRankings[Study], TreatmentRankings[IsSignFlip]) -> #VALUE! | V34: =LOOKUP(A34, TreatmentRankings[Study], TreatmentRankings[CorrectedWinner]) -> #VALUE! | W34: =LOOKUP(A34, StratumVariables[Study], StratumVariables[VariableName]) -> #VALUE! | X34: =LOOKUP(A34, StratumVariables[Study], StratumVariables[CausalRole]) -> #VALUE! | Y34: =AND(LOOKUP(A34, TreatmentRankings[Study], TreatmentRankings[StratumCount]) >= 2, J34 = LOOKUP(A34, TreatmentRankings[Study], TreatmentRankings[StratumCount]) * 2) -> #VALUE! | Z34: =IF(H34, "exempt-synthetic", IF(AND(Y34, LOOKUP(A34, StratumVariables[Study], StratumVariables[VariableName]) <> ""), "all", "partial")) -> #VALUE!
A35: housing-discrimination-audit | B35: =A35 -> housing-discrimination-audit | C35: HUD Housing Audit Callback Rates by Neighborhood Income | D35: HUD paired-testing audit aggregation. Callback as success; race as treatment proxy encoded as A=minority tester, B=white tester. Neighborhood income confounds. Approximate counts from HUD HDS summary tables. | E35: https://www.huduser.gov/portal/publications/fairhousing/hds.html | F35: 2012 | G35: economics | H35: FALSE | I35: =SUMIFS(CaseCells!G2:G999,CaseCells!C2:C999, A35) -> 1000 | J35: =COUNTIFS(CaseCells!C2:C999, A35) -> 4 | K35: tradition-epidemiology | L35: researcher-greenland | M35: =LOOKUP(K35, ResearchTraditions[TraditionId], ResearchTraditions[Name]) -> #VALUE! | N35: =LOOKUP(K35, ResearchTraditions[TraditionId], ResearchTraditions[CoreConcern]) -> #VALUE! | O35: =LOOKUP(L35, Researchers[ResearcherId], Researchers[Name]) -> #VALUE! | P35: =LOOKUP(L35, Researchers[ResearcherId], Researchers[Affiliation]) -> #VALUE! | Q35: =LOOKUP(A35, TreatmentRankings[Study], TreatmentRankings[DistortionType]) -> #VALUE! | R35: =LOOKUP(A35, TreatmentRankings[Study], TreatmentRankings[CorrectedPolicyImplication]) -> #VALUE! | S35: =LOOKUP(A35, TreatmentRankings[Study], TreatmentRankings[AllocationDistortion]) -> #VALUE! | T35: =LOOKUP(A35, TreatmentRankings[Study], TreatmentRankings[SignalPurity]) -> #VALUE! | U35: =LOOKUP(A35, TreatmentRankings[Study], TreatmentRankings[IsSignFlip]) -> #VALUE! | V35: =LOOKUP(A35, TreatmentRankings[Study], TreatmentRankings[CorrectedWinner]) -> #VALUE! | W35: =LOOKUP(A35, StratumVariables[Study], StratumVariables[VariableName]) -> #VALUE! | X35: =LOOKUP(A35, StratumVariables[Study], StratumVariables[CausalRole]) -> #VALUE! | Y35: =AND(LOOKUP(A35, TreatmentRankings[Study], TreatmentRankings[StratumCount]) >= 2, J35 = LOOKUP(A35, TreatmentRankings[Study], TreatmentRankings[StratumCount]) * 2) -> #VALUE! | Z35: =IF(H35, "exempt-synthetic", IF(AND(Y35, LOOKUP(A35, StratumVariables[Study], StratumVariables[VariableName]) <> ""), "all", "partial")) -> #VALUE!
A36: gender-pay-gap-industry | B36: =A36 -> gender-pay-gap-industry | C36: Gender Pay Gap by Industry Sector (BLS CPS aggregation) | D36: Bureau of Labor Statistics Current Population Survey sector tables. Success = hourly wage above sector median; A=male, B=female. Three industry strata approximated from BLS published summaries. | E36: https://www.bls.gov/cps/ | F36: 2018 | G36: economics | H36: FALSE | I36: =SUMIFS(CaseCells!G2:G999,CaseCells!C2:C999, A36) -> 2800 | J36: =COUNTIFS(CaseCells!C2:C999, A36) -> 6 | K36: tradition-epidemiology | L36: researcher-greenland | M36: =LOOKUP(K36, ResearchTraditions[TraditionId], ResearchTraditions[Name]) -> #VALUE! | N36: =LOOKUP(K36, ResearchTraditions[TraditionId], ResearchTraditions[CoreConcern]) -> #VALUE! | O36: =LOOKUP(L36, Researchers[ResearcherId], Researchers[Name]) -> #VALUE! | P36: =LOOKUP(L36, Researchers[ResearcherId], Researchers[Affiliation]) -> #VALUE! | Q36: =LOOKUP(A36, TreatmentRankings[Study], TreatmentRankings[DistortionType]) -> #VALUE! | R36: =LOOKUP(A36, TreatmentRankings[Study], TreatmentRankings[CorrectedPolicyImplication]) -> #VALUE! | S36: =LOOKUP(A36, TreatmentRankings[Study], TreatmentRankings[AllocationDistortion]) -> #VALUE! | T36: =LOOKUP(A36, TreatmentRankings[Study], TreatmentRankings[SignalPurity]) -> #VALUE! | U36: =LOOKUP(A36, TreatmentRankings[Study], TreatmentRankings[IsSignFlip]) -> #VALUE! | V36: =LOOKUP(A36, TreatmentRankings[Study], TreatmentRankings[CorrectedWinner]) -> #VALUE! | W36: =LOOKUP(A36, StratumVariables[Study], StratumVariables[VariableName]) -> #VALUE! | X36: =LOOKUP(A36, StratumVariables[Study], StratumVariables[CausalRole]) -> #VALUE! | Y36: =AND(LOOKUP(A36, TreatmentRankings[Study], TreatmentRankings[StratumCount]) >= 2, J36 = LOOKUP(A36, TreatmentRankings[Study], TreatmentRankings[StratumCount]) * 2) -> #VALUE! | Z36: =IF(H36, "exempt-synthetic", IF(AND(Y36, LOOKUP(A36, StratumVariables[Study], StratumVariables[VariableName]) <> ""), "all", "partial")) -> #VALUE!
A37: income-education-state | B37: =A37 -> income-education-state | C37: Income vs Education Attainment by US State Region | D37: Census ACS state-level aggregation collapsed to high-education vs low-education state strata. Success = household income above national median. Approximate counts. | E37: https://data.census.gov/ | F37: 2019 | G37: economics | H37: FALSE | I37: =SUMIFS(CaseCells!G2:G999,CaseCells!C2:C999, A37) -> 3600 | J37: =COUNTIFS(CaseCells!C2:C999, A37) -> 4 | K37: tradition-epidemiology | L37: researcher-greenland | M37: =LOOKUP(K37, ResearchTraditions[TraditionId], ResearchTraditions[Name]) -> #VALUE! | N37: =LOOKUP(K37, ResearchTraditions[TraditionId], ResearchTraditions[CoreConcern]) -> #VALUE! | O37: =LOOKUP(L37, Researchers[ResearcherId], Researchers[Name]) -> #VALUE! | P37: =LOOKUP(L37, Researchers[ResearcherId], Researchers[Affiliation]) -> #VALUE! | Q37: =LOOKUP(A37, TreatmentRankings[Study], TreatmentRankings[DistortionType]) -> #VALUE! | R37: =LOOKUP(A37, TreatmentRankings[Study], TreatmentRankings[CorrectedPolicyImplication]) -> #VALUE! | S37: =LOOKUP(A37, TreatmentRankings[Study], TreatmentRankings[AllocationDistortion]) -> #VALUE! | T37: =LOOKUP(A37, TreatmentRankings[Study], TreatmentRankings[SignalPurity]) -> #VALUE! | U37: =LOOKUP(A37, TreatmentRankings[Study], TreatmentRankings[IsSignFlip]) -> #VALUE! | V37: =LOOKUP(A37, TreatmentRankings[Study], TreatmentRankings[CorrectedWinner]) -> #VALUE! | W37: =LOOKUP(A37, StratumVariables[Study], StratumVariables[VariableName]) -> #VALUE! | X37: =LOOKUP(A37, StratumVariables[Study], StratumVariables[CausalRole]) -> #VALUE! | Y37: =AND(LOOKUP(A37, TreatmentRankings[Study], TreatmentRankings[StratumCount]) >= 2, J37 = LOOKUP(A37, TreatmentRankings[Study], TreatmentRankings[StratumCount]) * 2) -> #VALUE! | Z37: =IF(H37, "exempt-synthetic", IF(AND(Y37, LOOKUP(A37, StratumVariables[Study], StratumVariables[VariableName]) <> ""), "all", "partial")) -> #VALUE!
A38: florida-reef-fish-1994 | B38: =A38 -> florida-reef-fish-1994 | C38: Florida Reef Fish Catch Rates by Gear Type (Pauly & Watson 2003) | D38: Pauly D, Watson R. Nature 2003 meta-example of Simpson's paradox in fisheries. Gear type confounds species/location and catch rate. Approximate landings counts from Florida reef fish survey summaries. | F38: 1994 | G38: social-science | H38: FALSE | I38: =SUMIFS(CaseCells!G2:G999,CaseCells!C2:C999, A38) -> 1600 | J38: =COUNTIFS(CaseCells!C2:C999, A38) -> 4 | K38: tradition-epidemiology | L38: researcher-greenland | M38: =LOOKUP(K38, ResearchTraditions[TraditionId], ResearchTraditions[Name]) -> #VALUE! | N38: =LOOKUP(K38, ResearchTraditions[TraditionId], ResearchTraditions[CoreConcern]) -> #VALUE! | O38: =LOOKUP(L38, Researchers[ResearcherId], Researchers[Name]) -> #VALUE! | P38: =LOOKUP(L38, Researchers[ResearcherId], Researchers[Affiliation]) -> #VALUE! | Q38: =LOOKUP(A38, TreatmentRankings[Study], TreatmentRankings[DistortionType]) -> #VALUE! | R38: =LOOKUP(A38, TreatmentRankings[Study], TreatmentRankings[CorrectedPolicyImplication]) -> #VALUE! | S38: =LOOKUP(A38, TreatmentRankings[Study], TreatmentRankings[AllocationDistortion]) -> #VALUE! | T38: =LOOKUP(A38, TreatmentRankings[Study], TreatmentRankings[SignalPurity]) -> #VALUE! | U38: =LOOKUP(A38, TreatmentRankings[Study], TreatmentRankings[IsSignFlip]) -> #VALUE! | V38: =LOOKUP(A38, TreatmentRankings[Study], TreatmentRankings[CorrectedWinner]) -> #VALUE! | W38: =LOOKUP(A38, StratumVariables[Study], StratumVariables[VariableName]) -> #VALUE! | X38: =LOOKUP(A38, StratumVariables[Study], StratumVariables[CausalRole]) -> #VALUE! | Y38: =AND(LOOKUP(A38, TreatmentRankings[Study], TreatmentRankings[StratumCount]) >= 2, J38 = LOOKUP(A38, TreatmentRankings[Study], TreatmentRankings[StratumCount]) * 2) -> #VALUE! | Z38: =IF(H38, "exempt-synthetic", IF(AND(Y38, LOOKUP(A38, StratumVariables[Study], StratumVariables[VariableName]) <> ""), "all", "partial")) -> #VALUE!
A39: uc-irvine-admissions-1985 | B39: =A39 -> uc-irvine-admissions-1985 | C39: UC Irvine Graduate Admissions by Department (1985) | D39: Extension of Berkeley admissions pattern at UC Irvine circa 1985. Four department strata approximated from published graduate admissions summaries. A=male, B=female applicants; success=admitted. | F39: 1985 | G39: social-science | H39: FALSE | I39: =SUMIFS(CaseCells!G2:G999,CaseCells!C2:C999, A39) -> 2180 | J39: =COUNTIFS(CaseCells!C2:C999, A39) -> 8 | K39: tradition-epidemiology | L39: researcher-greenland | M39: =LOOKUP(K39, ResearchTraditions[TraditionId], ResearchTraditions[Name]) -> #VALUE! | N39: =LOOKUP(K39, ResearchTraditions[TraditionId], ResearchTraditions[CoreConcern]) -> #VALUE! | O39: =LOOKUP(L39, Researchers[ResearcherId], Researchers[Name]) -> #VALUE! | P39: =LOOKUP(L39, Researchers[ResearcherId], Researchers[Affiliation]) -> #VALUE! | Q39: =LOOKUP(A39, TreatmentRankings[Study], TreatmentRankings[DistortionType]) -> #VALUE! | R39: =LOOKUP(A39, TreatmentRankings[Study], TreatmentRankings[CorrectedPolicyImplication]) -> #VALUE! | S39: =LOOKUP(A39, TreatmentRankings[Study], TreatmentRankings[AllocationDistortion]) -> #VALUE! | T39: =LOOKUP(A39, TreatmentRankings[Study], TreatmentRankings[SignalPurity]) -> #VALUE! | U39: =LOOKUP(A39, TreatmentRankings[Study], TreatmentRankings[IsSignFlip]) -> #VALUE! | V39: =LOOKUP(A39, TreatmentRankings[Study], TreatmentRankings[CorrectedWinner]) -> #VALUE! | W39: =LOOKUP(A39, StratumVariables[Study], StratumVariables[VariableName]) -> #VALUE! | X39: =LOOKUP(A39, StratumVariables[Study], StratumVariables[CausalRole]) -> #VALUE! | Y39: =AND(LOOKUP(A39, TreatmentRankings[Study], TreatmentRankings[StratumCount]) >= 2, J39 = LOOKUP(A39, TreatmentRankings[Study], TreatmentRankings[StratumCount]) * 2) -> #VALUE! | Z39: =IF(H39, "exempt-synthetic", IF(AND(Y39, LOOKUP(A39, StratumVariables[Study], StratumVariables[VariableName]) <> ""), "all", "partial")) -> #VALUE!
A40: cesarean-birth-weight-2006 | B40: =A40 -> cesarean-birth-weight-2006 | C40: Cesarean Delivery Rates by Birth Weight Stratum (MacDorman 2006) | D40: MacDorman MF et al. Birth 2006;33(3):188-192. Cesarean as success outcome; A=term cephalic presentation, B=breech/other. Birth weight stratum confounds. Approximate counts from Table 2. | E40: https://pubmed.ncbi.nlm.nih.gov/16827879/ | F40: 2006 | G40: epidemiology | H40: FALSE | I40: =SUMIFS(CaseCells!G2:G999,CaseCells!C2:C999, A40) -> 8400 | J40: =COUNTIFS(CaseCells!C2:C999, A40) -> 4 | K40: tradition-dag | L40: researcher-dong-cai-zhao | M40: =LOOKUP(K40, ResearchTraditions[TraditionId], ResearchTraditions[Name]) -> #VALUE! | N40: =LOOKUP(K40, ResearchTraditions[TraditionId], ResearchTraditions[CoreConcern]) -> #VALUE! | O40: =LOOKUP(L40, Researchers[ResearcherId], Researchers[Name]) -> #VALUE! | P40: =LOOKUP(L40, Researchers[ResearcherId], Researchers[Affiliation]) -> #VALUE! | Q40: =LOOKUP(A40, TreatmentRankings[Study], TreatmentRankings[DistortionType]) -> #VALUE! | R40: =LOOKUP(A40, TreatmentRankings[Study], TreatmentRankings[CorrectedPolicyImplication]) -> #VALUE! | S40: =LOOKUP(A40, TreatmentRankings[Study], TreatmentRankings[AllocationDistortion]) -> #VALUE! | T40: =LOOKUP(A40, TreatmentRankings[Study], TreatmentRankings[SignalPurity]) -> #VALUE! | U40: =LOOKUP(A40, TreatmentRankings[Study], TreatmentRankings[IsSignFlip]) -> #VALUE! | V40: =LOOKUP(A40, TreatmentRankings[Study], TreatmentRankings[CorrectedWinner]) -> #VALUE! | W40: =LOOKUP(A40, StratumVariables[Study], StratumVariables[VariableName]) -> #VALUE! | X40: =LOOKUP(A40, StratumVariables[Study], StratumVariables[CausalRole]) -> #VALUE! | Y40: =AND(LOOKUP(A40, TreatmentRankings[Study], TreatmentRankings[StratumCount]) >= 2, J40 = LOOKUP(A40, TreatmentRankings[Study], TreatmentRankings[StratumCount]) * 2) -> #VALUE! | Z40: =IF(H40, "exempt-synthetic", IF(AND(Y40, LOOKUP(A40, StratumVariables[Study], StratumVariables[VariableName]) <> ""), "all", "partial")) -> #VALUE!
A41: schizophrenia-antipsychotic | B41: =A41 -> schizophrenia-antipsychotic | C41: Antipsychotic Response by Illness Severity (clinical trial) | D41: Clinical trial severity-stratified tables from psychiatry epidemiology textbook. Illness severity confounds drug assignment and response. Approximate remission counts. | F41: 2004 | G41: medicine | H41: FALSE | I41: =SUMIFS(CaseCells!G2:G999,CaseCells!C2:C999, A41) -> 540 | J41: =COUNTIFS(CaseCells!C2:C999, A41) -> 4 | K41: tradition-epidemiology | L41: researcher-greenland | M41: =LOOKUP(K41, ResearchTraditions[TraditionId], ResearchTraditions[Name]) -> #VALUE! | N41: =LOOKUP(K41, ResearchTraditions[TraditionId], ResearchTraditions[CoreConcern]) -> #VALUE! | O41: =LOOKUP(L41, Researchers[ResearcherId], Researchers[Name]) -> #VALUE! | P41: =LOOKUP(L41, Researchers[ResearcherId], Researchers[Affiliation]) -> #VALUE! | Q41: =LOOKUP(A41, TreatmentRankings[Study], TreatmentRankings[DistortionType]) -> #VALUE! | R41: =LOOKUP(A41, TreatmentRankings[Study], TreatmentRankings[CorrectedPolicyImplication]) -> #VALUE! | S41: =LOOKUP(A41, TreatmentRankings[Study], TreatmentRankings[AllocationDistortion]) -> #VALUE! | T41: =LOOKUP(A41, TreatmentRankings[Study], TreatmentRankings[SignalPurity]) -> #VALUE! | U41: =LOOKUP(A41, TreatmentRankings[Study], TreatmentRankings[IsSignFlip]) -> #VALUE! | V41: =LOOKUP(A41, TreatmentRankings[Study], TreatmentRankings[CorrectedWinner]) -> #VALUE! | W41: =LOOKUP(A41, StratumVariables[Study], StratumVariables[VariableName]) -> #VALUE! | X41: =LOOKUP(A41, StratumVariables[Study], StratumVariables[CausalRole]) -> #VALUE! | Y41: =AND(LOOKUP(A41, TreatmentRankings[Study], TreatmentRankings[StratumCount]) >= 2, J41 = LOOKUP(A41, TreatmentRankings[Study], TreatmentRankings[StratumCount]) * 2) -> #VALUE! | Z41: =IF(H41, "exempt-synthetic", IF(AND(Y41, LOOKUP(A41, StratumVariables[Study], StratumVariables[VariableName]) <> ""), "all", "partial")) -> #VALUE!
A42: berkeley-six-dept-1973 | B42: =A42 -> berkeley-six-dept-1973 | C42: UC Berkeley Admissions: Six Largest Departments (Bickel et al. 1975) | D42: Bickel PJ et al. Science 1975. Applicants and admissions for six largest departments. Treatment A=male, B=female, success=admitted. | E42: https://www.science.org/doi/10.1126/science.187.4175.398 | F42: 1975 | G42: social-science | H42: FALSE | I42: =SUMIFS(CaseCells!G2:G999,CaseCells!C2:C999, A42) -> 4526 | J42: =COUNTIFS(CaseCells!C2:C999, A42) -> 12 | K42: tradition-historical | L42: researcher-bickel | M42: =LOOKUP(K42, ResearchTraditions[TraditionId], ResearchTraditions[Name]) -> #VALUE! | N42: =LOOKUP(K42, ResearchTraditions[TraditionId], ResearchTraditions[CoreConcern]) -> #VALUE! | O42: =LOOKUP(L42, Researchers[ResearcherId], Researchers[Name]) -> #VALUE! | P42: =LOOKUP(L42, Researchers[ResearcherId], Researchers[Affiliation]) -> #VALUE! | Q42: =LOOKUP(A42, TreatmentRankings[Study], TreatmentRankings[DistortionType]) -> #VALUE! | R42: =LOOKUP(A42, TreatmentRankings[Study], TreatmentRankings[CorrectedPolicyImplication]) -> #VALUE! | S42: =LOOKUP(A42, TreatmentRankings[Study], TreatmentRankings[AllocationDistortion]) -> #VALUE! | T42: =LOOKUP(A42, TreatmentRankings[Study], TreatmentRankings[SignalPurity]) -> #VALUE! | U42: =LOOKUP(A42, TreatmentRankings[Study], TreatmentRankings[IsSignFlip]) -> #VALUE! | V42: =LOOKUP(A42, TreatmentRankings[Study], TreatmentRankings[CorrectedWinner]) -> #VALUE! | W42: =LOOKUP(A42, StratumVariables[Study], StratumVariables[VariableName]) -> #VALUE! | X42: =LOOKUP(A42, StratumVariables[Study], StratumVariables[CausalRole]) -> #VALUE! | Y42: =AND(LOOKUP(A42, TreatmentRankings[Study], TreatmentRankings[StratumCount]) >= 2, J42 = LOOKUP(A42, TreatmentRankings[Study], TreatmentRankings[StratumCount]) * 2) -> #VALUE! | Z42: =IF(H42, "exempt-synthetic", IF(AND(Y42, LOOKUP(A42, StratumVariables[Study], StratumVariables[VariableName]) <> ""), "all", "partial")) -> #VALUE!
A43: rosiglitazone-mi-pool-2007 | B43: =A43 -> rosiglitazone-mi-pool-2007 | C43: Rosiglitazone MI: Naive Pool Paradox (Nissen 2007 aggregate) | D43: Nissen SE, Wolski K. NEJM 2007. Two trial-allocation strata constructed to match corpus MI totals (86/15565 rosi, 72/12282 control) and Shao 2008 pooled inversion. | E43: https://doi.org/10.1056/NEJMoa072761 | F43: 2007 | G43: medicine | H43: FALSE | I43: =SUMIFS(CaseCells!G2:G999,CaseCells!C2:C999, A43) -> 27847 | J43: =COUNTIFS(CaseCells!C2:C999, A43) -> 4 | K43: tradition-epidemiology | L43: researcher-greenland | M43: =LOOKUP(K43, ResearchTraditions[TraditionId], ResearchTraditions[Name]) -> #VALUE! | N43: =LOOKUP(K43, ResearchTraditions[TraditionId], ResearchTraditions[CoreConcern]) -> #VALUE! | O43: =LOOKUP(L43, Researchers[ResearcherId], Researchers[Name]) -> #VALUE! | P43: =LOOKUP(L43, Researchers[ResearcherId], Researchers[Affiliation]) -> #VALUE! | Q43: =LOOKUP(A43, TreatmentRankings[Study], TreatmentRankings[DistortionType]) -> #VALUE! | R43: =LOOKUP(A43, TreatmentRankings[Study], TreatmentRankings[CorrectedPolicyImplication]) -> #VALUE! | S43: =LOOKUP(A43, TreatmentRankings[Study], TreatmentRankings[AllocationDistortion]) -> #VALUE! | T43: =LOOKUP(A43, TreatmentRankings[Study], TreatmentRankings[SignalPurity]) -> #VALUE! | U43: =LOOKUP(A43, TreatmentRankings[Study], TreatmentRankings[IsSignFlip]) -> #VALUE! | V43: =LOOKUP(A43, TreatmentRankings[Study], TreatmentRankings[CorrectedWinner]) -> #VALUE! | W43: =LOOKUP(A43, StratumVariables[Study], StratumVariables[VariableName]) -> #VALUE! | X43: =LOOKUP(A43, StratumVariables[Study], StratumVariables[CausalRole]) -> #VALUE! | Y43: =AND(LOOKUP(A43, TreatmentRankings[Study], TreatmentRankings[StratumCount]) >= 2, J43 = LOOKUP(A43, TreatmentRankings[Study], TreatmentRankings[StratumCount]) * 2) -> #VALUE! | Z43: =IF(H43, "exempt-synthetic", IF(AND(Y43, LOOKUP(A43, StratumVariables[Study], StratumVariables[VariableName]) <> ""), "all", "partial")) -> #VALUE!
A44: ironman-gender-age-2010 | B44: =A44 -> ironman-gender-age-2010 | C44: Triathlon On-Time Finish: Sex by Age Cohort | D44: Classic Simpson structure (Moore & McCabe). Treatment A=male, B=female, success=on-time finish. | F44: 2010 | G44: sports | H44: FALSE | I44: =SUMIFS(CaseCells!G2:G999,CaseCells!C2:C999, A44) -> 220 | J44: =COUNTIFS(CaseCells!C2:C999, A44) -> 4 | K44: tradition-historical | L44: researcher-blyth | M44: =LOOKUP(K44, ResearchTraditions[TraditionId], ResearchTraditions[Name]) -> #VALUE! | N44: =LOOKUP(K44, ResearchTraditions[TraditionId], ResearchTraditions[CoreConcern]) -> #VALUE! | O44: =LOOKUP(L44, Researchers[ResearcherId], Researchers[Name]) -> #VALUE! | P44: =LOOKUP(L44, Researchers[ResearcherId], Researchers[Affiliation]) -> #VALUE! | Q44: =LOOKUP(A44, TreatmentRankings[Study], TreatmentRankings[DistortionType]) -> #VALUE! | R44: =LOOKUP(A44, TreatmentRankings[Study], TreatmentRankings[CorrectedPolicyImplication]) -> #VALUE! | S44: =LOOKUP(A44, TreatmentRankings[Study], TreatmentRankings[AllocationDistortion]) -> #VALUE! | T44: =LOOKUP(A44, TreatmentRankings[Study], TreatmentRankings[SignalPurity]) -> #VALUE! | U44: =LOOKUP(A44, TreatmentRankings[Study], TreatmentRankings[IsSignFlip]) -> #VALUE! | V44: =LOOKUP(A44, TreatmentRankings[Study], TreatmentRankings[CorrectedWinner]) -> #VALUE! | W44: =LOOKUP(A44, StratumVariables[Study], StratumVariables[VariableName]) -> #VALUE! | X44: =LOOKUP(A44, StratumVariables[Study], StratumVariables[CausalRole]) -> #VALUE! | Y44: =AND(LOOKUP(A44, TreatmentRankings[Study], TreatmentRankings[StratumCount]) >= 2, J44 = LOOKUP(A44, TreatmentRankings[Study], TreatmentRankings[StratumCount]) * 2) -> #VALUE! | Z44: =IF(H44, "exempt-synthetic", IF(AND(Y44, LOOKUP(A44, StratumVariables[Study], StratumVariables[VariableName]) <> ""), "all", "partial")) -> #VALUE!
A45: hanley-power-lines-2000 | B45: =A45 -> hanley-power-lines-2000 | C45: Power Lines and Childhood Leukemia: Five-Study Meta-Analysis | D45: Hanley JA, Theriault G. Epidemiology 2000. Five studies, ≤100m exposure. A=exposed B=unexposed, success=leukemia case. | E45: https://doi.org/10.1097/00001648-200009000-00022 | F45: 2000 | G45: epidemiology | H45: FALSE | I45: =SUMIFS(CaseCells!G2:G999,CaseCells!C2:C999, A45) -> 1515 | J45: =COUNTIFS(CaseCells!C2:C999, A45) -> 10 | K45: tradition-epidemiology | L45: researcher-greenland | M45: =LOOKUP(K45, ResearchTraditions[TraditionId], ResearchTraditions[Name]) -> #VALUE! | N45: =LOOKUP(K45, ResearchTraditions[TraditionId], ResearchTraditions[CoreConcern]) -> #VALUE! | O45: =LOOKUP(L45, Researchers[ResearcherId], Researchers[Name]) -> #VALUE! | P45: =LOOKUP(L45, Researchers[ResearcherId], Researchers[Affiliation]) -> #VALUE! | Q45: =LOOKUP(A45, TreatmentRankings[Study], TreatmentRankings[DistortionType]) -> #VALUE! | R45: =LOOKUP(A45, TreatmentRankings[Study], TreatmentRankings[CorrectedPolicyImplication]) -> #VALUE! | S45: =LOOKUP(A45, TreatmentRankings[Study], TreatmentRankings[AllocationDistortion]) -> #VALUE! | T45: =LOOKUP(A45, TreatmentRankings[Study], TreatmentRankings[SignalPurity]) -> #VALUE! | U45: =LOOKUP(A45, TreatmentRankings[Study], TreatmentRankings[IsSignFlip]) -> #VALUE! | V45: =LOOKUP(A45, TreatmentRankings[Study], TreatmentRankings[CorrectedWinner]) -> #VALUE! | W45: =LOOKUP(A45, StratumVariables[Study], StratumVariables[VariableName]) -> #VALUE! | X45: =LOOKUP(A45, StratumVariables[Study], StratumVariables[CausalRole]) -> #VALUE! | Y45: =AND(LOOKUP(A45, TreatmentRankings[Study], TreatmentRankings[StratumCount]) >= 2, J45 = LOOKUP(A45, TreatmentRankings[Study], TreatmentRankings[StratumCount]) * 2) -> #VALUE! | Z45: =IF(H45, "exempt-synthetic", IF(AND(Y45, LOOKUP(A45, StratumVariables[Study], StratumVariables[VariableName]) <> ""), "all", "partial")) -> #VALUE!
A46: coffee-smoking-lung-1968 | B46: =A46 -> coffee-smoking-lung-1968 | C46: Coffee and Lung Cancer by Smoking Status | D46: Classic confounding structure (Cornfield / epidemiology textbooks). A=coffee drinker, success=lung cancer case. | F46: 1968 | G46: epidemiology | H46: FALSE | I46: =SUMIFS(CaseCells!G2:G999,CaseCells!C2:C999, A46) -> 1116 | J46: =COUNTIFS(CaseCells!C2:C999, A46) -> 4 | K46: tradition-epidemiology | L46: researcher-greenland | M46: =LOOKUP(K46, ResearchTraditions[TraditionId], ResearchTraditions[Name]) -> #VALUE! | N46: =LOOKUP(K46, ResearchTraditions[TraditionId], ResearchTraditions[CoreConcern]) -> #VALUE! | O46: =LOOKUP(L46, Researchers[ResearcherId], Researchers[Name]) -> #VALUE! | P46: =LOOKUP(L46, Researchers[ResearcherId], Researchers[Affiliation]) -> #VALUE! | Q46: =LOOKUP(A46, TreatmentRankings[Study], TreatmentRankings[DistortionType]) -> #VALUE! | R46: =LOOKUP(A46, TreatmentRankings[Study], TreatmentRankings[CorrectedPolicyImplication]) -> #VALUE! | S46: =LOOKUP(A46, TreatmentRankings[Study], TreatmentRankings[AllocationDistortion]) -> #VALUE! | T46: =LOOKUP(A46, TreatmentRankings[Study], TreatmentRankings[SignalPurity]) -> #VALUE! | U46: =LOOKUP(A46, TreatmentRankings[Study], TreatmentRankings[IsSignFlip]) -> #VALUE! | V46: =LOOKUP(A46, TreatmentRankings[Study], TreatmentRankings[CorrectedWinner]) -> #VALUE! | W46: =LOOKUP(A46, StratumVariables[Study], StratumVariables[VariableName]) -> #VALUE! | X46: =LOOKUP(A46, StratumVariables[Study], StratumVariables[CausalRole]) -> #VALUE! | Y46: =AND(LOOKUP(A46, TreatmentRankings[Study], TreatmentRankings[StratumCount]) >= 2, J46 = LOOKUP(A46, TreatmentRankings[Study], TreatmentRankings[StratumCount]) * 2) -> #VALUE! | Z46: =IF(H46, "exempt-synthetic", IF(AND(Y46, LOOKUP(A46, StratumVariables[Study], StratumVariables[VariableName]) <> ""), "all", "partial")) -> #VALUE!
A47: panama-sweden-mortality-1975 | B47: =A47 -> panama-sweden-mortality-1975 | C47: Panama vs Sweden Survival by Age Group (Rothman) | D47: Rothman KJ. Modern Epidemiology 2nd ed. Age-composition paradox. A=Panama B=Sweden, success=survival. | F47: 1975 | G47: epidemiology | H47: FALSE | I47: =SUMIFS(CaseCells!G2:G999,CaseCells!C2:C999, A47) -> 2000 | J47: =COUNTIFS(CaseCells!C2:C999, A47) -> 6 | K47: tradition-epidemiology | L47: researcher-greenland | M47: =LOOKUP(K47, ResearchTraditions[TraditionId], ResearchTraditions[Name]) -> #VALUE! | N47: =LOOKUP(K47, ResearchTraditions[TraditionId], ResearchTraditions[CoreConcern]) -> #VALUE! | O47: =LOOKUP(L47, Researchers[ResearcherId], Researchers[Name]) -> #VALUE! | P47: =LOOKUP(L47, Researchers[ResearcherId], Researchers[Affiliation]) -> #VALUE! | Q47: =LOOKUP(A47, TreatmentRankings[Study], TreatmentRankings[DistortionType]) -> #VALUE! | R47: =LOOKUP(A47, TreatmentRankings[Study], TreatmentRankings[CorrectedPolicyImplication]) -> #VALUE! | S47: =LOOKUP(A47, TreatmentRankings[Study], TreatmentRankings[AllocationDistortion]) -> #VALUE! | T47: =LOOKUP(A47, TreatmentRankings[Study], TreatmentRankings[SignalPurity]) -> #VALUE! | U47: =LOOKUP(A47, TreatmentRankings[Study], TreatmentRankings[IsSignFlip]) -> #VALUE! | V47: =LOOKUP(A47, TreatmentRankings[Study], TreatmentRankings[CorrectedWinner]) -> #VALUE! | W47: =LOOKUP(A47, StratumVariables[Study], StratumVariables[VariableName]) -> #VALUE! | X47: =LOOKUP(A47, StratumVariables[Study], StratumVariables[CausalRole]) -> #VALUE! | Y47: =AND(LOOKUP(A47, TreatmentRankings[Study], TreatmentRankings[StratumCount]) >= 2, J47 = LOOKUP(A47, TreatmentRankings[Study], TreatmentRankings[StratumCount]) * 2) -> #VALUE! | Z47: =IF(H47, "exempt-synthetic", IF(AND(Y47, LOOKUP(A47, StratumVariables[Study], StratumVariables[VariableName]) <> ""), "all", "partial")) -> #VALUE!
A48: hrt-whi-2002 | B48: =A48 -> hrt-whi-2002 | C48: HRT and CHD: Observational vs WHI RCT Design Reversal | D48: Writing Group for the WHI Investigators. JAMA 2002. Strata = study design (observational vs RCT). A=HRT, B=control/comparator, success=CHD event-free survival. | E48: https://doi.org/10.1001/jama.288.3.321 | F48: 2002 | G48: medicine | H48: FALSE | I48: =SUMIFS(CaseCells!G2:G999,CaseCells!C2:C999, A48) -> 210000 | J48: =COUNTIFS(CaseCells!C2:C999, A48) -> 4 | K48: tradition-epidemiology | L48: researcher-greenland | M48: =LOOKUP(K48, ResearchTraditions[TraditionId], ResearchTraditions[Name]) -> #VALUE! | N48: =LOOKUP(K48, ResearchTraditions[TraditionId], ResearchTraditions[CoreConcern]) -> #VALUE! | O48: =LOOKUP(L48, Researchers[ResearcherId], Researchers[Name]) -> #VALUE! | P48: =LOOKUP(L48, Researchers[ResearcherId], Researchers[Affiliation]) -> #VALUE! | Q48: =LOOKUP(A48, TreatmentRankings[Study], TreatmentRankings[DistortionType]) -> #VALUE! | R48: =LOOKUP(A48, TreatmentRankings[Study], TreatmentRankings[CorrectedPolicyImplication]) -> #VALUE! | S48: =LOOKUP(A48, TreatmentRankings[Study], TreatmentRankings[AllocationDistortion]) -> #VALUE! | T48: =LOOKUP(A48, TreatmentRankings[Study], TreatmentRankings[SignalPurity]) -> #VALUE! | U48: =LOOKUP(A48, TreatmentRankings[Study], TreatmentRankings[IsSignFlip]) -> #VALUE! | V48: =LOOKUP(A48, TreatmentRankings[Study], TreatmentRankings[CorrectedWinner]) -> #VALUE! | W48: =LOOKUP(A48, StratumVariables[Study], StratumVariables[VariableName]) -> #VALUE! | X48: =LOOKUP(A48, StratumVariables[Study], StratumVariables[CausalRole]) -> #VALUE! | Y48: =AND(LOOKUP(A48, TreatmentRankings[Study], TreatmentRankings[StratumCount]) >= 2, J48 = LOOKUP(A48, TreatmentRankings[Study], TreatmentRankings[StratumCount]) * 2) -> #VALUE! | Z48: =IF(H48, "exempt-synthetic", IF(AND(Y48, LOOKUP(A48, StratumVariables[Study], StratumVariables[VariableName]) <> ""), "all", "partial")) -> #VALUE!
A49: obesity-paradox-hf | B49: =A49 -> obesity-paradox-hf | C49: Obesity Paradox in Heart Failure Patients | D49: Gruberg L et al. Am Heart J 2003. A=obese BMI≥30, B=normal weight, success=survival. Strata: HF status. | E49: https://pubmed.ncbi.nlm.nih.gov/12766738/ | F49: 2003 | G49: medicine | H49: FALSE | I49: =SUMIFS(CaseCells!G2:G999,CaseCells!C2:C999, A49) -> 4000 | J49: =COUNTIFS(CaseCells!C2:C999, A49) -> 4 | K49: tradition-epidemiology | L49: researcher-greenland | M49: =LOOKUP(K49, ResearchTraditions[TraditionId], ResearchTraditions[Name]) -> #VALUE! | N49: =LOOKUP(K49, ResearchTraditions[TraditionId], ResearchTraditions[CoreConcern]) -> #VALUE! | O49: =LOOKUP(L49, Researchers[ResearcherId], Researchers[Name]) -> #VALUE! | P49: =LOOKUP(L49, Researchers[ResearcherId], Researchers[Affiliation]) -> #VALUE! | Q49: =LOOKUP(A49, TreatmentRankings[Study], TreatmentRankings[DistortionType]) -> #VALUE! | R49: =LOOKUP(A49, TreatmentRankings[Study], TreatmentRankings[CorrectedPolicyImplication]) -> #VALUE! | S49: =LOOKUP(A49, TreatmentRankings[Study], TreatmentRankings[AllocationDistortion]) -> #VALUE! | T49: =LOOKUP(A49, TreatmentRankings[Study], TreatmentRankings[SignalPurity]) -> #VALUE! | U49: =LOOKUP(A49, TreatmentRankings[Study], TreatmentRankings[IsSignFlip]) -> #VALUE! | V49: =LOOKUP(A49, TreatmentRankings[Study], TreatmentRankings[CorrectedWinner]) -> #VALUE! | W49: =LOOKUP(A49, StratumVariables[Study], StratumVariables[VariableName]) -> #VALUE! | X49: =LOOKUP(A49, StratumVariables[Study], StratumVariables[CausalRole]) -> #VALUE! | Y49: =AND(LOOKUP(A49, TreatmentRankings[Study], TreatmentRankings[StratumCount]) >= 2, J49 = LOOKUP(A49, TreatmentRankings[Study], TreatmentRankings[StratumCount]) * 2) -> #VALUE! | Z49: =IF(H49, "exempt-synthetic", IF(AND(Y49, LOOKUP(A49, StratumVariables[Study], StratumVariables[VariableName]) <> ""), "all", "partial")) -> #VALUE!
A50: dialysis-bmi-survival | B50: =A50 -> dialysis-bmi-survival | C50: Dialysis BMI Survival: Reverse Epidemiology | D50: Kalantar-Zadeh K et al. Kidney Int 2003. A=obese, B=normal weight, success=survival. Strata: ESRD/dialysis status. | E50: https://pubmed.ncbi.nlm.nih.gov/12776250/ | F50: 2001 | G50: medicine | H50: FALSE | I50: =SUMIFS(CaseCells!G2:G999,CaseCells!C2:C999, A50) -> 4000 | J50: =COUNTIFS(CaseCells!C2:C999, A50) -> 4 | K50: tradition-epidemiology | L50: researcher-greenland | M50: =LOOKUP(K50, ResearchTraditions[TraditionId], ResearchTraditions[Name]) -> #VALUE! | N50: =LOOKUP(K50, ResearchTraditions[TraditionId], ResearchTraditions[CoreConcern]) -> #VALUE! | O50: =LOOKUP(L50, Researchers[ResearcherId], Researchers[Name]) -> #VALUE! | P50: =LOOKUP(L50, Researchers[ResearcherId], Researchers[Affiliation]) -> #VALUE! | Q50: =LOOKUP(A50, TreatmentRankings[Study], TreatmentRankings[DistortionType]) -> #VALUE! | R50: =LOOKUP(A50, TreatmentRankings[Study], TreatmentRankings[CorrectedPolicyImplication]) -> #VALUE! | S50: =LOOKUP(A50, TreatmentRankings[Study], TreatmentRankings[AllocationDistortion]) -> #VALUE! | T50: =LOOKUP(A50, TreatmentRankings[Study], TreatmentRankings[SignalPurity]) -> #VALUE! | U50: =LOOKUP(A50, TreatmentRankings[Study], TreatmentRankings[IsSignFlip]) -> #VALUE! | V50: =LOOKUP(A50, TreatmentRankings[Study], TreatmentRankings[CorrectedWinner]) -> #VALUE! | W50: =LOOKUP(A50, StratumVariables[Study], StratumVariables[VariableName]) -> #VALUE! | X50: =LOOKUP(A50, StratumVariables[Study], StratumVariables[CausalRole]) -> #VALUE! | Y50: =AND(LOOKUP(A50, TreatmentRankings[Study], TreatmentRankings[StratumCount]) >= 2, J50 = LOOKUP(A50, TreatmentRankings[Study], TreatmentRankings[StratumCount]) * 2) -> #VALUE! | Z50: =IF(H50, "exempt-synthetic", IF(AND(Y50, LOOKUP(A50, StratumVariables[Study], StratumVariables[VariableName]) <> ""), "all", "partial")) -> #VALUE!
A51: sick-quitter-alcohol | B51: =A51 -> sick-quitter-alcohol | C51: Sick-Quitter Alcohol J-Curve: Abstainer Reference Bias | D51: Shaper AG et al. BMJ 1988. A=moderate drinker, B=abstainer, success=survival. Strata partition abstainer composition. | E51: https://pubmed.ncbi.nlm.nih.gov/3143436/ | F51: 1988 | G51: medicine | H51: FALSE | I51: =SUMIFS(CaseCells!G2:G999,CaseCells!C2:C999, A51) -> 4000 | J51: =COUNTIFS(CaseCells!C2:C999, A51) -> 4 | K51: tradition-epidemiology | L51: researcher-greenland | M51: =LOOKUP(K51, ResearchTraditions[TraditionId], ResearchTraditions[Name]) -> #VALUE! | N51: =LOOKUP(K51, ResearchTraditions[TraditionId], ResearchTraditions[CoreConcern]) -> #VALUE! | O51: =LOOKUP(L51, Researchers[ResearcherId], Researchers[Name]) -> #VALUE! | P51: =LOOKUP(L51, Researchers[ResearcherId], Researchers[Affiliation]) -> #VALUE! | Q51: =LOOKUP(A51, TreatmentRankings[Study], TreatmentRankings[DistortionType]) -> #VALUE! | R51: =LOOKUP(A51, TreatmentRankings[Study], TreatmentRankings[CorrectedPolicyImplication]) -> #VALUE! | S51: =LOOKUP(A51, TreatmentRankings[Study], TreatmentRankings[AllocationDistortion]) -> #VALUE! | T51: =LOOKUP(A51, TreatmentRankings[Study], TreatmentRankings[SignalPurity]) -> #VALUE! | U51: =LOOKUP(A51, TreatmentRankings[Study], TreatmentRankings[IsSignFlip]) -> #VALUE! | V51: =LOOKUP(A51, TreatmentRankings[Study], TreatmentRankings[CorrectedWinner]) -> #VALUE! | W51: =LOOKUP(A51, StratumVariables[Study], StratumVariables[VariableName]) -> #VALUE! | X51: =LOOKUP(A51, StratumVariables[Study], StratumVariables[CausalRole]) -> #VALUE! | Y51: =AND(LOOKUP(A51, TreatmentRankings[Study], TreatmentRankings[StratumCount]) >= 2, J51 = LOOKUP(A51, TreatmentRankings[Study], TreatmentRankings[StratumCount]) * 2) -> #VALUE! | Z51: =IF(H51, "exempt-synthetic", IF(AND(Y51, LOOKUP(A51, StratumVariables[Study], StratumVariables[VariableName]) <> ""), "all", "partial")) -> #VALUE!
A52: flu-vaccine-elderly-mortality | B52: =A52 -> flu-vaccine-elderly-mortality | C52: Flu Vaccine and Elderly Mortality: Frailty Selection Paradox | D52: Jackson LA et al. Int J Epidemiol 2006. A=vaccinated, B=unvaccinated, success=survival (inverse of mortality). Strata: age group. | E52: https://pubmed.ncbi.nlm.nih.gov/16338918/ | F52: 2005 | G52: medicine | H52: FALSE | I52: =SUMIFS(CaseCells!G2:G999,CaseCells!C2:C999, A52) -> 248000 | J52: =COUNTIFS(CaseCells!C2:C999, A52) -> 4 | K52: tradition-epidemiology | L52: researcher-greenland | M52: =LOOKUP(K52, ResearchTraditions[TraditionId], ResearchTraditions[Name]) -> #VALUE! | N52: =LOOKUP(K52, ResearchTraditions[TraditionId], ResearchTraditions[CoreConcern]) -> #VALUE! | O52: =LOOKUP(L52, Researchers[ResearcherId], Researchers[Name]) -> #VALUE! | P52: =LOOKUP(L52, Researchers[ResearcherId], Researchers[Affiliation]) -> #VALUE! | Q52: =LOOKUP(A52, TreatmentRankings[Study], TreatmentRankings[DistortionType]) -> #VALUE! | R52: =LOOKUP(A52, TreatmentRankings[Study], TreatmentRankings[CorrectedPolicyImplication]) -> #VALUE! | S52: =LOOKUP(A52, TreatmentRankings[Study], TreatmentRankings[AllocationDistortion]) -> #VALUE! | T52: =LOOKUP(A52, TreatmentRankings[Study], TreatmentRankings[SignalPurity]) -> #VALUE! | U52: =LOOKUP(A52, TreatmentRankings[Study], TreatmentRankings[IsSignFlip]) -> #VALUE! | V52: =LOOKUP(A52, TreatmentRankings[Study], TreatmentRankings[CorrectedWinner]) -> #VALUE! | W52: =LOOKUP(A52, StratumVariables[Study], StratumVariables[VariableName]) -> #VALUE! | X52: =LOOKUP(A52, StratumVariables[Study], StratumVariables[CausalRole]) -> #VALUE! | Y52: =AND(LOOKUP(A52, TreatmentRankings[Study], TreatmentRankings[StratumCount]) >= 2, J52 = LOOKUP(A52, TreatmentRankings[Study], TreatmentRankings[StratumCount]) * 2) -> #VALUE! | Z52: =IF(H52, "exempt-synthetic", IF(AND(Y52, LOOKUP(A52, StratumVariables[Study], StratumVariables[VariableName]) <> ""), "all", "partial")) -> #VALUE!
A53: covid-italy-china-cfr-2020 | B53: =A53 -> covid-italy-china-cfr-2020 | C53: COVID-19 CFR: Italy vs China by Age (von Kügelgen 2021) | D53: von Kügelgen J et al. Nature 2021. A=Italy, B=China, success=survival. Age-stratified CFR reversal from population age structure. | E53: https://doi.org/10.1038/s41586-021-03694-z | F53: 2020 | G53: epidemiology | H53: FALSE | I53: =SUMIFS(CaseCells!G2:G999,CaseCells!C2:C999, A53) -> 53400 | J53: =COUNTIFS(CaseCells!C2:C999, A53) -> 4 | K53: tradition-epidemiology | L53: researcher-greenland | M53: =LOOKUP(K53, ResearchTraditions[TraditionId], ResearchTraditions[Name]) -> #VALUE! | N53: =LOOKUP(K53, ResearchTraditions[TraditionId], ResearchTraditions[CoreConcern]) -> #VALUE! | O53: =LOOKUP(L53, Researchers[ResearcherId], Researchers[Name]) -> #VALUE! | P53: =LOOKUP(L53, Researchers[ResearcherId], Researchers[Affiliation]) -> #VALUE! | Q53: =LOOKUP(A53, TreatmentRankings[Study], TreatmentRankings[DistortionType]) -> #VALUE! | R53: =LOOKUP(A53, TreatmentRankings[Study], TreatmentRankings[CorrectedPolicyImplication]) -> #VALUE! | S53: =LOOKUP(A53, TreatmentRankings[Study], TreatmentRankings[AllocationDistortion]) -> #VALUE! | T53: =LOOKUP(A53, TreatmentRankings[Study], TreatmentRankings[SignalPurity]) -> #VALUE! | U53: =LOOKUP(A53, TreatmentRankings[Study], TreatmentRankings[IsSignFlip]) -> #VALUE! | V53: =LOOKUP(A53, TreatmentRankings[Study], TreatmentRankings[CorrectedWinner]) -> #VALUE! | W53: =LOOKUP(A53, StratumVariables[Study], StratumVariables[VariableName]) -> #VALUE! | X53: =LOOKUP(A53, StratumVariables[Study], StratumVariables[CausalRole]) -> #VALUE! | Y53: =AND(LOOKUP(A53, TreatmentRankings[Study], TreatmentRankings[StratumCount]) >= 2, J53 = LOOKUP(A53, TreatmentRankings[Study], TreatmentRankings[StratumCount]) * 2) -> #VALUE! | Z53: =IF(H53, "exempt-synthetic", IF(AND(Y53, LOOKUP(A53, StratumVariables[Study], StratumVariables[VariableName]) <> ""), "all", "partial")) -> #VALUE!
A54: israel-covid-severe-2021 | B54: =A54 -> israel-covid-severe-2021 | C54: Israel COVID-19 Severe Disease: Vaccinated vs Unvaccinated by Age (2021) | D54: Goldberg Y et al. NEJM 2021. A=vaccinated, B=unvaccinated, success=non-severe outcome. Independent from phe-covid-2021 UK dataset. | E54: https://doi.org/10.1056/NEJMoa2111456 | F54: 2021 | G54: epidemiology | H54: FALSE | I54: =SUMIFS(CaseCells!G2:G999,CaseCells!C2:C999, A54) -> 163000 | J54: =COUNTIFS(CaseCells!C2:C999, A54) -> 4 | K54: tradition-epidemiology | L54: researcher-greenland | M54: =LOOKUP(K54, ResearchTraditions[TraditionId], ResearchTraditions[Name]) -> #VALUE! | N54: =LOOKUP(K54, ResearchTraditions[TraditionId], ResearchTraditions[CoreConcern]) -> #VALUE! | O54: =LOOKUP(L54, Researchers[ResearcherId], Researchers[Name]) -> #VALUE! | P54: =LOOKUP(L54, Researchers[ResearcherId], Researchers[Affiliation]) -> #VALUE! | Q54: =LOOKUP(A54, TreatmentRankings[Study], TreatmentRankings[DistortionType]) -> #VALUE! | R54: =LOOKUP(A54, TreatmentRankings[Study], TreatmentRankings[CorrectedPolicyImplication]) -> #VALUE! | S54: =LOOKUP(A54, TreatmentRankings[Study], TreatmentRankings[AllocationDistortion]) -> #VALUE! | T54: =LOOKUP(A54, TreatmentRankings[Study], TreatmentRankings[SignalPurity]) -> #VALUE! | U54: =LOOKUP(A54, TreatmentRankings[Study], TreatmentRankings[IsSignFlip]) -> #VALUE! | V54: =LOOKUP(A54, TreatmentRankings[Study], TreatmentRankings[CorrectedWinner]) -> #VALUE! | W54: =LOOKUP(A54, StratumVariables[Study], StratumVariables[VariableName]) -> #VALUE! | X54: =LOOKUP(A54, StratumVariables[Study], StratumVariables[CausalRole]) -> #VALUE! | Y54: =AND(LOOKUP(A54, TreatmentRankings[Study], TreatmentRankings[StratumCount]) >= 2, J54 = LOOKUP(A54, TreatmentRankings[Study], TreatmentRankings[StratumCount]) * 2) -> #VALUE! | Z54: =IF(H54, "exempt-synthetic", IF(AND(Y54, LOOKUP(A54, StratumVariables[Study], StratumVariables[VariableName]) <> ""), "all", "partial")) -> #VALUE!
A55: cochran-smoking-1968 | B55: =A55 -> cochran-smoking-1968 | C55: Smoking and Mortality by Age (Cochran / Surgeon General 1964) | D55: Cochran WG. US Surgeon General Report 1964 Chapter 8. A=smoker, B=non-smoker, success=survival. Age composition produces crude reversal. | E55: https://www.unav.edu/documents/16089811/16155256/Smoking+and+Health+the+Surgeon+General+Report+1964.pdf | F55: 1968 | G55: epidemiology | H55: FALSE | I55: =SUMIFS(CaseCells!G2:G999,CaseCells!C2:C999, A55) -> 13000 | J55: =COUNTIFS(CaseCells!C2:C999, A55) -> 4 | K55: tradition-epidemiology | L55: researcher-greenland | M55: =LOOKUP(K55, ResearchTraditions[TraditionId], ResearchTraditions[Name]) -> #VALUE! | N55: =LOOKUP(K55, ResearchTraditions[TraditionId], ResearchTraditions[CoreConcern]) -> #VALUE! | O55: =LOOKUP(L55, Researchers[ResearcherId], Researchers[Name]) -> #VALUE! | P55: =LOOKUP(L55, Researchers[ResearcherId], Researchers[Affiliation]) -> #VALUE! | Q55: =LOOKUP(A55, TreatmentRankings[Study], TreatmentRankings[DistortionType]) -> #VALUE! | R55: =LOOKUP(A55, TreatmentRankings[Study], TreatmentRankings[CorrectedPolicyImplication]) -> #VALUE! | S55: =LOOKUP(A55, TreatmentRankings[Study], TreatmentRankings[AllocationDistortion]) -> #VALUE! | T55: =LOOKUP(A55, TreatmentRankings[Study], TreatmentRankings[SignalPurity]) -> #VALUE! | U55: =LOOKUP(A55, TreatmentRankings[Study], TreatmentRankings[IsSignFlip]) -> #VALUE! | V55: =LOOKUP(A55, TreatmentRankings[Study], TreatmentRankings[CorrectedWinner]) -> #VALUE! | W55: =LOOKUP(A55, StratumVariables[Study], StratumVariables[VariableName]) -> #VALUE! | X55: =LOOKUP(A55, StratumVariables[Study], StratumVariables[CausalRole]) -> #VALUE! | Y55: =AND(LOOKUP(A55, TreatmentRankings[Study], TreatmentRankings[StratumCount]) >= 2, J55 = LOOKUP(A55, TreatmentRankings[Study], TreatmentRankings[StratumCount]) * 2) -> #VALUE! | Z55: =IF(H55, "exempt-synthetic", IF(AND(Y55, LOOKUP(A55, StratumVariables[Study], StratumVariables[VariableName]) <> ""), "all", "partial")) -> #VALUE!
A56: healthy-worker-mortality | B56: =A56 -> healthy-worker-mortality | C56: Healthy Worker Effect: Occupational Mortality Selection | D56: Monson RR. Occupational Epidemiology 1990. A=employed, B=unemployed/general pop, success=survival. Selection at hire. | F56: 1987 | G56: epidemiology | H56: FALSE | I56: =SUMIFS(CaseCells!G2:G999,CaseCells!C2:C999, A56) -> 4000 | J56: =COUNTIFS(CaseCells!C2:C999, A56) -> 4 | K56: tradition-epidemiology | L56: researcher-greenland | M56: =LOOKUP(K56, ResearchTraditions[TraditionId], ResearchTraditions[Name]) -> #VALUE! | N56: =LOOKUP(K56, ResearchTraditions[TraditionId], ResearchTraditions[CoreConcern]) -> #VALUE! | O56: =LOOKUP(L56, Researchers[ResearcherId], Researchers[Name]) -> #VALUE! | P56: =LOOKUP(L56, Researchers[ResearcherId], Researchers[Affiliation]) -> #VALUE! | Q56: =LOOKUP(A56, TreatmentRankings[Study], TreatmentRankings[DistortionType]) -> #VALUE! | R56: =LOOKUP(A56, TreatmentRankings[Study], TreatmentRankings[CorrectedPolicyImplication]) -> #VALUE! | S56: =LOOKUP(A56, TreatmentRankings[Study], TreatmentRankings[AllocationDistortion]) -> #VALUE! | T56: =LOOKUP(A56, TreatmentRankings[Study], TreatmentRankings[SignalPurity]) -> #VALUE! | U56: =LOOKUP(A56, TreatmentRankings[Study], TreatmentRankings[IsSignFlip]) -> #VALUE! | V56: =LOOKUP(A56, TreatmentRankings[Study], TreatmentRankings[CorrectedWinner]) -> #VALUE! | W56: =LOOKUP(A56, StratumVariables[Study], StratumVariables[VariableName]) -> #VALUE! | X56: =LOOKUP(A56, StratumVariables[Study], StratumVariables[CausalRole]) -> #VALUE! | Y56: =AND(LOOKUP(A56, TreatmentRankings[Study], TreatmentRankings[StratumCount]) >= 2, J56 = LOOKUP(A56, TreatmentRankings[Study], TreatmentRankings[StratumCount]) * 2) -> #VALUE! | Z56: =IF(H56, "exempt-synthetic", IF(AND(Y56, LOOKUP(A56, StratumVariables[Study], StratumVariables[VariableName]) <> ""), "all", "partial")) -> #VALUE!
A57: compas-recidivism-base | B57: =A57 -> compas-recidivism-base | C57: COMPAS Recidivism: Base-Rate Fairness Paradox | D57: Chouldechova A. Big Data 2017; ProPublica COMPAS analysis. A=COMPAS high-risk prediction, B=low-risk, success=no recidivism. | E57: https://arxiv.org/abs/1610.07524 | F57: 2016 | G57: legal | H57: FALSE | I57: =SUMIFS(CaseCells!G2:G999,CaseCells!C2:C999, A57) -> 4000 | J57: =COUNTIFS(CaseCells!C2:C999, A57) -> 4 | K57: tradition-ai-fairness | L57: researcher-chouldechova | M57: =LOOKUP(K57, ResearchTraditions[TraditionId], ResearchTraditions[Name]) -> #VALUE! | N57: =LOOKUP(K57, ResearchTraditions[TraditionId], ResearchTraditions[CoreConcern]) -> #VALUE! | O57: =LOOKUP(L57, Researchers[ResearcherId], Researchers[Name]) -> #VALUE! | P57: =LOOKUP(L57, Researchers[ResearcherId], Researchers[Affiliation]) -> #VALUE! | Q57: =LOOKUP(A57, TreatmentRankings[Study], TreatmentRankings[DistortionType]) -> #VALUE! | R57: =LOOKUP(A57, TreatmentRankings[Study], TreatmentRankings[CorrectedPolicyImplication]) -> #VALUE! | S57: =LOOKUP(A57, TreatmentRankings[Study], TreatmentRankings[AllocationDistortion]) -> #VALUE! | T57: =LOOKUP(A57, TreatmentRankings[Study], TreatmentRankings[SignalPurity]) -> #VALUE! | U57: =LOOKUP(A57, TreatmentRankings[Study], TreatmentRankings[IsSignFlip]) -> #VALUE! | V57: =LOOKUP(A57, TreatmentRankings[Study], TreatmentRankings[CorrectedWinner]) -> #VALUE! | W57: =LOOKUP(A57, StratumVariables[Study], StratumVariables[VariableName]) -> #VALUE! | X57: =LOOKUP(A57, StratumVariables[Study], StratumVariables[CausalRole]) -> #VALUE! | Y57: =AND(LOOKUP(A57, TreatmentRankings[Study], TreatmentRankings[StratumCount]) >= 2, J57 = LOOKUP(A57, TreatmentRankings[Study], TreatmentRankings[StratumCount]) * 2) -> #VALUE! | Z57: =IF(H57, "exempt-synthetic", IF(AND(Y57, LOOKUP(A57, StratumVariables[Study], StratumVariables[VariableName]) <> ""), "all", "partial")) -> #VALUE!
A58: us-wage-composition-stagnation | B58: =A58 -> us-wage-composition-stagnation | C58: US Wage Stagnation: Composition-Over-Time Paradox | D58: Autor DH. NBER working paper series. A=2018 cohort, B=1978 cohort, success=above-median wage. Strata: education group. | E58: https://www.nber.org/papers/w24400 | F58: 2018 | G58: economics | H58: FALSE | I58: =SUMIFS(CaseCells!G2:G999,CaseCells!C2:C999, A58) -> 31000 | J58: =COUNTIFS(CaseCells!C2:C999, A58) -> 4 | K58: tradition-epidemiology | L58: researcher-greenland | M58: =LOOKUP(K58, ResearchTraditions[TraditionId], ResearchTraditions[Name]) -> #VALUE! | N58: =LOOKUP(K58, ResearchTraditions[TraditionId], ResearchTraditions[CoreConcern]) -> #VALUE! | O58: =LOOKUP(L58, Researchers[ResearcherId], Researchers[Name]) -> #VALUE! | P58: =LOOKUP(L58, Researchers[ResearcherId], Researchers[Affiliation]) -> #VALUE! | Q58: =LOOKUP(A58, TreatmentRankings[Study], TreatmentRankings[DistortionType]) -> #VALUE! | R58: =LOOKUP(A58, TreatmentRankings[Study], TreatmentRankings[CorrectedPolicyImplication]) -> #VALUE! | S58: =LOOKUP(A58, TreatmentRankings[Study], TreatmentRankings[AllocationDistortion]) -> #VALUE! | T58: =LOOKUP(A58, TreatmentRankings[Study], TreatmentRankings[SignalPurity]) -> #VALUE! | U58: =LOOKUP(A58, TreatmentRankings[Study], TreatmentRankings[IsSignFlip]) -> #VALUE! | V58: =LOOKUP(A58, TreatmentRankings[Study], TreatmentRankings[CorrectedWinner]) -> #VALUE! | W58: =LOOKUP(A58, StratumVariables[Study], StratumVariables[VariableName]) -> #VALUE! | X58: =LOOKUP(A58, StratumVariables[Study], StratumVariables[CausalRole]) -> #VALUE! | Y58: =AND(LOOKUP(A58, TreatmentRankings[Study], TreatmentRankings[StratumCount]) >= 2, J58 = LOOKUP(A58, TreatmentRankings[Study], TreatmentRankings[StratumCount]) * 2) -> #VALUE! | Z58: =IF(H58, "exempt-synthetic", IF(AND(Y58, LOOKUP(A58, StratumVariables[Study], StratumVariables[VariableName]) <> ""), "all", "partial")) -> #VALUE!
A59: borjas-immigrant-cohort | B59: =A59 -> borjas-immigrant-cohort | C59: Borjas Immigrant Earnings: Cohort vs Cross-Section Reversal | D59: Borjas GJ. J Labor Econ 1985. A=recent immigrant, B=native-born, success=above-poverty earnings. | E59: https://doi.org/10.1086/298065 | F59: 1987 | G59: economics | H59: FALSE | I59: =SUMIFS(CaseCells!G2:G999,CaseCells!C2:C999, A59) -> 4000 | J59: =COUNTIFS(CaseCells!C2:C999, A59) -> 4 | K59: tradition-epidemiology | L59: researcher-greenland | M59: =LOOKUP(K59, ResearchTraditions[TraditionId], ResearchTraditions[Name]) -> #VALUE! | N59: =LOOKUP(K59, ResearchTraditions[TraditionId], ResearchTraditions[CoreConcern]) -> #VALUE! | O59: =LOOKUP(L59, Researchers[ResearcherId], Researchers[Name]) -> #VALUE! | P59: =LOOKUP(L59, Researchers[ResearcherId], Researchers[Affiliation]) -> #VALUE! | Q59: =LOOKUP(A59, TreatmentRankings[Study], TreatmentRankings[DistortionType]) -> #VALUE! | R59: =LOOKUP(A59, TreatmentRankings[Study], TreatmentRankings[CorrectedPolicyImplication]) -> #VALUE! | S59: =LOOKUP(A59, TreatmentRankings[Study], TreatmentRankings[AllocationDistortion]) -> #VALUE! | T59: =LOOKUP(A59, TreatmentRankings[Study], TreatmentRankings[SignalPurity]) -> #VALUE! | U59: =LOOKUP(A59, TreatmentRankings[Study], TreatmentRankings[IsSignFlip]) -> #VALUE! | V59: =LOOKUP(A59, TreatmentRankings[Study], TreatmentRankings[CorrectedWinner]) -> #VALUE! | W59: =LOOKUP(A59, StratumVariables[Study], StratumVariables[VariableName]) -> #VALUE! | X59: =LOOKUP(A59, StratumVariables[Study], StratumVariables[CausalRole]) -> #VALUE! | Y59: =AND(LOOKUP(A59, TreatmentRankings[Study], TreatmentRankings[StratumCount]) >= 2, J59 = LOOKUP(A59, TreatmentRankings[Study], TreatmentRankings[StratumCount]) * 2) -> #VALUE! | Z59: =IF(H59, "exempt-synthetic", IF(AND(Y59, LOOKUP(A59, StratumVariables[Study], StratumVariables[VariableName]) <> ""), "all", "partial")) -> #VALUE!
A60: robinson-1950-literacy | B60: =A60 -> robinson-1950-literacy | C60: Robinson 1950: Literacy vs Nativity Ecological Fallacy | D60: Robinson WS. Am Sociol Rev 1950. A=foreign-born, B=native-born, success=literate. State-level aggregation strata. | E60: https://doi.org/10.2307/2087176 | F60: 1950 | G60: social-science | H60: FALSE | I60: =SUMIFS(CaseCells!G2:G999,CaseCells!C2:C999, A60) -> 14000 | J60: =COUNTIFS(CaseCells!C2:C999, A60) -> 4 | K60: tradition-historical | L60: researcher-blyth | M60: =LOOKUP(K60, ResearchTraditions[TraditionId], ResearchTraditions[Name]) -> #VALUE! | N60: =LOOKUP(K60, ResearchTraditions[TraditionId], ResearchTraditions[CoreConcern]) -> #VALUE! | O60: =LOOKUP(L60, Researchers[ResearcherId], Researchers[Name]) -> #VALUE! | P60: =LOOKUP(L60, Researchers[ResearcherId], Researchers[Affiliation]) -> #VALUE! | Q60: =LOOKUP(A60, TreatmentRankings[Study], TreatmentRankings[DistortionType]) -> #VALUE! | R60: =LOOKUP(A60, TreatmentRankings[Study], TreatmentRankings[CorrectedPolicyImplication]) -> #VALUE! | S60: =LOOKUP(A60, TreatmentRankings[Study], TreatmentRankings[AllocationDistortion]) -> #VALUE! | T60: =LOOKUP(A60, TreatmentRankings[Study], TreatmentRankings[SignalPurity]) -> #VALUE! | U60: =LOOKUP(A60, TreatmentRankings[Study], TreatmentRankings[IsSignFlip]) -> #VALUE! | V60: =LOOKUP(A60, TreatmentRankings[Study], TreatmentRankings[CorrectedWinner]) -> #VALUE! | W60: =LOOKUP(A60, StratumVariables[Study], StratumVariables[VariableName]) -> #VALUE! | X60: =LOOKUP(A60, StratumVariables[Study], StratumVariables[CausalRole]) -> #VALUE! | Y60: =AND(LOOKUP(A60, TreatmentRankings[Study], TreatmentRankings[StratumCount]) >= 2, J60 = LOOKUP(A60, TreatmentRankings[Study], TreatmentRankings[StratumCount]) * 2) -> #VALUE! | Z60: =IF(H60, "exempt-synthetic", IF(AND(Y60, LOOKUP(A60, StratumVariables[Study], StratumVariables[VariableName]) <> ""), "all", "partial")) -> #VALUE!
A61: ab-test-traffic-mix | B61: =A61 -> ab-test-traffic-mix | C61: A/B Test Reversal from Traffic Segment Mix Shift (Kohavi) | D61: Kohavi R et al. Trustworthy Online Controlled Experiments 2020. A=variant B (treatment), B=variant A (control), success=conversion. | E61: https://www.cambridge.org/core/books/trustworthy-online-controlled-experiments/ | F61: 2020 | G61: social-science | H61: FALSE | I61: =SUMIFS(CaseCells!G2:G999,CaseCells!C2:C999, A61) -> 24000 | J61: =COUNTIFS(CaseCells!C2:C999, A61) -> 4 | K61: tradition-historical | L61: researcher-blyth | M61: =LOOKUP(K61, ResearchTraditions[TraditionId], ResearchTraditions[Name]) -> #VALUE! | N61: =LOOKUP(K61, ResearchTraditions[TraditionId], ResearchTraditions[CoreConcern]) -> #VALUE! | O61: =LOOKUP(L61, Researchers[ResearcherId], Researchers[Name]) -> #VALUE! | P61: =LOOKUP(L61, Researchers[ResearcherId], Researchers[Affiliation]) -> #VALUE! | Q61: =LOOKUP(A61, TreatmentRankings[Study], TreatmentRankings[DistortionType]) -> #VALUE! | R61: =LOOKUP(A61, TreatmentRankings[Study], TreatmentRankings[CorrectedPolicyImplication]) -> #VALUE! | S61: =LOOKUP(A61, TreatmentRankings[Study], TreatmentRankings[AllocationDistortion]) -> #VALUE! | T61: =LOOKUP(A61, TreatmentRankings[Study], TreatmentRankings[SignalPurity]) -> #VALUE! | U61: =LOOKUP(A61, TreatmentRankings[Study], TreatmentRankings[IsSignFlip]) -> #VALUE! | V61: =LOOKUP(A61, TreatmentRankings[Study], TreatmentRankings[CorrectedWinner]) -> #VALUE! | W61: =LOOKUP(A61, StratumVariables[Study], StratumVariables[VariableName]) -> #VALUE! | X61: =LOOKUP(A61, StratumVariables[Study], StratumVariables[CausalRole]) -> #VALUE! | Y61: =AND(LOOKUP(A61, TreatmentRankings[Study], TreatmentRankings[StratumCount]) >= 2, J61 = LOOKUP(A61, TreatmentRankings[Study], TreatmentRankings[StratumCount]) * 2) -> #VALUE! | Z61: =IF(H61, "exempt-synthetic", IF(AND(Y61, LOOKUP(A61, StratumVariables[Study], StratumVariables[VariableName]) <> ""), "all", "partial")) -> #VALUE!
A62: recsys-offline-eval | B62: =A62 -> recsys-offline-eval | C62: Recommender Offline Evaluation: Exposure Popularity Bias | D62: Ding Y et al. arXiv:2104.08912. A=new model, B=baseline, success=accurate prediction. Strata by item popularity. | E62: https://arxiv.org/abs/2104.08912 | F62: 2021 | G62: social-science | H62: FALSE | I62: =SUMIFS(CaseCells!G2:G999,CaseCells!C2:C999, A62) -> 4000 | J62: =COUNTIFS(CaseCells!C2:C999, A62) -> 4 | K62: tradition-ai-fairness | L62: researcher-chouldechova | M62: =LOOKUP(K62, ResearchTraditions[TraditionId], ResearchTraditions[Name]) -> #VALUE! | N62: =LOOKUP(K62, ResearchTraditions[TraditionId], ResearchTraditions[CoreConcern]) -> #VALUE! | O62: =LOOKUP(L62, Researchers[ResearcherId], Researchers[Name]) -> #VALUE! | P62: =LOOKUP(L62, Researchers[ResearcherId], Researchers[Affiliation]) -> #VALUE! | Q62: =LOOKUP(A62, TreatmentRankings[Study], TreatmentRankings[DistortionType]) -> #VALUE! | R62: =LOOKUP(A62, TreatmentRankings[Study], TreatmentRankings[CorrectedPolicyImplication]) -> #VALUE! | S62: =LOOKUP(A62, TreatmentRankings[Study], TreatmentRankings[AllocationDistortion]) -> #VALUE! | T62: =LOOKUP(A62, TreatmentRankings[Study], TreatmentRankings[SignalPurity]) -> #VALUE! | U62: =LOOKUP(A62, TreatmentRankings[Study], TreatmentRankings[IsSignFlip]) -> #VALUE! | V62: =LOOKUP(A62, TreatmentRankings[Study], TreatmentRankings[CorrectedWinner]) -> #VALUE! | W62: =LOOKUP(A62, StratumVariables[Study], StratumVariables[VariableName]) -> #VALUE! | X62: =LOOKUP(A62, StratumVariables[Study], StratumVariables[CausalRole]) -> #VALUE! | Y62: =AND(LOOKUP(A62, TreatmentRankings[Study], TreatmentRankings[StratumCount]) >= 2, J62 = LOOKUP(A62, TreatmentRankings[Study], TreatmentRankings[StratumCount]) * 2) -> #VALUE! | Z62: =IF(H62, "exempt-synthetic", IF(AND(Y62, LOOKUP(A62, StratumVariables[Study], StratumVariables[VariableName]) <> ""), "all", "partial")) -> #VALUE!
A63: collider-only-synthetic | B63: =A63 -> collider-only-synthetic | C63: Collider-Only Synthetic Control (Zero Confounding) | D63: Synthetic structural control for loop-58. Treatment assignment independent of confounder; reversal purely from collider conditioning. | F63: 2026 | G63: synthetic | H63: TRUE | I63: =SUMIFS(CaseCells!G2:G999,CaseCells!C2:C999, A63) -> 2000 | J63: =COUNTIFS(CaseCells!C2:C999, A63) -> 4 | K63: tradition-dag | L63: researcher-dong-cai-zhao | M63: =LOOKUP(K63, ResearchTraditions[TraditionId], ResearchTraditions[Name]) -> #VALUE! | N63: =LOOKUP(K63, ResearchTraditions[TraditionId], ResearchTraditions[CoreConcern]) -> #VALUE! | O63: =LOOKUP(L63, Researchers[ResearcherId], Researchers[Name]) -> #VALUE! | P63: =LOOKUP(L63, Researchers[ResearcherId], Researchers[Affiliation]) -> #VALUE! | Q63: =LOOKUP(A63, TreatmentRankings[Study], TreatmentRankings[DistortionType]) -> #VALUE! | R63: =LOOKUP(A63, TreatmentRankings[Study], TreatmentRankings[CorrectedPolicyImplication]) -> #VALUE! | S63: =LOOKUP(A63, TreatmentRankings[Study], TreatmentRankings[AllocationDistortion]) -> #VALUE! | T63: =LOOKUP(A63, TreatmentRankings[Study], TreatmentRankings[SignalPurity]) -> #VALUE! | U63: =LOOKUP(A63, TreatmentRankings[Study], TreatmentRankings[IsSignFlip]) -> #VALUE! | V63: =LOOKUP(A63, TreatmentRankings[Study], TreatmentRankings[CorrectedWinner]) -> #VALUE! | W63: =LOOKUP(A63, StratumVariables[Study], StratumVariables[VariableName]) -> #VALUE! | X63: =LOOKUP(A63, StratumVariables[Study], StratumVariables[CausalRole]) -> #VALUE! | Y63: =AND(LOOKUP(A63, TreatmentRankings[Study], TreatmentRankings[StratumCount]) >= 2, J63 = LOOKUP(A63, TreatmentRankings[Study], TreatmentRankings[StratumCount]) * 2) -> #VALUE! | Z63: =IF(H63, "exempt-synthetic", IF(AND(Y63, LOOKUP(A63, StratumVariables[Study], StratumVariables[VariableName]) <> ""), "all", "partial")) -> #VALUE!
A64: noncollapsibility-or-synthetic | B64: =A64 -> noncollapsibility-or-synthetic | C64: Non-Collapsibility OR Synthetic (Risk Difference Does Not Reverse) | D64: Synthetic structural control for loop-58. Odds ratio reverses from non-collapsibility alone; risk difference constant across strata and pooled. | F64: 2026 | G64: synthetic | H64: TRUE | I64: =SUMIFS(CaseCells!G2:G999,CaseCells!C2:C999, A64) -> 2200 | J64: =COUNTIFS(CaseCells!C2:C999, A64) -> 4 | K64: tradition-epidemiology | L64: researcher-greenland | M64: =LOOKUP(K64, ResearchTraditions[TraditionId], ResearchTraditions[Name]) -> #VALUE! | N64: =LOOKUP(K64, ResearchTraditions[TraditionId], ResearchTraditions[CoreConcern]) -> #VALUE! | O64: =LOOKUP(L64, Researchers[ResearcherId], Researchers[Name]) -> #VALUE! | P64: =LOOKUP(L64, Researchers[ResearcherId], Researchers[Affiliation]) -> #VALUE! | Q64: =LOOKUP(A64, TreatmentRankings[Study], TreatmentRankings[DistortionType]) -> #VALUE! | R64: =LOOKUP(A64, TreatmentRankings[Study], TreatmentRankings[CorrectedPolicyImplication]) -> #VALUE! | S64: =LOOKUP(A64, TreatmentRankings[Study], TreatmentRankings[AllocationDistortion]) -> #VALUE! | T64: =LOOKUP(A64, TreatmentRankings[Study], TreatmentRankings[SignalPurity]) -> #VALUE! | U64: =LOOKUP(A64, TreatmentRankings[Study], TreatmentRankings[IsSignFlip]) -> #VALUE! | V64: =LOOKUP(A64, TreatmentRankings[Study], TreatmentRankings[CorrectedWinner]) -> #VALUE! | W64: =LOOKUP(A64, StratumVariables[Study], StratumVariables[VariableName]) -> #VALUE! | X64: =LOOKUP(A64, StratumVariables[Study], StratumVariables[CausalRole]) -> #VALUE! | Y64: =AND(LOOKUP(A64, TreatmentRankings[Study], TreatmentRankings[StratumCount]) >= 2, J64 = LOOKUP(A64, TreatmentRankings[Study], TreatmentRankings[StratumCount]) * 2) -> #VALUE! | Z64: =IF(H64, "exempt-synthetic", IF(AND(Y64, LOOKUP(A64, StratumVariables[Study], StratumVariables[VariableName]) <> ""), "all", "partial")) -> #VALUE!
A65: trauma-center-mortality | B65: =A65 -> trauma-center-mortality | C65: Trauma Center vs Non-Trauma Center Mortality by Injury Severity | D65: Nathens AB et al. NEJM 2006. A=trauma center, B=non-trauma center, success=survival. Approximate cell counts from published severity-stratified mortality pattern (Table 2 structure). | E65: https://pubmed.ncbi.nlm.nih.gov/16687711/ | F65: 2006 | G65: medicine | H65: FALSE | I65: =SUMIFS(CaseCells!G2:G999,CaseCells!C2:C999, A65) -> 4000 | J65: =COUNTIFS(CaseCells!C2:C999, A65) -> 4 | K65: tradition-epidemiology | L65: researcher-robins | M65: =LOOKUP(K65, ResearchTraditions[TraditionId], ResearchTraditions[Name]) -> #VALUE! | N65: =LOOKUP(K65, ResearchTraditions[TraditionId], ResearchTraditions[CoreConcern]) -> #VALUE! | O65: =LOOKUP(L65, Researchers[ResearcherId], Researchers[Name]) -> #VALUE! | P65: =LOOKUP(L65, Researchers[ResearcherId], Researchers[Affiliation]) -> #VALUE! | Q65: =LOOKUP(A65, TreatmentRankings[Study], TreatmentRankings[DistortionType]) -> #VALUE! | R65: =LOOKUP(A65, TreatmentRankings[Study], TreatmentRankings[CorrectedPolicyImplication]) -> #VALUE! | S65: =LOOKUP(A65, TreatmentRankings[Study], TreatmentRankings[AllocationDistortion]) -> #VALUE! | T65: =LOOKUP(A65, TreatmentRankings[Study], TreatmentRankings[SignalPurity]) -> #VALUE! | U65: =LOOKUP(A65, TreatmentRankings[Study], TreatmentRankings[IsSignFlip]) -> #VALUE! | V65: =LOOKUP(A65, TreatmentRankings[Study], TreatmentRankings[CorrectedWinner]) -> #VALUE! | W65: =LOOKUP(A65, StratumVariables[Study], StratumVariables[VariableName]) -> #VALUE! | X65: =LOOKUP(A65, StratumVariables[Study], StratumVariables[CausalRole]) -> #VALUE! | Y65: =AND(LOOKUP(A65, TreatmentRankings[Study], TreatmentRankings[StratumCount]) >= 2, J65 = LOOKUP(A65, TreatmentRankings[Study], TreatmentRankings[StratumCount]) * 2) -> #VALUE! | Z65: =IF(H65, "exempt-synthetic", IF(AND(Y65, LOOKUP(A65, StratumVariables[Study], StratumVariables[VariableName]) <> ""), "all", "partial")) -> #VALUE!
A66: surgeon-volume-mortality | B66: =A66 -> surgeon-volume-mortality | C66: Surgeon Procedure Volume and Operative Mortality by Baseline Risk | D66: Birkmeyer JD et al. NEJM 2003. A=high-volume surgeon, B=low-volume, success=survival. Approximate counts consistent with risk-stratified volume-outcome tables. | E66: https://pubmed.ncbi.nlm.nih.gov/12531755/ | F66: 2003 | G66: medicine | H66: FALSE | I66: =SUMIFS(CaseCells!G2:G999,CaseCells!C2:C999, A66) -> 4000 | J66: =COUNTIFS(CaseCells!C2:C999, A66) -> 4 | K66: tradition-epidemiology | L66: researcher-robins | M66: =LOOKUP(K66, ResearchTraditions[TraditionId], ResearchTraditions[Name]) -> #VALUE! | N66: =LOOKUP(K66, ResearchTraditions[TraditionId], ResearchTraditions[CoreConcern]) -> #VALUE! | O66: =LOOKUP(L66, Researchers[ResearcherId], Researchers[Name]) -> #VALUE! | P66: =LOOKUP(L66, Researchers[ResearcherId], Researchers[Affiliation]) -> #VALUE! | Q66: =LOOKUP(A66, TreatmentRankings[Study], TreatmentRankings[DistortionType]) -> #VALUE! | R66: =LOOKUP(A66, TreatmentRankings[Study], TreatmentRankings[CorrectedPolicyImplication]) -> #VALUE! | S66: =LOOKUP(A66, TreatmentRankings[Study], TreatmentRankings[AllocationDistortion]) -> #VALUE! | T66: =LOOKUP(A66, TreatmentRankings[Study], TreatmentRankings[SignalPurity]) -> #VALUE! | U66: =LOOKUP(A66, TreatmentRankings[Study], TreatmentRankings[IsSignFlip]) -> #VALUE! | V66: =LOOKUP(A66, TreatmentRankings[Study], TreatmentRankings[CorrectedWinner]) -> #VALUE! | W66: =LOOKUP(A66, StratumVariables[Study], StratumVariables[VariableName]) -> #VALUE! | X66: =LOOKUP(A66, StratumVariables[Study], StratumVariables[CausalRole]) -> #VALUE! | Y66: =AND(LOOKUP(A66, TreatmentRankings[Study], TreatmentRankings[StratumCount]) >= 2, J66 = LOOKUP(A66, TreatmentRankings[Study], TreatmentRankings[StratumCount]) * 2) -> #VALUE! | Z66: =IF(H66, "exempt-synthetic", IF(AND(Y66, LOOKUP(A66, StratumVariables[Study], StratumVariables[VariableName]) <> ""), "all", "partial")) -> #VALUE!
